Workbook

Sheet Summary
A1: Fund Performance Overview
A3: Initial Capital | B3: =Assumptions!B4 -> 100000000
A4: Final Portfolio Value (30-Sep-2025) | B4: =Daily_Ledger!L93 -> 1.0168325e+08
A5: Total P&L | B5: =B4-B3 -> 1683253.7
A6: Risk Free Rate (Annual) | B6: =Assumptions!B5 -> 0.06
A7: Risk Free Rate (Daily) | B7: =B6/365 -> 0.00016438356
A8: Start Date | B8: =Assumptions!B7 -> 45839
A9: End Date | B9: =Assumptions!B8 -> 45930
A10: Project Days | B10: =B9-B8+1 -> 92
A12: Total Return (92 Days) | B12: =B5/B3 -> 0.016832537
A13: Annualized Return | B13: =B12*(365/B10) -> 0.066781261
A15: Benchmark Comparison
A17: Risk-Free Benchmark (Annual) | B17: =B6 -> 0.06
A18: Benchmark Return (92 Days) | B18: =(1+B17)^(B10/365)-1 -> 0.014795341
A19: Outperformance (Alpha) | B19: =B13-B17 -> 0.0067812614
A21: Strategy Rules
A23: Minimum Annualized Spread (Net) | B23: =Assumptions!B13 -> 0.0645
A24: Allocation per Trade (% of Cash) | B24: =Assumptions!B14 -> 0.45
A25: Max Allocation (% of Fund) | B25: =Assumptions!B15 -> 0.33
A26: Spot T-Cost | B26: =Assumptions!B16 -> 0.0005
A27: Futures T-Cost | B27: =Assumptions!B17 -> 0.0002
A28: Initial Margin (%) | B28: =Assumptions!B18 -> 0.2
A29: Cost of Carry (%) | B29: =Assumptions!B19 -> 0.005
A31: Asset Details
A33: Asset | B33: Lot Size
A34: RELIANCE | B34: =Assumptions!B24 -> 500
A35: ADANI | B35: =Assumptions!B25 -> 300
A37: Contract | B37: Expiry_Date
A38: JUL | B38: =Assumptions!B30 -> 45869
A39: AUG | B39: =Assumptions!B31 -> 45897
A40: SEP | B40: =Assumptions!B32 -> 45930
A42: Trade Statistics
A44: Total Arbitrage Trades Executed | B44: =COUNT(Trade_Log!A:A) -> 12
A45: Total Interest from Money Market | B45: =SUM(Daily_Ledger!H:H) -> 1199969.5
A46: Total P&L from Arbitrage Trades | B46: =B5-B45 -> 483284.17

Sheet Assumptions
A2: Fund Details
A4: Initial Capital | B4: 100000000
A5: Risk Free Rate (Annual) | B5: 0.06
A6: Risk Free Rate (Daily) | B6: =B5/365 -> 0.00016438356
A7: Start Date | B7: 45839
A8: End Date | B8: 45930
A9: Project Days | B9: =B8-B7+1 -> 92
A11: Strategy Rules
A13: Minimum Annualized Spread (Net) | B13: 0.0645
A14: Allocation per Trade (% of Cash) | B14: 0.45
A15: Max Allocation (% of Fund) | B15: 0.33
A16: Spot T-Cost | B16: 0.0005
A17: Futures T-Cost | B17: 0.0002
A18: Initial Margin (%) | B18: 0.2
A19: Cost of Carry (%) | B19: 0.005
A21: Asset Details
A23: Asset | B23: Lot Size
A24: RELIANCE | B24: 500
A25: ADANI | B25: 300
A27: Contract Details
A29: Contract | B29: Expiry_Date
A30: JUL | B30: 45869
A31: AUG | B31: 45897
A32: SEP | B32: 45930

Sheet Data Analysis
A1: Date | B1: Stock | C1: Spot_Price | D1: July_Futures_Price | E1: July_Expiry_Date | F1: Date To Expiry | G1: Fair Value | H1: Gross Spread | I1: Total_T-costs | J1: Net Profit | K1: Capital Blocked | L1: Net Return (%) | M1: Annualized_Return (%) | N1: TRADE_SIGNAL | P1: August_Futures_Price | Q1: August_Expiry_Date | R1: Date To Expiry | S1: Fair Value | T1: Gross Spread | U1: Total_T-costs | V1: Net Profit | W1: Capital Blocked | X1: Net Return (%) | Y1: Annualized_Return (%) | Z1: TRADE_SIGNAL | AB1: September_Futures_Price | AC1: September_Expiry_Date | AD1: Date To Expiry | AE1: Fair Value | AF1: Gross Spread | AG1: Total_T-costs | AH1: Net Profit | AI1: Capital Blocked | AJ1: Net Return (%) | AK1: Annualized_Return (%) | AL1: TRADE_SIGNAL
A2: 45839 | B2: RELIANCE | C2: =VLOOKUP(A2, Raw_Data_Reliance!A:N, 8, FALSE) -> 1528.4 | D2: =VLOOKUP(A2, Raw_Data_Reliance!O:AA, 8, FALSE) -> 1532.1 | E2: =Assumptions!$B$30 -> 45869 | F2: =E2-A2 -> 30 | G2: =C2*(1+(Assumptions!$B$19*F2/365)) -> 1529.0281 | H2: =D2-G2 -> 3.0718904 | I2: =(C2*Assumptions!$B$16)+(D2*Assumptions!$B$17) -> 1.07062 | J2: =H2-I2 -> 2.0012704 | K2: =C2+(D2*Assumptions!$B$15) -> 2033.993 | L2: =J2/K2 -> 0.00098391214 | M2: =L2*(365/F2) -> 0.011970931 | N2: =IF(AND(F2>0, M2 > Assumptions!$B$13), "ENTER", "DONT ENTER") -> DONT ENTER | P2: =VLOOKUP(A2, Raw_Data_Reliance!AB:AP, 8, FALSE) -> 1536.2 | Q2: =Assumptions!$B$31 -> 45897 | R2: =Q2-A2 -> 58 | S2: =C2*(1+(Assumptions!$B$19*R2/365)) -> 1529.6143 | T2: =P2-S2 -> 6.5856548 | U2: =(C2*Assumptions!$B$16)+(P2*Assumptions!$B$17) -> 1.07144 | V2: =T2-U2 -> 5.5142148 | W2: =C2+(P2*Assumptions!$B$15) -> 2035.346 | X2: =V2/W2 -> 0.0027092272 | Y2: =X2*(365/R2) -> 0.017049447 | Z2: =IF(AND(R2>0,Y2 > Assumptions!$B$13), "ENTER", "DONT ENTER") -> DONT ENTER | AB2: =VLOOKUP(A2, Raw_Data_Reliance!AQ:BE, 8, FALSE) -> 1544.4 | AC2: =Assumptions!$B$32 -> 45930 | AD2: =AC2-A2 -> 91 | AE2: =C2*(1+(Assumptions!$B$13*AD2/365)) -> 1552.9779 | AF2: =AB2-AE2 -> -8.5779282 | AG2: =(C2*Assumptions!$B$16)+(AB2*Assumptions!$B$17) -> 1.07308 | AH2: =AF2-AG2 -> -9.6510082 | AI2: =C2+(AB2*Assumptions!$B$15) -> 2038.052 | AJ2: =AH2/AI2 -> -0.0047354082 | AK2: =AJ2*(365/AD2) -> -0.01899367 | AL2: =IF(AND(AD2>0,AK2 > Assumptions!$B$13), "ENTER", "DONT ENTER") -> DONT ENTER
A3: 45840 | B3: RELIANCE | C3: =VLOOKUP(A3, Raw_Data_Reliance!A:N, 8, FALSE) -> 1518.8 | D3: =VLOOKUP(A3, Raw_Data_Reliance!O:AA, 8, FALSE) -> 1523.2 | E3: =Assumptions!$B$30 -> 45869 | F3: =E3-A3 -> 29 | G3: =C3*(1+(Assumptions!$B$19*F3/365)) -> 1519.4034 | H3: =D3-G3 -> 3.7966411 | I3: =(C3*Assumptions!$B$16)+(D3*Assumptions!$B$17) -> 1.06404 | J3: =H3-I3 -> 2.7326011 | K3: =C3+(D3*Assumptions!$B$15) -> 2021.456 | L3: =J3/K3 -> 0.0013517985 | M3: =L3*(365/F3) -> 0.017014015 | N3: =IF(AND(F3>0, M3 > Assumptions!$B$13), "ENTER", "DONT ENTER") -> DONT ENTER | P3: =VLOOKUP(A3, Raw_Data_Reliance!AB:AP, 8, FALSE) -> 1527 | Q3: =Assumptions!$B$31 -> 45897 | R3: =Q3-A3 -> 57 | S3: =C3*(1+(Assumptions!$B$19*R3/365)) -> 1519.9859 | T3: =P3-S3 -> 7.0140877 | U3: =(C3*Assumptions!$B$16)+(P3*Assumptions!$B$17) -> 1.0648 | V3: =T3-U3 -> 5.9492877 | W3: =C3+(P3*Assumptions!$B$15) -> 2022.71 | X3: =V3/W3 -> 0.002941246 | Y3: =X3*(365/R3) -> 0.018834294 | Z3: =IF(AND(R3>0,Y3 > Assumptions!$B$13), "ENTER", "DONT ENTER") -> DONT ENTER | AB3: =VLOOKUP(A3, Raw_Data_Reliance!AQ:BE, 8, FALSE) -> 1536 | AC3: =Assumptions!$B$32 -> 45930 | AD3: =AC3-A3 -> 90 | AE3: =C3*(1+(Assumptions!$B$13*AD3/365)) -> 1542.9552 | AF3: =AB3-AE3 -> -6.9551616 | AG3: =(C3*Assumptions!$B$16)+(AB3*Assumptions!$B$17) -> 1.0666 | AH3: =AF3-AG3 -> -8.0217616 | AI3: =C3+(AB3*Assumptions!$B$15) -> 2025.68 | AJ3: =AH3/AI3 -> -0.003960034 | AK3: =AJ3*(365/AD3) -> -0.016060138 | AL3: =IF(AND(AD3>0,AK3 > Assumptions!$B$13), "ENTER", "DONT ENTER") -> DONT ENTER
A4: 45841 | B4: RELIANCE | C4: =VLOOKUP(A4, Raw_Data_Reliance!A:N, 8, FALSE) -> 1517.8 | D4: =VLOOKUP(A4, Raw_Data_Reliance!O:AA, 8, FALSE) -> 1525.3 | E4: =Assumptions!$B$30 -> 45869 | F4: =E4-A4 -> 28 | G4: =C4*(1+(Assumptions!$B$19*F4/365)) -> 1518.3822 | H4: =D4-G4 -> 6.9178301 | I4: =(C4*Assumptions!$B$16)+(D4*Assumptions!$B$17) -> 1.06396 | J4: =H4-I4 -> 5.8538701 | K4: =C4+(D4*Assumptions!$B$15) -> 2021.149 | L4: =J4/K4 -> 0.0028963081 | M4: =L4*(365/F4) -> 0.037755444 | N4: =IF(AND(F4>0, M4 > Assumptions!$B$13), "ENTER", "DONT ENTER") -> DONT ENTER | P4: =VLOOKUP(A4, Raw_Data_Reliance!AB:AP, 8, FALSE) -> 1527.7 | Q4: =Assumptions!$B$31 -> 45897 | R4: =Q4-A4 -> 56 | S4: =C4*(1+(Assumptions!$B$19*R4/365)) -> 1518.9643 | T4: =P4-S4 -> 8.7356603 | U4: =(C4*Assumptions!$B$16)+(P4*Assumptions!$B$17) -> 1.06444 | V4: =T4-U4 -> 7.6712203 | W4: =C4+(P4*Assumptions!$B$15) -> 2021.941 | X4: =V4/W4 -> 0.0037939882 | Y4: =X4*(365/R4) -> 0.024728673 | Z4: =IF(AND(R4>0,Y4 > Assumptions!$B$13), "ENTER", "DONT ENTER") -> DONT ENTER | AB4: =VLOOKUP(A4, Raw_Data_Reliance!AQ:BE, 8, FALSE) -> 1537.8 | AC4: =Assumptions!$B$32 -> 45930 | AD4: =AC4-A4 -> 89 | AE4: =C4*(1+(Assumptions!$B$13*AD4/365)) -> 1541.671 | AF4: =AB4-AE4 -> -3.8710436 | AG4: =(C4*Assumptions!$B$16)+(AB4*Assumptions!$B$17) -> 1.06646 | AH4: =AF4-AG4 -> -4.9375036 | AI4: =C4+(AB4*Assumptions!$B$15) -> 2025.274 | AJ4: =AH4/AI4 -> -0.0024379435 | AK4: =AJ4*(365/AD4) -> -0.0099983076 | AL4: =IF(AND(AD4>0,AK4 > Assumptions!$B$13), "ENTER", "DONT ENTER") -> DONT ENTER
A5: 45842 | B5: RELIANCE | C5: =VLOOKUP(A5, Raw_Data_Reliance!A:N, 8, FALSE) -> 1527.3 | D5: =VLOOKUP(A5, Raw_Data_Reliance!O:AA, 8, FALSE) -> 1531.3 | E5: =Assumptions!$B$30 -> 45869 | F5: =E5-A5 -> 27 | G5: =C5*(1+(Assumptions!$B$19*F5/365)) -> 1527.8649 | H5: =D5-G5 -> 3.4351082 | I5: =(C5*Assumptions!$B$16)+(D5*Assumptions!$B$17) -> 1.06991 | J5: =H5-I5 -> 2.3651982 | K5: =C5+(D5*Assumptions!$B$15) -> 2032.629 | L5: =J5/K5 -> 0.0011636153 | M5: =L5*(365/F5) -> 0.015730355 | N5: =IF(AND(F5>0, M5 > Assumptions!$B$13), "ENTER", "DONT ENTER") -> DONT ENTER | P5: =VLOOKUP(A5, Raw_Data_Reliance!AB:AP, 8, FALSE) -> 1534.1 | Q5: =Assumptions!$B$31 -> 45897 | R5: =Q5-A5 -> 55 | S5: =C5*(1+(Assumptions!$B$19*R5/365)) -> 1528.4507 | T5: =P5-S5 -> 5.6492945 | U5: =(C5*Assumptions!$B$16)+(P5*Assumptions!$B$17) -> 1.07047 | V5: =T5-U5 -> 4.5788245 | W5: =C5+(P5*Assumptions!$B$15) -> 2033.553 | X5: =V5/W5 -> 0.0022516377 | Y5: =X5*(365/R5) -> 0.014942686 | Z5: =IF(AND(R5>0,Y5 > Assumptions!$B$13), "ENTER", "DONT ENTER") -> DONT ENTER | AB5: =VLOOKUP(A5, Raw_Data_Reliance!AQ:BE, 8, FALSE) -> 1543.3 | AC5: =Assumptions!$B$32 -> 45930 | AD5: =AC5-A5 -> 88 | AE5: =C5*(1+(Assumptions!$B$13*AD5/365)) -> 1551.0506 | AF5: =AB5-AE5 -> -7.7505611 | AG5: =(C5*Assumptions!$B$16)+(AB5*Assumptions!$B$17) -> 1.07231 | AH5: =AF5-AG5 -> -8.8228711 | AI5: =C5+(AB5*Assumptions!$B$15) -> 2036.589 | AJ5: =AH5/AI5 -> -0.0043321805 | AK5: =AJ5*(365/AD5) -> -0.017968703 | AL5: =IF(AND(AD5>0,AK5 > Assumptions!$B$13), "ENTER", "DONT ENTER") -> DONT ENTER
A6: 45843 | B6: RELIANCE | C6: =VLOOKUP(A6, Raw_Data_Reliance!A:N, 8, FALSE) -> #N/A | D6: =VLOOKUP(A6, Raw_Data_Reliance!O:AA, 8, FALSE) -> #N/A | E6: =Assumptions!$B$30 -> 45869 | F6: =E6-A6 -> 26 | G6: =C6*(1+(Assumptions!$B$19*F6/365)) -> #N/A | H6: =D6-G6 -> #N/A | I6: =(C6*Assumptions!$B$16)+(D6*Assumptions!$B$17) -> #N/A | J6: =H6-I6 -> #N/A | K6: =C6+(D6*Assumptions!$B$15) -> #N/A | L6: =J6/K6 -> #N/A | M6: =L6*(365/F6) -> #N/A | N6: =IF(AND(F6>0, M6 > Assumptions!$B$13), "ENTER", "DONT ENTER") -> #N/A | P6: =VLOOKUP(A6, Raw_Data_Reliance!AB:AP, 8, FALSE) -> #N/A | Q6: =Assumptions!$B$31 -> 45897 | R6: =Q6-A6 -> 54 | S6: =C6*(1+(Assumptions!$B$19*R6/365)) -> #N/A | T6: =P6-S6 -> #N/A | U6: =(C6*Assumptions!$B$16)+(P6*Assumptions!$B$17) -> #N/A | V6: =T6-U6 -> #N/A | W6: =C6+(P6*Assumptions!$B$15) -> #N/A | X6: =V6/W6 -> #N/A | Y6: =X6*(365/R6) -> #N/A | Z6: =IF(AND(R6>0,Y6 > Assumptions!$B$13), "ENTER", "DONT ENTER") -> #N/A | AB6: =VLOOKUP(A6, Raw_Data_Reliance!AQ:BE, 8, FALSE) -> #N/A | AC6: =Assumptions!$B$32 -> 45930 | AD6: =AC6-A6 -> 87 | AE6: =C6*(1+(Assumptions!$B$13*AD6/365)) -> #N/A | AF6: =AB6-AE6 -> #N/A | AG6: =(C6*Assumptions!$B$16)+(AB6*Assumptions!$B$17) -> #N/A | AH6: =AF6-AG6 -> #N/A | AI6: =C6+(AB6*Assumptions!$B$15) -> #N/A | AJ6: =AH6/AI6 -> #N/A | AK6: =AJ6*(365/AD6) -> #N/A | AL6: =IF(AND(AD6>0,AK6 > Assumptions!$B$13), "ENTER", "DONT ENTER") -> #N/A
A7: 45844 | B7: RELIANCE | C7: =VLOOKUP(A7, Raw_Data_Reliance!A:N, 8, FALSE) -> #N/A | D7: =VLOOKUP(A7, Raw_Data_Reliance!O:AA, 8, FALSE) -> #N/A | E7: =Assumptions!$B$30 -> 45869 | F7: =E7-A7 -> 25 | G7: =C7*(1+(Assumptions!$B$19*F7/365)) -> #N/A | H7: =D7-G7 -> #N/A | I7: =(C7*Assumptions!$B$16)+(D7*Assumptions!$B$17) -> #N/A | J7: =H7-I7 -> #N/A | K7: =C7+(D7*Assumptions!$B$15) -> #N/A | L7: =J7/K7 -> #N/A | M7: =L7*(365/F7) -> #N/A | N7: =IF(AND(F7>0, M7 > Assumptions!$B$13), "ENTER", "DONT ENTER") -> #N/A | P7: =VLOOKUP(A7, Raw_Data_Reliance!AB:AP, 8, FALSE) -> #N/A | Q7: =Assumptions!$B$31 -> 45897 | R7: =Q7-A7 -> 53 | S7: =C7*(1+(Assumptions!$B$19*R7/365)) -> #N/A | T7: =P7-S7 -> #N/A | U7: =(C7*Assumptions!$B$16)+(P7*Assumptions!$B$17) -> #N/A | V7: =T7-U7 -> #N/A | W7: =C7+(P7*Assumptions!$B$15) -> #N/A | X7: =V7/W7 -> #N/A | Y7: =X7*(365/R7) -> #N/A | Z7: =IF(AND(R7>0,Y7 > Assumptions!$B$13), "ENTER", "DONT ENTER") -> #N/A | AB7: =VLOOKUP(A7, Raw_Data_Reliance!AQ:BE, 8, FALSE) -> #N/A | AC7: =Assumptions!$B$32 -> 45930 | AD7: =AC7-A7 -> 86 | AE7: =C7*(1+(Assumptions!$B$13*AD7/365)) -> #N/A | AF7: =AB7-AE7 -> #N/A | AG7: =(C7*Assumptions!$B$16)+(AB7*Assumptions!$B$17) -> #N/A | AH7: =AF7-AG7 -> #N/A | AI7: =C7+(AB7*Assumptions!$B$15) -> #N/A | AJ7: =AH7/AI7 -> #N/A | AK7: =AJ7*(365/AD7) -> #N/A | AL7: =IF(AND(AD7>0,AK7 > Assumptions!$B$13), "ENTER", "DONT ENTER") -> #N/A
A8: 45845 | B8: RELIANCE | C8: =VLOOKUP(A8, Raw_Data_Reliance!A:N, 8, FALSE) -> 1541.5 | D8: =VLOOKUP(A8, Raw_Data_Reliance!O:AA, 8, FALSE) -> 1544.5 | E8: =Assumptions!$B$30 -> 45869 | F8: =E8-A8 -> 24 | G8: =C8*(1+(Assumptions!$B$19*F8/365)) -> 1542.0068 | H8: =D8-G8 -> 2.4932055 | I8: =(C8*Assumptions!$B$16)+(D8*Assumptions!$B$17) -> 1.07965 | J8: =H8-I8 -> 1.4135555 | K8: =C8+(D8*Assumptions!$B$15) -> 2051.185 | L8: =J8/K8 -> 0.0006891409 | M8: =L8*(365/F8) -> 0.010480685 | N8: =IF(AND(F8>0, M8 > Assumptions!$B$13), "ENTER", "DONT ENTER") -> DONT ENTER | P8: =VLOOKUP(A8, Raw_Data_Reliance!AB:AP, 8, FALSE) -> 1547.5 | Q8: =Assumptions!$B$31 -> 45897 | R8: =Q8-A8 -> 52 | S8: =C8*(1+(Assumptions!$B$19*R8/365)) -> 1542.5981 | T8: =P8-S8 -> 4.9019452 | U8: =(C8*Assumptions!$B$16)+(P8*Assumptions!$B$17) -> 1.08025 | V8: =T8-U8 -> 3.8216952 | W8: =C8+(P8*Assumptions!$B$15) -> 2052.175 | X8: =V8/W8 -> 0.0018622657 | Y8: =X8*(365/R8) -> 0.013071673 | Z8: =IF(AND(R8>0,Y8 > Assumptions!$B$13), "ENTER", "DONT ENTER") -> DONT ENTER | AB8: =VLOOKUP(A8, Raw_Data_Reliance!AQ:BE, 8, FALSE) -> 1555.6 | AC8: =Assumptions!$B$32 -> 45930 | AD8: =AC8-A8 -> 85 | AE8: =C8*(1+(Assumptions!$B$13*AD8/365)) -> 1564.6542 | AF8: =AB8-AE8 -> -9.0541747 | AG8: =(C8*Assumptions!$B$16)+(AB8*Assumptions!$B$17) -> 1.08187 | AH8: =AF8-AG8 -> -10.136045 | AI8: =C8+(AB8*Assumptions!$B$15) -> 2054.848 | AJ8: =AH8/AI8 -> -0.0049327467 | AK8: =AJ8*(365/AD8) -> -0.021181795 | AL8: =IF(AND(AD8>0,AK8 > Assumptions!$B$13), "ENTER", "DONT ENTER") -> DONT ENTER
A9: 45846 | B9: RELIANCE | C9: =VLOOKUP(A9, Raw_Data_Reliance!A:N, 8, FALSE) -> 1537.6 | D9: =VLOOKUP(A9, Raw_Data_Reliance!O:AA, 8, FALSE) -> 1545.1 | E9: =Assumptions!$B$30 -> 45869 | F9: =E9-A9 -> 23 | G9: =C9*(1+(Assumptions!$B$19*F9/365)) -> 1538.0844 | H9: =D9-G9 -> 7.0155507 | I9: =(C9*Assumptions!$B$16)+(D9*Assumptions!$B$17) -> 1.07782 | J9: =H9-I9 -> 5.9377307 | K9: =C9+(D9*Assumptions!$B$15) -> 2047.483 | L9: =J9/K9 -> 0.0029000146 | M9: =L9*(365/F9) -> 0.046021972 | N9: =IF(AND(F9>0, M9 > Assumptions!$B$13), "ENTER", "DONT ENTER") -> DONT ENTER | P9: =VLOOKUP(A9, Raw_Data_Reliance!AB:AP, 8, FALSE) -> 1547.6 | Q9: =Assumptions!$B$31 -> 45897 | R9: =Q9-A9 -> 51 | S9: =C9*(1+(Assumptions!$B$19*R9/365)) -> 1538.6742 | T9: =P9-S9 -> 8.9257863 | U9: =(C9*Assumptions!$B$16)+(P9*Assumptions!$B$17) -> 1.07832 | V9: =T9-U9 -> 7.8474663 | W9: =C9+(P9*Assumptions!$B$15) -> 2048.308 | X9: =V9/W9 -> 0.0038311945 | Y9: =X9*(365/R9) -> 0.027419333 | Z9: =IF(AND(R9>0,Y9 > Assumptions!$B$13), "ENTER", "DONT ENTER") -> DONT ENTER | AB9: =VLOOKUP(A9, Raw_Data_Reliance!AQ:BE, 8, FALSE) -> 1556.8 | AC9: =Assumptions!$B$32 -> 45930 | AD9: =AC9-A9 -> 84 | AE9: =C9*(1+(Assumptions!$B$13*AD9/365)) -> 1560.4239 | AF9: =AB9-AE9 -> -3.6238816 | AG9: =(C9*Assumptions!$B$16)+(AB9*Assumptions!$B$17) -> 1.08016 | AH9: =AF9-AG9 -> -4.7040416 | AI9: =C9+(AB9*Assumptions!$B$15) -> 2051.344 | AJ9: =AH9/AI9 -> -0.002293151 | AK9: =AJ9*(365/AD9) -> -0.0099642873 | AL9: =IF(AND(AD9>0,AK9 > Assumptions!$B$13), "ENTER", "DONT ENTER") -> DONT ENTER
A10: 45847 | B10: RELIANCE | C10: =VLOOKUP(A10, Raw_Data_Reliance!A:N, 8, FALSE) -> 1519 | D10: =VLOOKUP(A10, Raw_Data_Reliance!O:AA, 8, FALSE) -> 1524.6 | E10: =Assumptions!$B$30 -> 45869 | F10: =E10-A10 -> 22 | G10: =C10*(1+(Assumptions!$B$19*F10/365)) -> 1519.4578 | H10: =D10-G10 -> 5.1422192 | I10: =(C10*Assumptions!$B$16)+(D10*Assumptions!$B$17) -> 1.06442 | J10: =H10-I10 -> 4.0777992 | K10: =C10+(D10*Assumptions!$B$15) -> 2022.118 | L10: =J10/K10 -> 0.002016598 | M10: =L10*(365/F10) -> 0.033457195 | N10: =IF(AND(F10>0, M10 > Assumptions!$B$13), "ENTER", "DONT ENTER") -> DONT ENTER | P10: =VLOOKUP(A10, Raw_Data_Reliance!AB:AP, 8, FALSE) -> 1528.1 | Q10: =Assumptions!$B$31 -> 45897 | R10: =Q10-A10 -> 50 | S10: =C10*(1+(Assumptions!$B$19*R10/365)) -> 1520.0404 | T10: =P10-S10 -> 8.059589 | U10: =(C10*Assumptions!$B$16)+(P10*Assumptions!$B$17) -> 1.06512 | V10: =T10-U10 -> 6.994469 | W10: =C10+(P10*Assumptions!$B$15) -> 2023.273 | X10: =V10/W10 -> 0.0034570071 | Y10: =X10*(365/R10) -> 0.025236152 | Z10: =IF(AND(R10>0,Y10 > Assumptions!$B$13), "ENTER", "DONT ENTER") -> DONT ENTER | AB10: =VLOOKUP(A10, Raw_Data_Reliance!AQ:BE, 8, FALSE) -> 1538.1 | AC10: =Assumptions!$B$32 -> 45930 | AD10: =AC10-A10 -> 83 | AE10: =C10*(1+(Assumptions!$B$13*AD10/365)) -> 1541.2794 | AF10: =AB10-AE10 -> -3.1793603 | AG10: =(C10*Assumptions!$B$16)+(AB10*Assumptions!$B$17) -> 1.06712 | AH10: =AF10-AG10 -> -4.2464803 | AI10: =C10+(AB10*Assumptions!$B$15) -> 2026.573 | AJ10: =AH10/AI10 -> -0.0020953996 | AK10: =AJ10*(365/AD10) -> -0.0092147091 | AL10: =IF(AND(AD10>0,AK10 > Assumptions!$B$13), "ENTER", "DONT ENTER") -> DONT ENTER
A11: 45848 | B11: RELIANCE | C11: =VLOOKUP(A11, Raw_Data_Reliance!A:N, 8, FALSE) -> 1517.2 | D11: =VLOOKUP(A11, Raw_Data_Reliance!O:AA, 8, FALSE) -> 1519.7 | E11: =Assumptions!$B$30 -> 45869 | F11: =E11-A11 -> 21 | G11: =C11*(1+(Assumptions!$B$19*F11/365)) -> 1517.6365 | H11: =D11-G11 -> 2.0635452 | I11: =(C11*Assumptions!$B$16)+(D11*Assumptions!$B$17) -> 1.06254 | J11: =H11-I11 -> 1.0010052 | K11: =C11+(D11*Assumptions!$B$15) -> 2018.701 | L11: =J11/K11 -> 0.00049586601 | M11: =L11*(365/F11) -> 0.0086186235 | N11: =IF(AND(F11>0, M11 > Assumptions!$B$13), "ENTER", "DONT ENTER") -> DONT ENTER | P11: =VLOOKUP(A11, Raw_Data_Reliance!AB:AP, 8, FALSE) -> 1522.5 | Q11: =Assumptions!$B$31 -> 45897 | R11: =Q11-A11 -> 49 | S11: =C11*(1+(Assumptions!$B$19*R11/365)) -> 1518.2184 | T11: =P11-S11 -> 4.2816055 | U11: =(C11*Assumptions!$B$16)+(P11*Assumptions!$B$17) -> 1.0631 | V11: =T11-U11 -> 3.2185055 | W11: =C11+(P11*Assumptions!$B$15) -> 2019.625 | X11: =V11/W11 -> 0.0015936154 | Y11: =X11*(365/R11) -> 0.011870809 | Z11: =IF(AND(R11>0,Y11 > Assumptions!$B$13), "ENTER", "DONT ENTER") -> DONT ENTER | AB11: =VLOOKUP(A11, Raw_Data_Reliance!AQ:BE, 8, FALSE) -> 1532.1 | AC11: =Assumptions!$B$32 -> 45930 | AD11: =AC11-A11 -> 82 | AE11: =C11*(1+(Assumptions!$B$13*AD11/365)) -> 1539.1849 | AF11: =AB11-AE11 -> -7.0848515 | AG11: =(C11*Assumptions!$B$16)+(AB11*Assumptions!$B$17) -> 1.06502 | AH11: =AF11-AG11 -> -8.1498715 | AI11: =C11+(AB11*Assumptions!$B$15) -> 2022.793 | AJ11: =AH11/AI11 -> -0.004029019 | AK11: =AJ11*(365/AD11) -> -0.017934048 | AL11: =IF(AND(AD11>0,AK11 > Assumptions!$B$13), "ENTER", "DONT ENTER") -> DONT ENTER
A12: 45849 | B12: RELIANCE | C12: =VLOOKUP(A12, Raw_Data_Reliance!A:N, 8, FALSE) -> 1495.2 | D12: =VLOOKUP(A12, Raw_Data_Reliance!O:AA, 8, FALSE) -> 1500.7 | E12: =Assumptions!$B$30 -> 45869 | F12: =E12-A12 -> 20 | G12: =C12*(1+(Assumptions!$B$19*F12/365)) -> 1495.6096 | H12: =D12-G12 -> 5.0903562 | I12: =(C12*Assumptions!$B$16)+(D12*Assumptions!$B$17) -> 1.04774 | J12: =H12-I12 -> 4.0426162 | K12: =C12+(D12*Assumptions!$B$15) -> 1990.431 | L12: =J12/K12 -> 0.0020310255 | M12: =L12*(365/F12) -> 0.037066216 | N12: =IF(AND(F12>0, M12 > Assumptions!$B$13), "ENTER", "DONT ENTER") -> DONT ENTER | P12: =VLOOKUP(A12, Raw_Data_Reliance!AB:AP, 8, FALSE) -> 1503.3 | Q12: =Assumptions!$B$31 -> 45897 | R12: =Q12-A12 -> 48 | S12: =C12*(1+(Assumptions!$B$19*R12/365)) -> 1496.1831 | T12: =P12-S12 -> 7.1168548 | U12: =(C12*Assumptions!$B$16)+(P12*Assumptions!$B$17) -> 1.04826 | V12: =T12-U12 -> 6.0685948 | W12: =C12+(P12*Assumptions!$B$15) -> 1991.289 | X12: =V12/W12 -> 0.0030475711 | Y12: =X12*(365/R12) -> 0.023174239 | Z12: =IF(AND(R12>0,Y12 > Assumptions!$B$13), "ENTER", "DONT ENTER") -> DONT ENTER | AB12: =VLOOKUP(A12, Raw_Data_Reliance!AQ:BE, 8, FALSE) -> 1512.2 | AC12: =Assumptions!$B$32 -> 45930 | AD12: =AC12-A12 -> 81 | AE12: =C12*(1+(Assumptions!$B$13*AD12/365)) -> 1516.6018 | AF12: =AB12-AE12 -> -4.4018422 | AG12: =(C12*Assumptions!$B$16)+(AB12*Assumptions!$B$17) -> 1.05004 | AH12: =AF12-AG12 -> -5.4518822 | AI12: =C12+(AB12*Assumptions!$B$15) -> 1994.226 | AJ12: =AH12/AI12 -> -0.0027338337 | AK12: =AJ12*(365/AD12) -> -0.012319127 | AL12: =IF(AND(AD12>0,AK12 > Assumptions!$B$13), "ENTER", "DONT ENTER") -> DONT ENTER
A13: 45850 | B13: RELIANCE | C13: =VLOOKUP(A13, Raw_Data_Reliance!A:N, 8, FALSE) -> #N/A | D13: =VLOOKUP(A13, Raw_Data_Reliance!O:AA, 8, FALSE) -> #N/A | E13: =Assumptions!$B$30 -> 45869 | F13: =E13-A13 -> 19 | G13: =C13*(1+(Assumptions!$B$19*F13/365)) -> #N/A | H13: =D13-G13 -> #N/A | I13: =(C13*Assumptions!$B$16)+(D13*Assumptions!$B$17) -> #N/A | J13: =H13-I13 -> #N/A | K13: =C13+(D13*Assumptions!$B$15) -> #N/A | L13: =J13/K13 -> #N/A | M13: =L13*(365/F13) -> #N/A | N13: =IF(AND(F13>0, M13 > Assumptions!$B$13), "ENTER", "DONT ENTER") -> #N/A | P13: =VLOOKUP(A13, Raw_Data_Reliance!AB:AP, 8, FALSE) -> #N/A | Q13: =Assumptions!$B$31 -> 45897 | R13: =Q13-A13 -> 47 | S13: =C13*(1+(Assumptions!$B$19*R13/365)) -> #N/A | T13: =P13-S13 -> #N/A | U13: =(C13*Assumptions!$B$16)+(P13*Assumptions!$B$17) -> #N/A | V13: =T13-U13 -> #N/A | W13: =C13+(P13*Assumptions!$B$15) -> #N/A | X13: =V13/W13 -> #N/A | Y13: =X13*(365/R13) -> #N/A | Z13: =IF(AND(R13>0,Y13 > Assumptions!$B$13), "ENTER", "DONT ENTER") -> #N/A | AB13: =VLOOKUP(A13, Raw_Data_Reliance!AQ:BE, 8, FALSE) -> #N/A | AC13: =Assumptions!$B$32 -> 45930 | AD13: =AC13-A13 -> 80 | AE13: =C13*(1+(Assumptions!$B$13*AD13/365)) -> #N/A | AF13: =AB13-AE13 -> #N/A | AG13: =(C13*Assumptions!$B$16)+(AB13*Assumptions!$B$17) -> #N/A | AH13: =AF13-AG13 -> #N/A | AI13: =C13+(AB13*Assumptions!$B$15) -> #N/A | AJ13: =AH13/AI13 -> #N/A | AK13: =AJ13*(365/AD13) -> #N/A | AL13: =IF(AND(AD13>0,AK13 > Assumptions!$B$13), "ENTER", "DONT ENTER") -> #N/A
... A32: 45869 | B32: RELIANCE | C32: =VLOOKUP(A32, Raw_Data_Reliance!A:N, 8, FALSE) -> 1390.2 | D32: =VLOOKUP(A32, Raw_Data_Reliance!O:AA, 8, FALSE) -> 1390.2 | E32: =Assumptions!$B$30 -> 45869 | F32: =E32-A32 -> 0 | G32: =C32*(1+(Assumptions!$B$19*F32/365)) -> 1390.2 | H32: =D32-G32 -> 0 | I32: =(C32*Assumptions!$B$16)+(D32*Assumptions!$B$17) -> 0.97314 | J32: =H32-I32 -> -0.97314 | K32: =C32+(D32*Assumptions!$B$15) -> 1848.966 | L32: =J32/K32 -> -0.00052631579 | M32: =L32*(365/F32) -> #DIV/0! | N32: =IF(AND(F32>0, M32 > Assumptions!$B$13), "ENTER", "DONT ENTER") -> #DIV/0! | P32: =VLOOKUP(A32, Raw_Data_Reliance!AB:AP, 8, FALSE) -> 1393.9 | Q32: =Assumptions!$B$31 -> 45897 | R32: =Q32-A32 -> 28 | S32: =C32*(1+(Assumptions!$B$19*R32/365)) -> 1390.7332 | T32: =P32-S32 -> 3.1667726 | U32: =(C32*Assumptions!$B$16)+(P32*Assumptions!$B$17) -> 0.97388 | V32: =T32-U32 -> 2.1928926 | W32: =C32+(P32*Assumptions!$B$15) -> 1850.187 | X32: =V32/W32 -> 0.0011852275 | Y32: =X32*(365/R32) -> 0.015450288 | Z32: =IF(AND(R32>0,Y32 > Assumptions!$B$13), "ENTER", "DONT ENTER") -> DONT ENTER | AB32: =VLOOKUP(A32, Raw_Data_Reliance!AQ:BE, 8, FALSE) -> 1400.5 | AC32: =Assumptions!$B$32 -> 45930 | AD32: =AC32-A32 -> 61 | AE32: =C32*(1+(Assumptions!$B$13*AD32/365)) -> 1405.1856 | AF32: =AB32-AE32 -> -4.6855942 | AG32: =(C32*Assumptions!$B$16)+(AB32*Assumptions!$B$17) -> 0.9752 | AH32: =AF32-AG32 -> -5.6607942 | AI32: =C32+(AB32*Assumptions!$B$15) -> 1852.365 | AJ32: =AH32/AI32 -> -0.0030559821 | AK32: =AJ32*(365/AD32) -> -0.018285794 | AL32: =IF(AND(AD32>0,AK32 > Assumptions!$B$13), "ENTER", "DONT ENTER") -> DONT ENTER
A33: 45870 | B33: RELIANCE | C33: =VLOOKUP(A33, Raw_Data_Reliance!A:N, 8, FALSE) -> 1393.7 | P33: =VLOOKUP(A33, Raw_Data_Reliance!AB:AP, 8, FALSE) -> 1392.9 | Q33: =Assumptions!$B$31 -> 45897 | R33: =Q33-A33 -> 27 | S33: =C33*(1+(Assumptions!$B$19*R33/365)) -> 1394.2155 | T33: =P33-S33 -> -1.3154781 | U33: =(C33*Assumptions!$B$16)+(P33*Assumptions!$B$17) -> 0.97543 | V33: =T33-U33 -> -2.2909081 | W33: =C33+(P33*Assumptions!$B$15) -> 1853.357 | X33: =V33/W33 -> -0.0012360857 | Y33: =X33*(365/R33) -> -0.016710047 | Z33: =IF(AND(R33>0,Y33 > Assumptions!$B$13), "ENTER", "DONT ENTER") -> DONT ENTER | AB33: =VLOOKUP(A33, Raw_Data_Reliance!AQ:BE, 8, FALSE) -> 1400.6 | AC33: =Assumptions!$B$32 -> 45930 | AD33: =AC33-A33 -> 60 | AE33: =C33*(1+(Assumptions!$B$13*AD33/365)) -> 1408.477 | AF33: =AB33-AE33 -> -7.8770384 | AG33: =(C33*Assumptions!$B$16)+(AB33*Assumptions!$B$17) -> 0.97697 | AH33: =AF33-AG33 -> -8.8540084 | AI33: =C33+(AB33*Assumptions!$B$15) -> 1855.898 | AJ33: =AH33/AI33 -> -0.0047707408 | AK33: =AJ33*(365/AD33) -> -0.029022007 | AL33: =IF(AND(AD33>0,AK33 > Assumptions!$B$13), "ENTER", "DONT ENTER") -> DONT ENTER
A34: 45871 | B34: RELIANCE | C34: =VLOOKUP(A34, Raw_Data_Reliance!A:N, 8, FALSE) -> #N/A | P34: =VLOOKUP(A34, Raw_Data_Reliance!AB:AP, 8, FALSE) -> #N/A | Q34: =Assumptions!$B$31 -> 45897 | R34: =Q34-A34 -> 26 | S34: =C34*(1+(Assumptions!$B$19*R34/365)) -> #N/A | T34: =P34-S34 -> #N/A | U34: =(C34*Assumptions!$B$16)+(P34*Assumptions!$B$17) -> #N/A | V34: =T34-U34 -> #N/A | W34: =C34+(P34*Assumptions!$B$15) -> #N/A | X34: =V34/W34 -> #N/A | Y34: =X34*(365/R34) -> #N/A | Z34: =IF(AND(R34>0,Y34 > Assumptions!$B$13), "ENTER", "DONT ENTER") -> #N/A | AB34: =VLOOKUP(A34, Raw_Data_Reliance!AQ:BE, 8, FALSE) -> #N/A | AC34: =Assumptions!$B$32 -> 45930 | AD34: =AC34-A34 -> 59 | AE34: =C34*(1+(Assumptions!$B$13*AD34/365)) -> #N/A | AF34: =AB34-AE34 -> #N/A | AG34: =(C34*Assumptions!$B$16)+(AB34*Assumptions!$B$17) -> #N/A | AH34: =AF34-AG34 -> #N/A | AI34: =C34+(AB34*Assumptions!$B$15) -> #N/A | AJ34: =AH34/AI34 -> #N/A | AK34: =AJ34*(365/AD34) -> #N/A | AL34: =IF(AND(AD34>0,AK34 > Assumptions!$B$13), "ENTER", "DONT ENTER") -> #N/A
A35: 45872 | B35: RELIANCE | C35: =VLOOKUP(A35, Raw_Data_Reliance!A:N, 8, FALSE) -> #N/A | P35: =VLOOKUP(A35, Raw_Data_Reliance!AB:AP, 8, FALSE) -> #N/A | Q35: =Assumptions!$B$31 -> 45897 | R35: =Q35-A35 -> 25 | S35: =C35*(1+(Assumptions!$B$19*R35/365)) -> #N/A | T35: =P35-S35 -> #N/A | U35: =(C35*Assumptions!$B$16)+(P35*Assumptions!$B$17) -> #N/A | V35: =T35-U35 -> #N/A | W35: =C35+(P35*Assumptions!$B$15) -> #N/A | X35: =V35/W35 -> #N/A | Y35: =X35*(365/R35) -> #N/A | Z35: =IF(AND(R35>0,Y35 > Assumptions!$B$13), "ENTER", "DONT ENTER") -> #N/A | AB35: =VLOOKUP(A35, Raw_Data_Reliance!AQ:BE, 8, FALSE) -> #N/A | AC35: =Assumptions!$B$32 -> 45930 | AD35: =AC35-A35 -> 58 | AE35: =C35*(1+(Assumptions!$B$13*AD35/365)) -> #N/A | AF35: =AB35-AE35 -> #N/A | AG35: =(C35*Assumptions!$B$16)+(AB35*Assumptions!$B$17) -> #N/A | AH35: =AF35-AG35 -> #N/A | AI35: =C35+(AB35*Assumptions!$B$15) -> #N/A | AJ35: =AH35/AI35 -> #N/A | AK35: =AJ35*(365/AD35) -> #N/A | AL35: =IF(AND(AD35>0,AK35 > Assumptions!$B$13), "ENTER", "DONT ENTER") -> #N/A
A36: 45873 | B36: RELIANCE | C36: =VLOOKUP(A36, Raw_Data_Reliance!A:N, 8, FALSE) -> 1411.5 | P36: =VLOOKUP(A36, Raw_Data_Reliance!AB:AP, 8, FALSE) -> 1409.9 | Q36: =Assumptions!$B$31 -> 45897 | R36: =Q36-A36 -> 24 | S36: =C36*(1+(Assumptions!$B$19*R36/365)) -> 1411.9641 | T36: =P36-S36 -> -2.0640548 | U36: =(C36*Assumptions!$B$16)+(P36*Assumptions!$B$17) -> 0.98773 | V36: =T36-U36 -> -3.0517848 | W36: =C36+(P36*Assumptions!$B$15) -> 1876.767 | X36: =V36/W36 -> -0.0016260861 | Y36: =X36*(365/R36) -> -0.02473006 | Z36: =IF(AND(R36>0,Y36 > Assumptions!$B$13), "ENTER", "DONT ENTER") -> DONT ENTER | AB36: =VLOOKUP(A36, Raw_Data_Reliance!AQ:BE, 8, FALSE) -> 1417.5 | AC36: =Assumptions!$B$32 -> 45930 | AD36: =AC36-A36 -> 57 | AE36: =C36*(1+(Assumptions!$B$13*AD36/365)) -> 1425.7175 | AF36: =AB36-AE36 -> -8.2174788 | AG36: =(C36*Assumptions!$B$16)+(AB36*Assumptions!$B$17) -> 0.98925 | AH36: =AF36-AG36 -> -9.2067288 | AI36: =C36+(AB36*Assumptions!$B$15) -> 1879.275 | AJ36: =AH36/AI36 -> -0.0048990854 | AK36: =AJ36*(365/AD36) -> -0.031371337 | AL36: =IF(AND(AD36>0,AK36 > Assumptions!$B$13), "ENTER", "DONT ENTER") -> DONT ENTER
A37: 45874 | B37: RELIANCE | C37: =VLOOKUP(A37, Raw_Data_Reliance!A:N, 8, FALSE) -> 1391.7 | P37: =VLOOKUP(A37, Raw_Data_Reliance!AB:AP, 8, FALSE) -> 1389.9 | Q37: =Assumptions!$B$31 -> 45897 | R37: =Q37-A37 -> 23 | S37: =C37*(1+(Assumptions!$B$19*R37/365)) -> 1392.1385 | T37: =P37-S37 -> -2.2384808 | U37: =(C37*Assumptions!$B$16)+(P37*Assumptions!$B$17) -> 0.97383 | V37: =T37-U37 -> -3.2123108 | W37: =C37+(P37*Assumptions!$B$15) -> 1850.367 | X37: =V37/W37 -> -0.0017360398 | Y37: =X37*(365/R37) -> -0.027550197 | Z37: =IF(AND(R37>0,Y37 > Assumptions!$B$13), "ENTER", "DONT ENTER") -> DONT ENTER | AB37: =VLOOKUP(A37, Raw_Data_Reliance!AQ:BE, 8, FALSE) -> 1398.3 | AC37: =Assumptions!$B$32 -> 45930 | AD37: =AC37-A37 -> 56 | AE37: =C37*(1+(Assumptions!$B$13*AD37/365)) -> 1405.4721 | AF37: =AB37-AE37 -> -7.1721107 | AG37: =(C37*Assumptions!$B$16)+(AB37*Assumptions!$B$17) -> 0.97551 | AH37: =AF37-AG37 -> -8.1476207 | AI37: =C37+(AB37*Assumptions!$B$15) -> 1853.139 | AJ37: =AH37/AI37 -> -0.0043966592 | AK37: =AJ37*(365/AD37) -> -0.028656797 | AL37: =IF(AND(AD37>0,AK37 > Assumptions!$B$13), "ENTER", "DONT ENTER") -> DONT ENTER
A38: 45875 | B38: RELIANCE | C38: =VLOOKUP(A38, Raw_Data_Reliance!A:N, 8, FALSE) -> 1392.8 | P38: =VLOOKUP(A38, Raw_Data_Reliance!AB:AP, 8, FALSE) -> 1393.5 | Q38: =Assumptions!$B$31 -> 45897 | R38: =Q38-A38 -> 22 | S38: =C38*(1+(Assumptions!$B$19*R38/365)) -> 1393.2197 | T38: =P38-S38 -> 0.28025205 | U38: =(C38*Assumptions!$B$16)+(P38*Assumptions!$B$17) -> 0.9751 | V38: =T38-U38 -> -0.69484795 | W38: =C38+(P38*Assumptions!$B$15) -> 1852.655 | X38: =V38/W38 -> -0.00037505523 | Y38: =X38*(365/R38) -> -0.0062225072 | Z38: =IF(AND(R38>0,Y38 > Assumptions!$B$13), "ENTER", "DONT ENTER") -> DONT ENTER | AB38: =VLOOKUP(A38, Raw_Data_Reliance!AQ:BE, 8, FALSE) -> 1401.4 | AC38: =Assumptions!$B$32 -> 45930 | AD38: =AC38-A38 -> 55 | AE38: =C38*(1+(Assumptions!$B$13*AD38/365)) -> 1406.3369 | AF38: =AB38-AE38 -> -4.9368712 | AG38: =(C38*Assumptions!$B$16)+(AB38*Assumptions!$B$17) -> 0.97668 | AH38: =AF38-AG38 -> -5.9135512 | AI38: =C38+(AB38*Assumptions!$B$15) -> 1855.262 | AJ38: =AH38/AI38 -> -0.003187448 | AK38: =AJ38*(365/AD38) -> -0.021153064 | AL38: =IF(AND(AD38>0,AK38 > Assumptions!$B$13), "ENTER", "DONT ENTER") -> DONT ENTER
A39: 45876 | B39: RELIANCE | C39: =VLOOKUP(A39, Raw_Data_Reliance!A:N, 8, FALSE) -> 1389.4 | P39: =VLOOKUP(A39, Raw_Data_Reliance!AB:AP, 8, FALSE) -> 1390.6 | Q39: =Assumptions!$B$31 -> 45897 | R39: =Q39-A39 -> 21 | S39: =C39*(1+(Assumptions!$B$19*R39/365)) -> 1389.7997 | T39: =P39-S39 -> 0.80030959 | U39: =(C39*Assumptions!$B$16)+(P39*Assumptions!$B$17) -> 0.97282 | V39: =T39-U39 -> -0.17251041 | W39: =C39+(P39*Assumptions!$B$15) -> 1848.298 | X39: =V39/W39 -> -9.3334739e-05 | Y39: =X39*(365/R39) -> -0.0016222466 | Z39: =IF(AND(R39>0,Y39 > Assumptions!$B$13), "ENTER", "DONT ENTER") -> DONT ENTER | AB39: =VLOOKUP(A39, Raw_Data_Reliance!AQ:BE, 8, FALSE) -> 1398.3 | AC39: =Assumptions!$B$32 -> 45930 | AD39: =AC39-A39 -> 54 | AE39: =C39*(1+(Assumptions!$B$13*AD39/365)) -> 1402.6583 | AF39: =AB39-AE39 -> -4.3583019 | AG39: =(C39*Assumptions!$B$16)+(AB39*Assumptions!$B$17) -> 0.97436 | AH39: =AF39-AG39 -> -5.3326619 | AI39: =C39+(AB39*Assumptions!$B$15) -> 1850.839 | AJ39: =AH39/AI39 -> -0.0028812133 | AK39: =AJ39*(365/AD39) -> -0.019474868 | AL39: =IF(AND(AD39>0,AK39 > Assumptions!$B$13), "ENTER", "DONT ENTER") -> DONT ENTER
A40: 45877 | B40: RELIANCE | C40: =VLOOKUP(A40, Raw_Data_Reliance!A:N, 8, FALSE) -> 1367.8 | P40: =VLOOKUP(A40, Raw_Data_Reliance!AB:AP, 8, FALSE) -> 1368.3 | Q40: =Assumptions!$B$31 -> 45897 | R40: =Q40-A40 -> 20 | S40: =C40*(1+(Assumptions!$B$19*R40/365)) -> 1368.1747 | T40: =P40-S40 -> 0.12526027 | U40: =(C40*Assumptions!$B$16)+(P40*Assumptions!$B$17) -> 0.95756 | V40: =T40-U40 -> -0.83229973 | W40: =C40+(P40*Assumptions!$B$15) -> 1819.339 | X40: =V40/W40 -> -0.00045747369 | Y40: =X40*(365/R40) -> -0.0083488948 | Z40: =IF(AND(R40>0,Y40 > Assumptions!$B$13), "ENTER", "DONT ENTER") -> DONT ENTER | AB40: =VLOOKUP(A40, Raw_Data_Reliance!AQ:BE, 8, FALSE) -> 1376.1 | AC40: =Assumptions!$B$32 -> 45930 | AD40: =AC40-A40 -> 53 | AE40: =C40*(1+(Assumptions!$B$13*AD40/365)) -> 1380.6105 | AF40: =AB40-AE40 -> -4.5104775 | AG40: =(C40*Assumptions!$B$16)+(AB40*Assumptions!$B$17) -> 0.95912 | AH40: =AF40-AG40 -> -5.4695975 | AI40: =C40+(AB40*Assumptions!$B$15) -> 1821.913 | AJ40: =AH40/AI40 -> -0.0030021178 | AK40: =AJ40*(365/AD40) -> -0.020674963 | AL40: =IF(AND(AD40>0,AK40 > Assumptions!$B$13), "ENTER", "DONT ENTER") -> DONT ENTER
A41: 45878 | B41: RELIANCE | C41: =VLOOKUP(A41, Raw_Data_Reliance!A:N, 8, FALSE) -> #N/A | P41: =VLOOKUP(A41, Raw_Data_Reliance!AB:AP, 8, FALSE) -> #N/A | Q41: =Assumptions!$B$31 -> 45897 | R41: =Q41-A41 -> 19 | S41: =C41*(1+(Assumptions!$B$19*R41/365)) -> #N/A | T41: =P41-S41 -> #N/A | U41: =(C41*Assumptions!$B$16)+(P41*Assumptions!$B$17) -> #N/A | V41: =T41-U41 -> #N/A | W41: =C41+(P41*Assumptions!$B$15) -> #N/A | X41: =V41/W41 -> #N/A | Y41: =X41*(365/R41) -> #N/A | Z41: =IF(AND(R41>0,Y41 > Assumptions!$B$13), "ENTER", "DONT ENTER") -> #N/A | AB41: =VLOOKUP(A41, Raw_Data_Reliance!AQ:BE, 8, FALSE) -> #N/A | AC41: =Assumptions!$B$32 -> 45930 | AD41: =AC41-A41 -> 52 | AE41: =C41*(1+(Assumptions!$B$13*AD41/365)) -> #N/A | AF41: =AB41-AE41 -> #N/A | AG41: =(C41*Assumptions!$B$16)+(AB41*Assumptions!$B$17) -> #N/A | AH41: =AF41-AG41 -> #N/A | AI41: =C41+(AB41*Assumptions!$B$15) -> #N/A | AJ41: =AH41/AI41 -> #N/A | AK41: =AJ41*(365/AD41) -> #N/A | AL41: =IF(AND(AD41>0,AK41 > Assumptions!$B$13), "ENTER", "DONT ENTER") -> #N/A
A42: 45879 | B42: RELIANCE | C42: =VLOOKUP(A42, Raw_Data_Reliance!A:N, 8, FALSE) -> #N/A | P42: =VLOOKUP(A42, Raw_Data_Reliance!AB:AP, 8, FALSE) -> #N/A | Q42: =Assumptions!$B$31 -> 45897 | R42: =Q42-A42 -> 18 | S42: =C42*(1+(Assumptions!$B$19*R42/365)) -> #N/A | T42: =P42-S42 -> #N/A | U42: =(C42*Assumptions!$B$16)+(P42*Assumptions!$B$17) -> #N/A | V42: =T42-U42 -> #N/A | W42: =C42+(P42*Assumptions!$B$15) -> #N/A | X42: =V42/W42 -> #N/A | Y42: =X42*(365/R42) -> #N/A | Z42: =IF(AND(R42>0,Y42 > Assumptions!$B$13), "ENTER", "DONT ENTER") -> #N/A | AB42: =VLOOKUP(A42, Raw_Data_Reliance!AQ:BE, 8, FALSE) -> #N/A | AC42: =Assumptions!$B$32 -> 45930 | AD42: =AC42-A42 -> 51 | AE42: =C42*(1+(Assumptions!$B$13*AD42/365)) -> #N/A | AF42: =AB42-AE42 -> #N/A | AG42: =(C42*Assumptions!$B$16)+(AB42*Assumptions!$B$17) -> #N/A | AH42: =AF42-AG42 -> #N/A | AI42: =C42+(AB42*Assumptions!$B$15) -> #N/A | AJ42: =AH42/AI42 -> #N/A | AK42: =AJ42*(365/AD42) -> #N/A | AL42: =IF(AND(AD42>0,AK42 > Assumptions!$B$13), "ENTER", "DONT ENTER") -> #N/A
A43: 45880 | B43: RELIANCE | C43: =VLOOKUP(A43, Raw_Data_Reliance!A:N, 8, FALSE) -> 1386.2 | P43: =VLOOKUP(A43, Raw_Data_Reliance!AB:AP, 8, FALSE) -> 1383.1 | Q43: =Assumptions!$B$31 -> 45897 | R43: =Q43-A43 -> 17 | S43: =C43*(1+(Assumptions!$B$19*R43/365)) -> 1386.5228 | T43: =P43-S43 -> -3.4228137 | U43: =(C43*Assumptions!$B$16)+(P43*Assumptions!$B$17) -> 0.96972 | V43: =T43-U43 -> -4.3925337 | W43: =C43+(P43*Assumptions!$B$15) -> 1842.623 | X43: =V43/W43 -> -0.0023838483 | Y43: =X43*(365/R43) -> -0.051182625 | Z43: =IF(AND(R43>0,Y43 > Assumptions!$B$13), "ENTER", "DONT ENTER") -> DONT ENTER | AB43: =VLOOKUP(A43, Raw_Data_Reliance!AQ:BE, 8, FALSE) -> 1390.4 | AC43: =Assumptions!$B$32 -> 45930 | AD43: =AC43-A43 -> 50 | AE43: =C43*(1+(Assumptions!$B$13*AD43/365)) -> 1398.4479 | AF43: =AB43-AE43 -> -8.0479315 | AG43: =(C43*Assumptions!$B$16)+(AB43*Assumptions!$B$17) -> 0.97118 | AH43: =AF43-AG43 -> -9.0191115 | AI43: =C43+(AB43*Assumptions!$B$15) -> 1845.032 | AJ43: =AH43/AI43 -> -0.0048883225 | AK43: =AJ43*(365/AD43) -> -0.035684755 | AL43: =IF(AND(AD43>0,AK43 > Assumptions!$B$13), "ENTER", "DONT ENTER") -> DONT ENTER
A44: 45881 | B44: RELIANCE | C44: =VLOOKUP(A44, Raw_Data_Reliance!A:N, 8, FALSE) -> 1380.4 | P44: =VLOOKUP(A44, Raw_Data_Reliance!AB:AP, 8, FALSE) -> 1380 | Q44: =Assumptions!$B$31 -> 45897 | R44: =Q44-A44 -> 16 | S44: =C44*(1+(Assumptions!$B$19*R44/365)) -> 1380.7026 | T44: =P44-S44 -> -0.70255342 | U44: =(C44*Assumptions!$B$16)+(P44*Assumptions!$B$17) -> 0.9662 | V44: =T44-U44 -> -1.6687534 | W44: =C44+(P44*Assumptions!$B$15) -> 1835.8 | X44: =V44/W44 -> -0.00090900611 | Y44: =X44*(365/R44) -> -0.020736702 | Z44: =IF(AND(R44>0,Y44 > Assumptions!$B$13), "ENTER", "DONT ENTER") -> DONT ENTER | AB44: =VLOOKUP(A44, Raw_Data_Reliance!AQ:BE, 8, FALSE) -> 1387.8 | AC44: =Assumptions!$B$32 -> 45930 | AD44: =AC44-A44 -> 49 | AE44: =C44*(1+(Assumptions!$B$13*AD44/365)) -> 1392.3528 | AF44: =AB44-AE44 -> -4.5527512 | AG44: =(C44*Assumptions!$B$16)+(AB44*Assumptions!$B$17) -> 0.96776 | AH44: =AF44-AG44 -> -5.5205112 | AI44: =C44+(AB44*Assumptions!$B$15) -> 1838.374 | AJ44: =AH44/AI44 -> -0.0030029315 | AK44: =AJ44*(365/AD44) -> -0.022368776 | AL44: =IF(AND(AD44>0,AK44 > Assumptions!$B$13), "ENTER", "DONT ENTER") -> DONT ENTER
... A60: 45897 | B60: RELIANCE | C60: =VLOOKUP(A60, Raw_Data_Reliance!A:N, 8, FALSE) -> 1385.9 | P60: =VLOOKUP(A60, Raw_Data_Reliance!AB:AP, 8, FALSE) -> 1387.6 | Q60: =Assumptions!$B$31 -> 45897 | R60: =Q60-A60 -> 0 | S60: =C60*(1+(Assumptions!$B$19*R60/365)) -> 1385.9 | T60: =P60-S60 -> 1.7 | U60: =(C60*Assumptions!$B$16)+(P60*Assumptions!$B$17) -> 0.97047 | V60: =T60-U60 -> 0.72953 | W60: =C60+(P60*Assumptions!$B$15) -> 1843.808 | X60: =V60/W60 -> 0.00039566484 | Y60: =X60*(365/R60) -> #DIV/0! | Z60: =IF(AND(R60>0,Y60 > Assumptions!$B$13), "ENTER", "DONT ENTER") -> #DIV/0! | AB60: =VLOOKUP(A60, Raw_Data_Reliance!AQ:BE, 8, FALSE) -> 1395.4 | AC60: =Assumptions!$B$32 -> 45930 | AD60: =AC60-A60 -> 33 | AE60: =C60*(1+(Assumptions!$B$13*AD60/365)) -> 1393.9819 | AF60: =AB60-AE60 -> 1.4181147 | AG60: =(C60*Assumptions!$B$16)+(AB60*Assumptions!$B$17) -> 0.97203 | AH60: =AF60-AG60 -> 0.44608466 | AI60: =C60+(AB60*Assumptions!$B$15) -> 1846.382 | AJ60: =AH60/AI60 -> 0.00024159933 | AK60: =AJ60*(365/AD60) -> 0.002672235 | AL60: =IF(AND(AD60>0,AK60 > Assumptions!$B$13), "ENTER", "DONT ENTER") -> DONT ENTER
A61: 45898 | B61: RELIANCE | C61: =VLOOKUP(A61, Raw_Data_Reliance!A:N, 8, FALSE) -> 1357.2 | AB61: =VLOOKUP(A61, Raw_Data_Reliance!AQ:BE, 8, FALSE) -> 1364.4 | AC61: =Assumptions!$B$32 -> 45930 | AD61: =AC61-A61 -> 32 | AE61: =C61*(1+(Assumptions!$B$13*AD61/365)) -> 1364.8747 | AF61: =AB61-AE61 -> -0.47468712 | AG61: =(C61*Assumptions!$B$16)+(AB61*Assumptions!$B$17) -> 0.95148 | AH61: =AF61-AG61 -> -1.4261671 | AI61: =C61+(AB61*Assumptions!$B$15) -> 1807.452 | AJ61: =AH61/AI61 -> -0.00078904841 | AK61: =AJ61*(365/AD61) -> -0.0090000834 | AL61: =IF(AND(AD61>0,AK61 > Assumptions!$B$13), "ENTER", "DONT ENTER") -> DONT ENTER
A62: 45899 | B62: RELIANCE | C62: =VLOOKUP(A62, Raw_Data_Reliance!A:N, 8, FALSE) -> #N/A | AB62: =VLOOKUP(A62, Raw_Data_Reliance!AQ:BE, 8, FALSE) -> #N/A | AC62: =Assumptions!$B$32 -> 45930 | AD62: =AC62-A62 -> 31 | AE62: =C62*(1+(Assumptions!$B$13*AD62/365)) -> #N/A | AF62: =AB62-AE62 -> #N/A | AG62: =(C62*Assumptions!$B$16)+(AB62*Assumptions!$B$17) -> #N/A | AH62: =AF62-AG62 -> #N/A | AI62: =C62+(AB62*Assumptions!$B$15) -> #N/A | AJ62: =AH62/AI62 -> #N/A | AK62: =AJ62*(365/AD62) -> #N/A | AL62: =IF(AND(AD62>0,AK62 > Assumptions!$B$13), "ENTER", "DONT ENTER") -> #N/A
A63: 45900 | B63: RELIANCE | C63: =VLOOKUP(A63, Raw_Data_Reliance!A:N, 8, FALSE) -> #N/A | AB63: =VLOOKUP(A63, Raw_Data_Reliance!AQ:BE, 8, FALSE) -> #N/A | AC63: =Assumptions!$B$32 -> 45930 | AD63: =AC63-A63 -> 30 | AE63: =C63*(1+(Assumptions!$B$13*AD63/365)) -> #N/A | AF63: =AB63-AE63 -> #N/A | AG63: =(C63*Assumptions!$B$16)+(AB63*Assumptions!$B$17) -> #N/A | AH63: =AF63-AG63 -> #N/A | AI63: =C63+(AB63*Assumptions!$B$15) -> #N/A | AJ63: =AH63/AI63 -> #N/A | AK63: =AJ63*(365/AD63) -> #N/A | AL63: =IF(AND(AD63>0,AK63 > Assumptions!$B$13), "ENTER", "DONT ENTER") -> #N/A
A64: 45901 | B64: RELIANCE | C64: =VLOOKUP(A64, Raw_Data_Reliance!A:N, 8, FALSE) -> 1353.9 | AB64: =VLOOKUP(A64, Raw_Data_Reliance!AQ:BE, 8, FALSE) -> 1360.5 | AC64: =Assumptions!$B$32 -> 45930 | AD64: =AC64-A64 -> 29 | AE64: =C64*(1+(Assumptions!$B$13*AD64/365)) -> 1360.8383 | AF64: =AB64-AE64 -> -0.33827384 | AG64: =(C64*Assumptions!$B$16)+(AB64*Assumptions!$B$17) -> 0.94905 | AH64: =AF64-AG64 -> -1.2873238 | AI64: =C64+(AB64*Assumptions!$B$15) -> 1802.865 | AJ64: =AH64/AI64 -> -0.00071404339 | AK64: =AJ64*(365/AD64) -> -0.0089870978 | AL64: =IF(AND(AD64>0,AK64 > Assumptions!$B$13), "ENTER", "DONT ENTER") -> DONT ENTER
A65: 45902 | B65: RELIANCE | C65: =VLOOKUP(A65, Raw_Data_Reliance!A:N, 8, FALSE) -> 1366.5 | AB65: =VLOOKUP(A65, Raw_Data_Reliance!AQ:BE, 8, FALSE) -> 1372.6 | AC65: =Assumptions!$B$32 -> 45930 | AD65: =AC65-A65 -> 28 | AE65: =C65*(1+(Assumptions!$B$13*AD65/365)) -> 1373.2614 | AF65: =AB65-AE65 -> -0.66136712 | AG65: =(C65*Assumptions!$B$16)+(AB65*Assumptions!$B$17) -> 0.95777 | AH65: =AF65-AG65 -> -1.6191371 | AI65: =C65+(AB65*Assumptions!$B$15) -> 1819.458 | AJ65: =AH65/AI65 -> -0.0008899008 | AK65: =AJ65*(365/AD65) -> -0.011600493 | AL65: =IF(AND(AD65>0,AK65 > Assumptions!$B$13), "ENTER", "DONT ENTER") -> DONT ENTER
A66: 45903 | B66: RELIANCE | C66: =VLOOKUP(A66, Raw_Data_Reliance!A:N, 8, FALSE) -> 1372.6 | AB66: =VLOOKUP(A66, Raw_Data_Reliance!AQ:BE, 8, FALSE) -> 1377.2 | AC66: =Assumptions!$B$32 -> 45930 | AD66: =AC66-A66 -> 27 | AE66: =C66*(1+(Assumptions!$B$13*AD66/365)) -> 1379.149 | AF66: =AB66-AE66 -> -1.9489942 | AG66: =(C66*Assumptions!$B$16)+(AB66*Assumptions!$B$17) -> 0.96174 | AH66: =AF66-AG66 -> -2.9107342 | AI66: =C66+(AB66*Assumptions!$B$15) -> 1827.076 | AJ66: =AH66/AI66 -> -0.0015931107 | AK66: =AJ66*(365/AD66) -> -0.021536496 | AL66: =IF(AND(AD66>0,AK66 > Assumptions!$B$13), "ENTER", "DONT ENTER") -> DONT ENTER
A67: 45904 | B67: RELIANCE | C67: =VLOOKUP(A67, Raw_Data_Reliance!A:N, 8, FALSE) -> 1359.3 | AB67: =VLOOKUP(A67, Raw_Data_Reliance!AQ:BE, 8, FALSE) -> 1365.9 | AC67: =Assumptions!$B$32 -> 45930 | AD67: =AC67-A67 -> 26 | AE67: =C67*(1+(Assumptions!$B$13*AD67/365)) -> 1365.5453 | AF67: =AB67-AE67 -> 0.35466822 | AG67: =(C67*Assumptions!$B$16)+(AB67*Assumptions!$B$17) -> 0.95283 | AH67: =AF67-AG67 -> -0.59816178 | AI67: =C67+(AB67*Assumptions!$B$15) -> 1810.047 | AJ67: =AH67/AI67 -> -0.00033046754 | AK67: =AJ67*(365/AD67) -> -0.0046392559 | AL67: =IF(AND(AD67>0,AK67 > Assumptions!$B$13), "ENTER", "DONT ENTER") -> DONT ENTER
A68: 45905 | B68: RELIANCE | C68: =VLOOKUP(A68, Raw_Data_Reliance!A:N, 8, FALSE) -> 1375 | AB68: =VLOOKUP(A68, Raw_Data_Reliance!AQ:BE, 8, FALSE) -> 1378.6 | AC68: =Assumptions!$B$32 -> 45930 | AD68: =AC68-A68 -> 25 | AE68: =C68*(1+(Assumptions!$B$13*AD68/365)) -> 1381.0745 | AF68: =AB68-AE68 -> -2.4744863 | AG68: =(C68*Assumptions!$B$16)+(AB68*Assumptions!$B$17) -> 0.96322 | AH68: =AF68-AG68 -> -3.4377063 | AI68: =C68+(AB68*Assumptions!$B$15) -> 1829.938 | AJ68: =AH68/AI68 -> -0.0018785917 | AK68: =AJ68*(365/AD68) -> -0.027427439 | AL68: =IF(AND(AD68>0,AK68 > Assumptions!$B$13), "ENTER", "DONT ENTER") -> DONT ENTER
A69: 45906 | B69: RELIANCE | C69: =VLOOKUP(A69, Raw_Data_Reliance!A:N, 8, FALSE) -> #N/A | AB69: =VLOOKUP(A69, Raw_Data_Reliance!AQ:BE, 8, FALSE) -> #N/A | AC69: =Assumptions!$B$32 -> 45930 | AD69: =AC69-A69 -> 24 | AE69: =C69*(1+(Assumptions!$B$13*AD69/365)) -> #N/A | AF69: =AB69-AE69 -> #N/A | AG69: =(C69*Assumptions!$B$16)+(AB69*Assumptions!$B$17) -> #N/A | AH69: =AF69-AG69 -> #N/A | AI69: =C69+(AB69*Assumptions!$B$15) -> #N/A | AJ69: =AH69/AI69 -> #N/A | AK69: =AJ69*(365/AD69) -> #N/A | AL69: =IF(AND(AD69>0,AK69 > Assumptions!$B$13), "ENTER", "DONT ENTER") -> #N/A
A70: 45907 | B70: RELIANCE | C70: =VLOOKUP(A70, Raw_Data_Reliance!A:N, 8, FALSE) -> #N/A | AB70: =VLOOKUP(A70, Raw_Data_Reliance!AQ:BE, 8, FALSE) -> #N/A | AC70: =Assumptions!$B$32 -> 45930 | AD70: =AC70-A70 -> 23 | AE70: =C70*(1+(Assumptions!$B$13*AD70/365)) -> #N/A | AF70: =AB70-AE70 -> #N/A | AG70: =(C70*Assumptions!$B$16)+(AB70*Assumptions!$B$17) -> #N/A | AH70: =AF70-AG70 -> #N/A | AI70: =C70+(AB70*Assumptions!$B$15) -> #N/A | AJ70: =AH70/AI70 -> #N/A | AK70: =AJ70*(365/AD70) -> #N/A | AL70: =IF(AND(AD70>0,AK70 > Assumptions!$B$13), "ENTER", "DONT ENTER") -> #N/A
A71: 45908 | B71: RELIANCE | C71: =VLOOKUP(A71, Raw_Data_Reliance!A:N, 8, FALSE) -> 1378.5 | AB71: =VLOOKUP(A71, Raw_Data_Reliance!AQ:BE, 8, FALSE) -> 1382.3 | AC71: =Assumptions!$B$32 -> 45930 | AD71: =AC71-A71 -> 22 | AE71: =C71*(1+(Assumptions!$B$13*AD71/365)) -> 1383.8592 | AF71: =AB71-AE71 -> -1.5591548 | AG71: =(C71*Assumptions!$B$16)+(AB71*Assumptions!$B$17) -> 0.96571 | AH71: =AF71-AG71 -> -2.5248648 | AI71: =C71+(AB71*Assumptions!$B$15) -> 1834.659 | AJ71: =AH71/AI71 -> -0.0013762039 | AK71: =AJ71*(365/AD71) -> -0.022832473 | AL71: =IF(AND(AD71>0,AK71 > Assumptions!$B$13), "ENTER", "DONT ENTER") -> DONT ENTER
A72: 45909 | B72: RELIANCE | C72: =VLOOKUP(A72, Raw_Data_Reliance!A:N, 8, FALSE) -> 1376.2 | AB72: =VLOOKUP(A72, Raw_Data_Reliance!AQ:BE, 8, FALSE) -> 1380 | AC72: =Assumptions!$B$32 -> 45930 | AD72: =AC72-A72 -> 21 | AE72: =C72*(1+(Assumptions!$B$13*AD72/365)) -> 1381.307 | AF72: =AB72-AE72 -> -1.3070216 | AG72: =(C72*Assumptions!$B$16)+(AB72*Assumptions!$B$17) -> 0.9641 | AH72: =AF72-AG72 -> -2.2711216 | AI72: =C72+(AB72*Assumptions!$B$15) -> 1831.6 | AJ72: =AH72/AI72 -> -0.001239966 | AK72: =AJ72*(365/AD72) -> -0.021551789 | AL72: =IF(AND(AD72>0,AK72 > Assumptions!$B$13), "ENTER", "DONT ENTER") -> DONT ENTER
... A93: 45930 | B93: RELIANCE | C93: =VLOOKUP(A93, Raw_Data_Reliance!A:N, 8, FALSE) -> 1364 | AB93: =VLOOKUP(A93, Raw_Data_Reliance!AQ:BE, 8, FALSE) -> 1363.2 | AC93: =Assumptions!$B$32 -> 45930 | AD93: =AC93-A93 -> 0 | AE93: =C93*(1+(Assumptions!$B$13*AD93/365)) -> 1364 | AF93: =AB93-AE93 -> -0.8 | AG93: =(C93*Assumptions!$B$16)+(AB93*Assumptions!$B$17) -> 0.95464 | AH93: =AF93-AG93 -> -1.75464 | AI93: =C93+(AB93*Assumptions!$B$15) -> 1813.856 | AJ93: =AH93/AI93 -> -0.00096735353 | AK93: =AJ93*(365/AD93) -> #DIV/0! | AL93: =IF(AND(AD93>0,AK93 > Assumptions!$B$13), "ENTER", "DONT ENTER") -> #DIV/0!
A94: 45839 | B94: ADANI | C94: =VLOOKUP(A94, Raw_Data_Adani!A:N, 8, FALSE) -> 2621.8 | D94: =VLOOKUP(A94, Raw_Data_Adani!O:Y, 8, FALSE) -> 2631.7 | E94: =Assumptions!$B$30 -> 45869 | F94: =E94-A94 -> 30 | G94: =C94*(1+(Assumptions!$B$19*F94/365)) -> 2622.8775 | H94: =D94-G94 -> 8.8225479 | I94: =(C94*Assumptions!$B$16)+(D94*Assumptions!$B$17) -> 1.83724 | J94: =H94-I94 -> 6.9853079 | K94: =C94+(D94*Assumptions!$B$15) -> 3490.261 | L94: =J94/K94 -> 0.0020013712 | M94: =L94*(365/F94) -> 0.024350017 | N94: =IF(AND(F94>0, M94 > Assumptions!$B$13), "ENTER", "DONT ENTER") -> DONT ENTER | P94: =VLOOKUP(A94, Raw_Data_Adani!AB:AP, 8, FALSE) -> 2647 | Q94: =Assumptions!$B$31 -> 45897 | R94: =Q94-A94 -> 58 | S94: =C94*(1+(Assumptions!$B$19*R94/365)) -> 2623.8831 | T94: =P94-S94 -> 23.116926 | U94: =(C94*Assumptions!$B$16)+(P94*Assumptions!$B$17) -> 1.8403 | V94: =T94-U94 -> 21.276626 | W94: =C94+(P94*Assumptions!$B$15) -> 3495.31 | X94: =V94/W94 -> 0.0060871928 | Y94: =X94*(365/R94) -> 0.038307334 | Z94: =IF(AND(R94>0,Y94 > Assumptions!$B$13), "ENTER", "DONT ENTER") -> DONT ENTER | AB94: =VLOOKUP(A94, Raw_Data_Adani!AQ:BE, 8, FALSE) -> 2664.9 | AC94: =Assumptions!$B$32 -> 45930 | AD94: =AC94-A94 -> 91 | AE94: =C94*(1+(Assumptions!$B$13*AD94/365)) -> 2663.9607 | AF94: =AB94-AE94 -> 0.9393011 | AG94: =(C94*Assumptions!$B$16)+(AB94*Assumptions!$B$17) -> 1.84388 | AH94: =AF94-AG94 -> -0.9045789 | AI94: =C94+(AB94*Assumptions!$B$15) -> 3501.217 | AJ94: =AH94/AI94 -> -0.00025836128 | AK94: =AJ94*(365/AD94) -> -0.0010362843 | AL94: =IF(AND(AD94>0,AK94 > Assumptions!$B$13), "ENTER", "DONT ENTER") -> DONT ENTER
A95: 45840 | B95: ADANI | C95: =VLOOKUP(A95, Raw_Data_Adani!A:N, 8, FALSE) -> 2630.2 | D95: =VLOOKUP(A95, Raw_Data_Adani!O:Y, 8, FALSE) -> 2644.4 | E95: =Assumptions!$B$30 -> 45869 | F95: =E95-A95 -> 29 | G95: =C95*(1+(Assumptions!$B$19*F95/365)) -> 2631.2449 | H95: =D95-G95 -> 13.155126 | I95: =(C95*Assumptions!$B$16)+(D95*Assumptions!$B$17) -> 1.84398 | J95: =H95-I95 -> 11.311146 | K95: =C95+(D95*Assumptions!$B$15) -> 3502.852 | L95: =J95/K95 -> 0.0032291247 | M95: =L95*(365/F95) -> 0.040642432 | N95: =IF(AND(F95>0, M95 > Assumptions!$B$13), "ENTER", "DONT ENTER") -> DONT ENTER | P95: =VLOOKUP(A95, Raw_Data_Adani!AB:AP, 8, FALSE) -> 2658.9 | Q95: =Assumptions!$B$31 -> 45897 | R95: =Q95-A95 -> 57 | S95: =C95*(1+(Assumptions!$B$19*R95/365)) -> 2632.2537 | T95: =P95-S95 -> 26.646282 | U95: =(C95*Assumptions!$B$16)+(P95*Assumptions!$B$17) -> 1.84688 | V95: =T95-U95 -> 24.799402 | W95: =C95+(P95*Assumptions!$B$15) -> 3507.637 | X95: =V95/W95 -> 0.0070701165 | Y95: =X95*(365/R95) -> 0.045273553 | Z95: =IF(AND(R95>0,Y95 > Assumptions!$B$13), "ENTER", "DONT ENTER") -> DONT ENTER | AB95: =VLOOKUP(A95, Raw_Data_Adani!AQ:BE, 8, FALSE) -> 2673.4 | AC95: =Assumptions!$B$32 -> 45930 | AD95: =AC95-A95 -> 90 | AE95: =C95*(1+(Assumptions!$B$13*AD95/365)) -> 2672.031 | AF95: =AB95-AE95 -> 1.369011 | AG95: =(C95*Assumptions!$B$16)+(AB95*Assumptions!$B$17) -> 1.84978 | AH95: =AF95-AG95 -> -0.48076904 | AI95: =C95+(AB95*Assumptions!$B$15) -> 3512.422 | AJ95: =AH95/AI95 -> -0.00013687679 | AK95: =AJ95*(365/AD95) -> -0.00055511142 | AL95: =IF(AND(AD95>0,AK95 > Assumptions!$B$13), "ENTER", "DONT ENTER") -> DONT ENTER
A96: 45841 | B96: ADANI | C96: =VLOOKUP(A96, Raw_Data_Adani!A:N, 8, FALSE) -> 2611.2 | D96: =VLOOKUP(A96, Raw_Data_Adani!O:Y, 8, FALSE) -> 2626.6 | E96: =Assumptions!$B$30 -> 45869 | F96: =E96-A96 -> 28 | G96: =C96*(1+(Assumptions!$B$19*F96/365)) -> 2612.2016 | H96: =D96-G96 -> 14.398444 | I96: =(C96*Assumptions!$B$16)+(D96*Assumptions!$B$17) -> 1.83092 | J96: =H96-I96 -> 12.567524 | K96: =C96+(D96*Assumptions!$B$15) -> 3477.978 | L96: =J96/K96 -> 0.003613457 | M96: =L96*(365/F96) -> 0.047103993 | N96: =IF(AND(F96>0, M96 > Assumptions!$B$13), "ENTER", "DONT ENTER") -> DONT ENTER | P96: =VLOOKUP(A96, Raw_Data_Adani!AB:AP, 8, FALSE) -> 2640.1 | Q96: =Assumptions!$B$31 -> 45897 | R96: =Q96-A96 -> 56 | S96: =C96*(1+(Assumptions!$B$19*R96/365)) -> 2613.2031 | T96: =P96-S96 -> 26.896888 | U96: =(C96*Assumptions!$B$16)+(P96*Assumptions!$B$17) -> 1.83362 | V96: =T96-U96 -> 25.063268 | W96: =C96+(P96*Assumptions!$B$15) -> 3482.433 | X96: =V96/W96 -> 0.0071970567 | Y96: =X96*(365/R96) -> 0.046909387 | Z96: =IF(AND(R96>0,Y96 > Assumptions!$B$13), "ENTER", "DONT ENTER") -> DONT ENTER | AB96: =VLOOKUP(A96, Raw_Data_Adani!AQ:BE, 8, FALSE) -> 2668 | AC96: =Assumptions!$B$32 -> 45930 | AD96: =AC96-A96 -> 89 | AE96: =C96*(1+(Assumptions!$B$13*AD96/365)) -> 2652.2674 | AF96: =AB96-AE96 -> 15.73262 | AG96: =(C96*Assumptions!$B$16)+(AB96*Assumptions!$B$17) -> 1.8392 | AH96: =AF96-AG96 -> 13.89342 | AI96: =C96+(AB96*Assumptions!$B$15) -> 3491.64 | AJ96: =AH96/AI96 -> 0.0039790529 | AK96: =AJ96*(365/AD96) -> 0.016318588 | AL96: =IF(AND(AD96>0,AK96 > Assumptions!$B$13), "ENTER", "DONT ENTER") -> DONT ENTER
A97: 45842 | B97: ADANI | C97: =VLOOKUP(A97, Raw_Data_Adani!A:N, 8, FALSE) -> 2599.1 | D97: =VLOOKUP(A97, Raw_Data_Adani!O:Y, 8, FALSE) -> 2609.6 | E97: =Assumptions!$B$30 -> 45869 | F97: =E97-A97 -> 27 | G97: =C97*(1+(Assumptions!$B$19*F97/365)) -> 2600.0613 | H97: =D97-G97 -> 9.538689 | I97: =(C97*Assumptions!$B$16)+(D97*Assumptions!$B$17) -> 1.82147 | J97: =H97-I97 -> 7.717219 | K97: =C97+(D97*Assumptions!$B$15) -> 3460.268 | L97: =J97/K97 -> 0.0022302374 | M97: =L97*(365/F97) -> 0.030149505 | N97: =IF(AND(F97>0, M97 > Assumptions!$B$13), "ENTER", "DONT ENTER") -> DONT ENTER | P97: =VLOOKUP(A97, Raw_Data_Adani!AB:AP, 8, FALSE) -> 2622.9 | Q97: =Assumptions!$B$31 -> 45897 | R97: =Q97-A97 -> 55 | S97: =C97*(1+(Assumptions!$B$19*R97/365)) -> 2601.0582 | T97: =P97-S97 -> 21.841774 | U97: =(C97*Assumptions!$B$16)+(P97*Assumptions!$B$17) -> 1.82413 | V97: =T97-U97 -> 20.017644 | W97: =C97+(P97*Assumptions!$B$15) -> 3464.657 | X97: =V97/W97 -> 0.0057776698 | Y97: =X97*(365/R97) -> 0.038342717 | Z97: =IF(AND(R97>0,Y97 > Assumptions!$B$13), "ENTER", "DONT ENTER") -> DONT ENTER | AB97: =VLOOKUP(A97, Raw_Data_Adani!AQ:BE, 8, FALSE) -> 2638.5 | AC97: =Assumptions!$B$32 -> 45930 | AD97: =AC97-A97 -> 88 | AE97: =C97*(1+(Assumptions!$B$13*AD97/365)) -> 2639.5178 | AF97: =AB97-AE97 -> -1.0177852 | AG97: =(C97*Assumptions!$B$16)+(AB97*Assumptions!$B$17) -> 1.82725 | AH97: =AF97-AG97 -> -2.8450352 | AI97: =C97+(AB97*Assumptions!$B$15) -> 3469.805 | AJ97: =AH97/AI97 -> -0.00081994095 | AK97: =AJ97*(365/AD97) -> -0.0034008914 | AL97: =IF(AND(AD97>0,AK97 > Assumptions!$B$13), "ENTER", "DONT ENTER") -> DONT ENTER
A98: 45843 | B98: ADANI | C98: =VLOOKUP(A98, Raw_Data_Adani!A:N, 8, FALSE) -> #N/A | D98: =VLOOKUP(A98, Raw_Data_Adani!O:Y, 8, FALSE) -> #N/A | E98: =Assumptions!$B$30 -> 45869 | F98: =E98-A98 -> 26 | G98: =C98*(1+(Assumptions!$B$19*F98/365)) -> #N/A | H98: =D98-G98 -> #N/A | I98: =(C98*Assumptions!$B$16)+(D98*Assumptions!$B$17) -> #N/A | J98: =H98-I98 -> #N/A | K98: =C98+(D98*Assumptions!$B$15) -> #N/A | L98: =J98/K98 -> #N/A | M98: =L98*(365/F98) -> #N/A | N98: =IF(AND(F98>0, M98 > Assumptions!$B$13), "ENTER", "DONT ENTER") -> #N/A | P98: =VLOOKUP(A98, Raw_Data_Adani!AB:AP, 8, FALSE) -> #N/A | Q98: =Assumptions!$B$31 -> 45897 | R98: =Q98-A98 -> 54 | S98: =C98*(1+(Assumptions!$B$19*R98/365)) -> #N/A | T98: =P98-S98 -> #N/A | U98: =(C98*Assumptions!$B$16)+(P98*Assumptions!$B$17) -> #N/A | V98: =T98-U98 -> #N/A | W98: =C98+(P98*Assumptions!$B$15) -> #N/A | X98: =V98/W98 -> #N/A | Y98: =X98*(365/R98) -> #N/A | Z98: =IF(AND(R98>0,Y98 > Assumptions!$B$13), "ENTER", "DONT ENTER") -> #N/A | AB98: =VLOOKUP(A98, Raw_Data_Adani!AQ:BE, 8, FALSE) -> #N/A | AC98: =Assumptions!$B$32 -> 45930 | AD98: =AC98-A98 -> 87 | AE98: =C98*(1+(Assumptions!$B$13*AD98/365)) -> #N/A | AF98: =AB98-AE98 -> #N/A | AG98: =(C98*Assumptions!$B$16)+(AB98*Assumptions!$B$17) -> #N/A | AH98: =AF98-AG98 -> #N/A | AI98: =C98+(AB98*Assumptions!$B$15) -> #N/A | AJ98: =AH98/AI98 -> #N/A | AK98: =AJ98*(365/AD98) -> #N/A | AL98: =IF(AND(AD98>0,AK98 > Assumptions!$B$13), "ENTER", "DONT ENTER") -> #N/A
A99: 45844 | B99: ADANI | C99: =VLOOKUP(A99, Raw_Data_Adani!A:N, 8, FALSE) -> #N/A | D99: =VLOOKUP(A99, Raw_Data_Adani!O:Y, 8, FALSE) -> #N/A | E99: =Assumptions!$B$30 -> 45869 | F99: =E99-A99 -> 25 | G99: =C99*(1+(Assumptions!$B$19*F99/365)) -> #N/A | H99: =D99-G99 -> #N/A | I99: =(C99*Assumptions!$B$16)+(D99*Assumptions!$B$17) -> #N/A | J99: =H99-I99 -> #N/A | K99: =C99+(D99*Assumptions!$B$15) -> #N/A | L99: =J99/K99 -> #N/A | M99: =L99*(365/F99) -> #N/A | N99: =IF(AND(F99>0, M99 > Assumptions!$B$13), "ENTER", "DONT ENTER") -> #N/A | P99: =VLOOKUP(A99, Raw_Data_Adani!AB:AP, 8, FALSE) -> #N/A | Q99: =Assumptions!$B$31 -> 45897 | R99: =Q99-A99 -> 53 | S99: =C99*(1+(Assumptions!$B$19*R99/365)) -> #N/A | T99: =P99-S99 -> #N/A | U99: =(C99*Assumptions!$B$16)+(P99*Assumptions!$B$17) -> #N/A | V99: =T99-U99 -> #N/A | W99: =C99+(P99*Assumptions!$B$15) -> #N/A | X99: =V99/W99 -> #N/A | Y99: =X99*(365/R99) -> #N/A | Z99: =IF(AND(R99>0,Y99 > Assumptions!$B$13), "ENTER", "DONT ENTER") -> #N/A | AB99: =VLOOKUP(A99, Raw_Data_Adani!AQ:BE, 8, FALSE) -> #N/A | AC99: =Assumptions!$B$32 -> 45930 | AD99: =AC99-A99 -> 86 | AE99: =C99*(1+(Assumptions!$B$13*AD99/365)) -> #N/A | AF99: =AB99-AE99 -> #N/A | AG99: =(C99*Assumptions!$B$16)+(AB99*Assumptions!$B$17) -> #N/A | AH99: =AF99-AG99 -> #N/A | AI99: =C99+(AB99*Assumptions!$B$15) -> #N/A | AJ99: =AH99/AI99 -> #N/A | AK99: =AJ99*(365/AD99) -> #N/A | AL99: =IF(AND(AD99>0,AK99 > Assumptions!$B$13), "ENTER", "DONT ENTER") -> #N/A
A100: 45845 | B100: ADANI | C100: =VLOOKUP(A100, Raw_Data_Adani!A:N, 8, FALSE) -> 2576.1 | D100: =VLOOKUP(A100, Raw_Data_Adani!O:Y, 8, FALSE) -> 2588.9 | E100: =Assumptions!$B$30 -> 45869 | F100: =E100-A100 -> 24 | G100: =C100*(1+(Assumptions!$B$19*F100/365)) -> 2576.9469 | H100: =D100-G100 -> 11.953063 | I100: =(C100*Assumptions!$B$16)+(D100*Assumptions!$B$17) -> 1.80583 | J100: =H100-I100 -> 10.147233 | K100: =C100+(D100*Assumptions!$B$15) -> 3430.437 | L100: =J100/K100 -> 0.0029580001 | M100: =L100*(365/F100) -> 0.044986252 | N100: =IF(AND(F100>0, M100 > Assumptions!$B$13), "ENTER", "DONT ENTER") -> DONT ENTER | P100: =VLOOKUP(A100, Raw_Data_Adani!AB:AP, 8, FALSE) -> 2601.8 | Q100: =Assumptions!$B$31 -> 45897 | R100: =Q100-A100 -> 52 | S100: =C100*(1+(Assumptions!$B$19*R100/365)) -> 2577.935 | T100: =P100-S100 -> 23.86497 | U100: =(C100*Assumptions!$B$16)+(P100*Assumptions!$B$17) -> 1.80841 | V100: =T100-U100 -> 22.05656 | W100: =C100+(P100*Assumptions!$B$15) -> 3434.694 | X100: =V100/W100 -> 0.0064216958 | Y100: =X100*(365/R100) -> 0.045075364 | Z100: =IF(AND(R100>0,Y100 > Assumptions!$B$13), "ENTER", "DONT ENTER") -> DONT ENTER | AB100: =VLOOKUP(A100, Raw_Data_Adani!AQ:BE, 8, FALSE) -> 2617.4 | AC100: =Assumptions!$B$32 -> 45930 | AD100: =AC100-A100 -> 85 | AE100: =C100*(1+(Assumptions!$B$13*AD100/365)) -> 2614.7944 | AF100: =AB100-AE100 -> 2.6055664 | AG100: =(C100*Assumptions!$B$16)+(AB100*Assumptions!$B$17) -> 1.81153 | AH100: =AF100-AG100 -> 0.79403644 | AI100: =C100+(AB100*Assumptions!$B$15) -> 3439.842 | AJ100: =AH100/AI100 -> 0.00023083515 | AK100: =AJ100*(365/AD100) -> 0.00099123328 | AL100: =IF(AND(AD100>0,AK100 > Assumptions!$B$13), "ENTER", "DONT ENTER") -> DONT ENTER
A101: 45846 | B101: ADANI | C101: =VLOOKUP(A101, Raw_Data_Adani!A:N, 8, FALSE) -> 2591.3 | D101: =VLOOKUP(A101, Raw_Data_Adani!O:Y, 8, FALSE) -> 2605.1 | E101: =Assumptions!$B$30 -> 45869 | F101: =E101-A101 -> 23 | G101: =C101*(1+(Assumptions!$B$19*F101/365)) -> 2592.1164 | H101: =D101-G101 -> 12.983563 | I101: =(C101*Assumptions!$B$16)+(D101*Assumptions!$B$17) -> 1.81667 | J101: =H101-I101 -> 11.166893 | K101: =C101+(D101*Assumptions!$B$15) -> 3450.983 | L101: =J101/K101 -> 0.0032358586 | M101: =L101*(365/F101) -> 0.051351669 | N101: =IF(AND(F101>0, M101 > Assumptions!$B$13), "ENTER", "DONT ENTER") -> DONT ENTER | P101: =VLOOKUP(A101, Raw_Data_Adani!AB:AP, 8, FALSE) -> 2618.8 | Q101: =Assumptions!$B$31 -> 45897 | R101: =Q101-A101 -> 51 | S101: =C101*(1+(Assumptions!$B$19*R101/365)) -> 2593.1104 | T101: =P101-S101 -> 25.68964 | U101: =(C101*Assumptions!$B$16)+(P101*Assumptions!$B$17) -> 1.81941 | V101: =T101-U101 -> 23.87023 | W101: =C101+(P101*Assumptions!$B$15) -> 3455.504 | X101: =V101/W101 -> 0.0069078866 | Y101: =X101*(365/R101) -> 0.049438796 | Z101: =IF(AND(R101>0,Y101 > Assumptions!$B$13), "ENTER", "DONT ENTER") -> DONT ENTER | AB101: =VLOOKUP(A101, Raw_Data_Adani!AQ:BE, 8, FALSE) -> 2635.6 | AC101: =Assumptions!$B$32 -> 45930 | AD101: =AC101-A101 -> 84 | AE101: =C101*(1+(Assumptions!$B$13*AD101/365)) -> 2629.7648 | AF101: =AB101-AE101 -> 5.8351688 | AG101: =(C101*Assumptions!$B$16)+(AB101*Assumptions!$B$17) -> 1.82277 | AH101: =AF101-AG101 -> 4.0123988 | AI101: =C101+(AB101*Assumptions!$B$15) -> 3461.048 | AJ101: =AH101/AI101 -> 0.0011593017 | AK101: =AJ101*(365/AD101) -> 0.0050374418 | AL101: =IF(AND(AD101>0,AK101 > Assumptions!$B$13), "ENTER", "DONT ENTER") -> DONT ENTER
A102: 45847 | B102: ADANI | C102: =VLOOKUP(A102, Raw_Data_Adani!A:N, 8, FALSE) -> 2583 | D102: =VLOOKUP(A102, Raw_Data_Adani!O:Y, 8, FALSE) -> 2591.4 | E102: =Assumptions!$B$30 -> 45869 | F102: =E102-A102 -> 22 | G102: =C102*(1+(Assumptions!$B$19*F102/365)) -> 2583.7784 | H102: =D102-G102 -> 7.6215616 | I102: =(C102*Assumptions!$B$16)+(D102*Assumptions!$B$17) -> 1.80978 | J102: =H102-I102 -> 5.8117816 | K102: =C102+(D102*Assumptions!$B$15) -> 3438.162 | L102: =J102/K102 -> 0.0016903746 | M102: =L102*(365/F102) -> 0.028044851 | N102: =IF(AND(F102>0, M102 > Assumptions!$B$13), "ENTER", "DONT ENTER") -> DONT ENTER | P102: =VLOOKUP(A102, Raw_Data_Adani!AB:AP, 8, FALSE) -> 2604.7 | Q102: =Assumptions!$B$31 -> 45897 | R102: =Q102-A102 -> 50 | S102: =C102*(1+(Assumptions!$B$19*R102/365)) -> 2584.7692 | T102: =P102-S102 -> 19.930822 | U102: =(C102*Assumptions!$B$16)+(P102*Assumptions!$B$17) -> 1.81244 | V102: =T102-U102 -> 18.118382 | W102: =C102+(P102*Assumptions!$B$15) -> 3442.551 | X102: =V102/W102 -> 0.0052630686 | Y102: =X102*(365/R102) -> 0.0384204 | Z102: =IF(AND(R102>0,Y102 > Assumptions!$B$13), "ENTER", "DONT ENTER") -> DONT ENTER | AB102: =VLOOKUP(A102, Raw_Data_Adani!AQ:BE, 8, FALSE) -> 2616.3 | AC102: =Assumptions!$B$32 -> 45930 | AD102: =AC102-A102 -> 83 | AE102: =C102*(1+(Assumptions!$B$13*AD102/365)) -> 2620.8852 | AF102: =AB102-AE102 -> -4.5851795 | AG102: =(C102*Assumptions!$B$16)+(AB102*Assumptions!$B$17) -> 1.81476 | AH102: =AF102-AG102 -> -6.3999395 | AI102: =C102+(AB102*Assumptions!$B$15) -> 3446.379 | AJ102: =AH102/AI102 -> -0.001857004 | AK102: =AJ102*(365/AD102) -> -0.0081663427 | AL102: =IF(AND(AD102>0,AK102 > Assumptions!$B$13), "ENTER", "DONT ENTER") -> DONT ENTER
A103: 45848 | B103: ADANI | C103: =VLOOKUP(A103, Raw_Data_Adani!A:N, 8, FALSE) -> 2581 | D103: =VLOOKUP(A103, Raw_Data_Adani!O:Y, 8, FALSE) -> 2587.4 | E103: =Assumptions!$B$30 -> 45869 | F103: =E103-A103 -> 21 | G103: =C103*(1+(Assumptions!$B$19*F103/365)) -> 2581.7425 | H103: =D103-G103 -> 5.6575205 | I103: =(C103*Assumptions!$B$16)+(D103*Assumptions!$B$17) -> 1.80798 | J103: =H103-I103 -> 3.8495405 | K103: =C103+(D103*Assumptions!$B$15) -> 3434.842 | L103: =J103/K103 -> 0.0011207329 | M103: =L103*(365/F103) -> 0.019479406 | N103: =IF(AND(F103>0, M103 > Assumptions!$B$13), "ENTER", "DONT ENTER") -> DONT ENTER | P103: =VLOOKUP(A103, Raw_Data_Adani!AB:AP, 8, FALSE) -> 2601.4 | Q103: =Assumptions!$B$31 -> 45897 | R103: =Q103-A103 -> 49 | S103: =C103*(1+(Assumptions!$B$19*R103/365)) -> 2582.7325 | T103: =P103-S103 -> 18.667548 | U103: =(C103*Assumptions!$B$16)+(P103*Assumptions!$B$17) -> 1.81078 | V103: =T103-U103 -> 16.856768 | W103: =C103+(P103*Assumptions!$B$15) -> 3439.462 | X103: =V103/W103 -> 0.0049009897 | Y103: =X103*(365/R103) -> 0.036507372 | Z103: =IF(AND(R103>0,Y103 > Assumptions!$B$13), "ENTER", "DONT ENTER") -> DONT ENTER | AB103: =VLOOKUP(A103, Raw_Data_Adani!AQ:BE, 8, FALSE) -> 2622 | AC103: =Assumptions!$B$32 -> 45930 | AD103: =AC103-A103 -> 82 | AE103: =C103*(1+(Assumptions!$B$13*AD103/365)) -> 2618.3998 | AF103: =AB103-AE103 -> 3.6002493 | AG103: =(C103*Assumptions!$B$16)+(AB103*Assumptions!$B$17) -> 1.8149 | AH103: =AF103-AG103 -> 1.7853493 | AI103: =C103+(AB103*Assumptions!$B$15) -> 3446.26 | AJ103: =AH103/AI103 -> 0.00051805416 | AK103: =AJ103*(365/AD103) -> 0.0023059728 | AL103: =IF(AND(AD103>0,AK103 > Assumptions!$B$13), "ENTER", "DONT ENTER") -> DONT ENTER
A104: 45849 | B104: ADANI | C104: =VLOOKUP(A104, Raw_Data_Adani!A:N, 8, FALSE) -> 2558.7 | D104: =VLOOKUP(A104, Raw_Data_Adani!O:Y, 8, FALSE) -> 2569 | E104: =Assumptions!$B$30 -> 45869 | F104: =E104-A104 -> 20 | G104: =C104*(1+(Assumptions!$B$19*F104/365)) -> 2559.401 | H104: =D104-G104 -> 9.5989863 | I104: =(C104*Assumptions!$B$16)+(D104*Assumptions!$B$17) -> 1.79315 | J104: =H104-I104 -> 7.8058363 | K104: =C104+(D104*Assumptions!$B$15) -> 3406.47 | L104: =J104/K104 -> 0.0022914737 | M104: =L104*(365/F104) -> 0.041819394 | N104: =IF(AND(F104>0, M104 > Assumptions!$B$13), "ENTER", "DONT ENTER") -> DONT ENTER | P104: =VLOOKUP(A104, Raw_Data_Adani!AB:AP, 8, FALSE) -> 2580.2 | Q104: =Assumptions!$B$31 -> 45897 | R104: =Q104-A104 -> 48 | S104: =C104*(1+(Assumptions!$B$19*R104/365)) -> 2560.3824 | T104: =P104-S104 -> 19.817567 | U104: =(C104*Assumptions!$B$16)+(P104*Assumptions!$B$17) -> 1.79539 | V104: =T104-U104 -> 18.022177 | W104: =C104+(P104*Assumptions!$B$15) -> 3410.166 | X104: =V104/W104 -> 0.0052848387 | Y104: =X104*(365/R104) -> 0.040186794 | Z104: =IF(AND(R104>0,Y104 > Assumptions!$B$13), "ENTER", "DONT ENTER") -> DONT ENTER | AB104: =VLOOKUP(A104, Raw_Data_Adani!AQ:BE, 8, FALSE) -> 2601 | AC104: =Assumptions!$B$32 -> 45930 | AD104: =AC104-A104 -> 81 | AE104: =C104*(1+(Assumptions!$B$13*AD104/365)) -> 2595.3245 | AF104: =AB104-AE104 -> 5.6755393 | AG104: =(C104*Assumptions!$B$16)+(AB104*Assumptions!$B$17) -> 1.79955 | AH104: =AF104-AG104 -> 3.8759893 | AI104: =C104+(AB104*Assumptions!$B$15) -> 3417.03 | AJ104: =AH104/AI104 -> 0.0011343153 | AK104: =AJ104*(365/AD104) -> 0.0051114207 | AL104: =IF(AND(AD104>0,AK104 > Assumptions!$B$13), "ENTER", "DONT ENTER") -> DONT ENTER
A105: 45850 | B105: ADANI | C105: =VLOOKUP(A105, Raw_Data_Adani!A:N, 8, FALSE) -> #N/A | D105: =VLOOKUP(A105, Raw_Data_Adani!O:Y, 8, FALSE) -> #N/A | E105: =Assumptions!$B$30 -> 45869 | F105: =E105-A105 -> 19 | G105: =C105*(1+(Assumptions!$B$19*F105/365)) -> #N/A | H105: =D105-G105 -> #N/A | I105: =(C105*Assumptions!$B$16)+(D105*Assumptions!$B$17) -> #N/A | J105: =H105-I105 -> #N/A | K105: =C105+(D105*Assumptions!$B$15) -> #N/A | L105: =J105/K105 -> #N/A | M105: =L105*(365/F105) -> #N/A | N105: =IF(AND(F105>0, M105 > Assumptions!$B$13), "ENTER", "DONT ENTER") -> #N/A | P105: =VLOOKUP(A105, Raw_Data_Adani!AB:AP, 8, FALSE) -> #N/A | Q105: =Assumptions!$B$31 -> 45897 | R105: =Q105-A105 -> 47 | S105: =C105*(1+(Assumptions!$B$19*R105/365)) -> #N/A | T105: =P105-S105 -> #N/A | U105: =(C105*Assumptions!$B$16)+(P105*Assumptions!$B$17) -> #N/A | V105: =T105-U105 -> #N/A | W105: =C105+(P105*Assumptions!$B$15) -> #N/A | X105: =V105/W105 -> #N/A | Y105: =X105*(365/R105) -> #N/A | Z105: =IF(AND(R105>0,Y105 > Assumptions!$B$13), "ENTER", "DONT ENTER") -> #N/A | AB105: =VLOOKUP(A105, Raw_Data_Adani!AQ:BE, 8, FALSE) -> #N/A | AC105: =Assumptions!$B$32 -> 45930 | AD105: =AC105-A105 -> 80 | AE105: =C105*(1+(Assumptions!$B$13*AD105/365)) -> #N/A | AF105: =AB105-AE105 -> #N/A | AG105: =(C105*Assumptions!$B$16)+(AB105*Assumptions!$B$17) -> #N/A | AH105: =AF105-AG105 -> #N/A | AI105: =C105+(AB105*Assumptions!$B$15) -> #N/A | AJ105: =AH105/AI105 -> #N/A | AK105: =AJ105*(365/AD105) -> #N/A | AL105: =IF(AND(AD105>0,AK105 > Assumptions!$B$13), "ENTER", "DONT ENTER") -> #N/A
... A124: 45869 | B124: ADANI | C124: =VLOOKUP(A124, Raw_Data_Adani!A:N, 8, FALSE) -> 2430.7 | D124: =VLOOKUP(A124, Raw_Data_Adani!O:Y, 8, FALSE) -> 2430.7 | E124: =Assumptions!$B$30 -> 45869 | F124: =E124-A124 -> 0 | G124: =C124*(1+(Assumptions!$B$19*F124/365)) -> 2430.7 | H124: =D124-G124 -> 0 | I124: =(C124*Assumptions!$B$16)+(D124*Assumptions!$B$17) -> 1.70149 | J124: =H124-I124 -> -1.70149 | K124: =C124+(D124*Assumptions!$B$15) -> 3232.831 | L124: =J124/K124 -> -0.00052631579 | M124: =L124*(365/F124) -> #DIV/0! | N124: =IF(AND(F124>0, M124 > Assumptions!$B$13), "ENTER", "DONT ENTER") -> #DIV/0! | P124: =VLOOKUP(A124, Raw_Data_Adani!AB:AP, 8, FALSE) -> 2440.1 | Q124: =Assumptions!$B$31 -> 45897 | R124: =Q124-A124 -> 28 | S124: =C124*(1+(Assumptions!$B$19*R124/365)) -> 2431.6323 | T124: =P124-S124 -> 8.4676767 | U124: =(C124*Assumptions!$B$16)+(P124*Assumptions!$B$17) -> 1.70337 | V124: =T124-U124 -> 6.7643067 | W124: =C124+(P124*Assumptions!$B$15) -> 3235.933 | X124: =V124/W124 -> 0.0020903729 | Y124: =X124*(365/R124) -> 0.027249504 | Z124: =IF(AND(R124>0,Y124 > Assumptions!$B$13), "ENTER", "DONT ENTER") -> DONT ENTER | AB124: =VLOOKUP(A124, Raw_Data_Adani!AQ:BE, 8, FALSE) -> 2454.7 | AC124: =Assumptions!$B$32 -> 45930 | AD124: =AC124-A124 -> 61 | AE124: =C124*(1+(Assumptions!$B$13*AD124/365)) -> 2456.9016 | AF124: =AB124-AE124 -> -2.2016141 | AG124: =(C124*Assumptions!$B$16)+(AB124*Assumptions!$B$17) -> 1.70629 | AH124: =AF124-AG124 -> -3.9079041 | AI124: =C124+(AB124*Assumptions!$B$15) -> 3240.751 | AJ124: =AH124/AI124 -> -0.0012058637 | AK124: =AJ124*(365/AD124) -> -0.0072154142 | AL124: =IF(AND(AD124>0,AK124 > Assumptions!$B$13), "ENTER", "DONT ENTER") -> DONT ENTER
A125: 45870 | B125: ADANI | C125: =VLOOKUP(A125, Raw_Data_Adani!A:N, 8, FALSE) -> 2350.9 | P125: =VLOOKUP(A125, Raw_Data_Adani!AB:AP, 8, FALSE) -> 2356.4 | Q125: =Assumptions!$B$31 -> 45897 | R125: =Q125-A125 -> 27 | S125: =C125*(1+(Assumptions!$B$19*R125/365)) -> 2351.7695 | T125: =P125-S125 -> 4.630489 | U125: =(C125*Assumptions!$B$16)+(P125*Assumptions!$B$17) -> 1.64673 | V125: =T125-U125 -> 2.983759 | W125: =C125+(P125*Assumptions!$B$15) -> 3128.512 | X125: =V125/W125 -> 0.00095373105 | Y125: =X125*(365/R125) -> 0.012893031 | Z125: =IF(AND(R125>0,Y125 > Assumptions!$B$13), "ENTER", "DONT ENTER") -> DONT ENTER | AB125: =VLOOKUP(A125, Raw_Data_Adani!AQ:BE, 8, FALSE) -> 2369.2 | AC125: =Assumptions!$B$32 -> 45930 | AD125: =AC125-A125 -> 60 | AE125: =C125*(1+(Assumptions!$B$13*AD125/365)) -> 2375.826 | AF125: =AB125-AE125 -> -6.6259808 | AG125: =(C125*Assumptions!$B$16)+(AB125*Assumptions!$B$17) -> 1.64929 | AH125: =AF125-AG125 -> -8.2752708 | AI125: =C125+(AB125*Assumptions!$B$15) -> 3132.736 | AJ125: =AH125/AI125 -> -0.0026415475 | AK125: =AJ125*(365/AD125) -> -0.016069414 | AL125: =IF(AND(AD125>0,AK125 > Assumptions!$B$13), "ENTER", "DONT ENTER") -> DONT ENTER
A126: 45871 | B126: ADANI | C126: =VLOOKUP(A126, Raw_Data_Adani!A:N, 8, FALSE) -> #N/A | P126: =VLOOKUP(A126, Raw_Data_Adani!AB:AP, 8, FALSE) -> #N/A | Q126: =Assumptions!$B$31 -> 45897 | R126: =Q126-A126 -> 26 | S126: =C126*(1+(Assumptions!$B$19*R126/365)) -> #N/A | T126: =P126-S126 -> #N/A | U126: =(C126*Assumptions!$B$16)+(P126*Assumptions!$B$17) -> #N/A | V126: =T126-U126 -> #N/A | W126: =C126+(P126*Assumptions!$B$15) -> #N/A | X126: =V126/W126 -> #N/A | Y126: =X126*(365/R126) -> #N/A | Z126: =IF(AND(R126>0,Y126 > Assumptions!$B$13), "ENTER", "DONT ENTER") -> #N/A | AB126: =VLOOKUP(A126, Raw_Data_Adani!AQ:BE, 8, FALSE) -> #N/A | AC126: =Assumptions!$B$32 -> 45930 | AD126: =AC126-A126 -> 59 | AE126: =C126*(1+(Assumptions!$B$13*AD126/365)) -> #N/A | AF126: =AB126-AE126 -> #N/A | AG126: =(C126*Assumptions!$B$16)+(AB126*Assumptions!$B$17) -> #N/A | AH126: =AF126-AG126 -> #N/A | AI126: =C126+(AB126*Assumptions!$B$15) -> #N/A | AJ126: =AH126/AI126 -> #N/A | AK126: =AJ126*(365/AD126) -> #N/A | AL126: =IF(AND(AD126>0,AK126 > Assumptions!$B$13), "ENTER", "DONT ENTER") -> #N/A
A127: 45872 | B127: ADANI | C127: =VLOOKUP(A127, Raw_Data_Adani!A:N, 8, FALSE) -> #N/A | P127: =VLOOKUP(A127, Raw_Data_Adani!AB:AP, 8, FALSE) -> #N/A | Q127: =Assumptions!$B$31 -> 45897 | R127: =Q127-A127 -> 25 | S127: =C127*(1+(Assumptions!$B$19*R127/365)) -> #N/A | T127: =P127-S127 -> #N/A | U127: =(C127*Assumptions!$B$16)+(P127*Assumptions!$B$17) -> #N/A | V127: =T127-U127 -> #N/A | W127: =C127+(P127*Assumptions!$B$15) -> #N/A | X127: =V127/W127 -> #N/A | Y127: =X127*(365/R127) -> #N/A | Z127: =IF(AND(R127>0,Y127 > Assumptions!$B$13), "ENTER", "DONT ENTER") -> #N/A | AB127: =VLOOKUP(A127, Raw_Data_Adani!AQ:BE, 8, FALSE) -> #N/A | AC127: =Assumptions!$B$32 -> 45930 | AD127: =AC127-A127 -> 58 | AE127: =C127*(1+(Assumptions!$B$13*AD127/365)) -> #N/A | AF127: =AB127-AE127 -> #N/A | AG127: =(C127*Assumptions!$B$16)+(AB127*Assumptions!$B$17) -> #N/A | AH127: =AF127-AG127 -> #N/A | AI127: =C127+(AB127*Assumptions!$B$15) -> #N/A | AJ127: =AH127/AI127 -> #N/A | AK127: =AJ127*(365/AD127) -> #N/A | AL127: =IF(AND(AD127>0,AK127 > Assumptions!$B$13), "ENTER", "DONT ENTER") -> #N/A
A128: 45873 | B128: ADANI | C128: =VLOOKUP(A128, Raw_Data_Adani!A:N, 8, FALSE) -> 2363.6 | P128: =VLOOKUP(A128, Raw_Data_Adani!AB:AP, 8, FALSE) -> 2372.1 | Q128: =Assumptions!$B$31 -> 45897 | R128: =Q128-A128 -> 24 | S128: =C128*(1+(Assumptions!$B$19*R128/365)) -> 2364.3771 | T128: =P128-S128 -> 7.722926 | U128: =(C128*Assumptions!$B$16)+(P128*Assumptions!$B$17) -> 1.65622 | V128: =T128-U128 -> 6.066706 | W128: =C128+(P128*Assumptions!$B$15) -> 3146.393 | X128: =V128/W128 -> 0.0019281463 | Y128: =X128*(365/R128) -> 0.029323892 | Z128: =IF(AND(R128>0,Y128 > Assumptions!$B$13), "ENTER", "DONT ENTER") -> DONT ENTER | AB128: =VLOOKUP(A128, Raw_Data_Adani!AQ:BE, 8, FALSE) -> 2385.7 | AC128: =Assumptions!$B$32 -> 45930 | AD128: =AC128-A128 -> 57 | AE128: =C128*(1+(Assumptions!$B$13*AD128/365)) -> 2387.4076 | AF128: =AB128-AE128 -> -1.7076038 | AG128: =(C128*Assumptions!$B$16)+(AB128*Assumptions!$B$17) -> 1.65894 | AH128: =AF128-AG128 -> -3.3665438 | AI128: =C128+(AB128*Assumptions!$B$15) -> 3150.881 | AJ128: =AH128/AI128 -> -0.0010684452 | AK128: =AJ128*(365/AD128) -> -0.0068417985 | AL128: =IF(AND(AD128>0,AK128 > Assumptions!$B$13), "ENTER", "DONT ENTER") -> DONT ENTER
A129: 45874 | B129: ADANI | C129: =VLOOKUP(A129, Raw_Data_Adani!A:N, 8, FALSE) -> 2328.2 | P129: =VLOOKUP(A129, Raw_Data_Adani!AB:AP, 8, FALSE) -> 2333 | Q129: =Assumptions!$B$31 -> 45897 | R129: =Q129-A129 -> 23 | S129: =C129*(1+(Assumptions!$B$19*R129/365)) -> 2328.9335 | T129: =P129-S129 -> 4.0664575 | U129: =(C129*Assumptions!$B$16)+(P129*Assumptions!$B$17) -> 1.6307 | V129: =T129-U129 -> 2.4357575 | W129: =C129+(P129*Assumptions!$B$15) -> 3098.09 | X129: =V129/W129 -> 0.00078621265 | Y129: =X129*(365/R129) -> 0.012476853 | Z129: =IF(AND(R129>0,Y129 > Assumptions!$B$13), "ENTER", "DONT ENTER") -> DONT ENTER | AB129: =VLOOKUP(A129, Raw_Data_Adani!AQ:BE, 8, FALSE) -> 2350.2 | AC129: =Assumptions!$B$32 -> 45930 | AD129: =AC129-A129 -> 56 | AE129: =C129*(1+(Assumptions!$B$13*AD129/365)) -> 2351.2396 | AF129: =AB129-AE129 -> -1.0396121 | AG129: =(C129*Assumptions!$B$16)+(AB129*Assumptions!$B$17) -> 1.63414 | AH129: =AF129-AG129 -> -2.6737521 | AI129: =C129+(AB129*Assumptions!$B$15) -> 3103.766 | AJ129: =AH129/AI129 -> -0.00086145414 | AK129: =AJ129*(365/AD129) -> -0.005614835 | AL129: =IF(AND(AD129>0,AK129 > Assumptions!$B$13), "ENTER", "DONT ENTER") -> DONT ENTER
A130: 45875 | B130: ADANI | C130: =VLOOKUP(A130, Raw_Data_Adani!A:N, 8, FALSE) -> 2300.3 | P130: =VLOOKUP(A130, Raw_Data_Adani!AB:AP, 8, FALSE) -> 2304.6 | Q130: =Assumptions!$B$31 -> 45897 | R130: =Q130-A130 -> 22 | S130: =C130*(1+(Assumptions!$B$19*R130/365)) -> 2300.9932 | T130: =P130-S130 -> 3.6067589 | U130: =(C130*Assumptions!$B$16)+(P130*Assumptions!$B$17) -> 1.61107 | V130: =T130-U130 -> 1.9956889 | W130: =C130+(P130*Assumptions!$B$15) -> 3060.818 | X130: =V130/W130 -> 0.00065201162 | Y130: =X130*(365/R130) -> 0.010817466 | Z130: =IF(AND(R130>0,Y130 > Assumptions!$B$13), "ENTER", "DONT ENTER") -> DONT ENTER | AB130: =VLOOKUP(A130, Raw_Data_Adani!AQ:BE, 8, FALSE) -> 2318.3 | AC130: =Assumptions!$B$32 -> 45930 | AD130: =AC130-A130 -> 55 | AE130: =C130*(1+(Assumptions!$B$13*AD130/365)) -> 2322.657 | AF130: =AB130-AE130 -> -4.3570253 | AG130: =(C130*Assumptions!$B$16)+(AB130*Assumptions!$B$17) -> 1.61381 | AH130: =AF130-AG130 -> -5.9708353 | AI130: =C130+(AB130*Assumptions!$B$15) -> 3065.339 | AJ130: =AH130/AI130 -> -0.0019478548 | AK130: =AJ130*(365/AD130) -> -0.012926673 | AL130: =IF(AND(AD130>0,AK130 > Assumptions!$B$13), "ENTER", "DONT ENTER") -> DONT ENTER
A131: 45876 | B131: ADANI | C131: =VLOOKUP(A131, Raw_Data_Adani!A:N, 8, FALSE) -> 2249.8 | P131: =VLOOKUP(A131, Raw_Data_Adani!AB:AP, 8, FALSE) -> 2258.7 | Q131: =Assumptions!$B$31 -> 45897 | R131: =Q131-A131 -> 21 | S131: =C131*(1+(Assumptions!$B$19*R131/365)) -> 2250.4472 | T131: =P131-S131 -> 8.2527973 | U131: =(C131*Assumptions!$B$16)+(P131*Assumptions!$B$17) -> 1.57664 | V131: =T131-U131 -> 6.6761573 | W131: =C131+(P131*Assumptions!$B$15) -> 2995.171 | X131: =V131/W131 -> 0.0022289737 | Y131: =X131*(365/R131) -> 0.038741685 | Z131: =IF(AND(R131>0,Y131 > Assumptions!$B$13), "ENTER", "DONT ENTER") -> DONT ENTER | AB131: =VLOOKUP(A131, Raw_Data_Adani!AQ:BE, 8, FALSE) -> 2273.7 | AC131: =Assumptions!$B$32 -> 45930 | AD131: =AC131-A131 -> 54 | AE131: =C131*(1+(Assumptions!$B$13*AD131/365)) -> 2271.2686 | AF131: =AB131-AE131 -> 2.4313605 | AG131: =(C131*Assumptions!$B$16)+(AB131*Assumptions!$B$17) -> 1.57964 | AH131: =AF131-AG131 -> 0.85172055 | AI131: =C131+(AB131*Assumptions!$B$15) -> 3000.121 | AJ131: =AH131/AI131 -> 0.0002838954 | AK131: =AJ131*(365/AD131) -> 0.0019189226 | AL131: =IF(AND(AD131>0,AK131 > Assumptions!$B$13), "ENTER", "DONT ENTER") -> DONT ENTER
A132: 45877 | B132: ADANI | C132: =VLOOKUP(A132, Raw_Data_Adani!A:N, 8, FALSE) -> 2178.1 | P132: =VLOOKUP(A132, Raw_Data_Adani!AB:AP, 8, FALSE) -> 2181.7 | Q132: =Assumptions!$B$31 -> 45897 | R132: =Q132-A132 -> 20 | S132: =C132*(1+(Assumptions!$B$19*R132/365)) -> 2178.6967 | T132: =P132-S132 -> 3.0032603 | U132: =(C132*Assumptions!$B$16)+(P132*Assumptions!$B$17) -> 1.52539 | V132: =T132-U132 -> 1.4778703 | W132: =C132+(P132*Assumptions!$B$15) -> 2898.061 | X132: =V132/W132 -> 0.0005099514 | Y132: =X132*(365/R132) -> 0.0093066131 | Z132: =IF(AND(R132>0,Y132 > Assumptions!$B$13), "ENTER", "DONT ENTER") -> DONT ENTER | AB132: =VLOOKUP(A132, Raw_Data_Adani!AQ:BE, 8, FALSE) -> 2194.4 | AC132: =Assumptions!$B$32 -> 45930 | AD132: =AC132-A132 -> 53 | AE132: =C132*(1+(Assumptions!$B$13*AD132/365)) -> 2198.4995 | AF132: =AB132-AE132 -> -4.0995475 | AG132: =(C132*Assumptions!$B$16)+(AB132*Assumptions!$B$17) -> 1.52793 | AH132: =AF132-AG132 -> -5.6274775 | AI132: =C132+(AB132*Assumptions!$B$15) -> 2902.252 | AJ132: =AH132/AI132 -> -0.0019390038 | AK132: =AJ132*(365/AD132) -> -0.013353516 | AL132: =IF(AND(AD132>0,AK132 > Assumptions!$B$13), "ENTER", "DONT ENTER") -> DONT ENTER
A133: 45878 | B133: ADANI | C133: =VLOOKUP(A133, Raw_Data_Adani!A:N, 8, FALSE) -> #N/A | P133: =VLOOKUP(A133, Raw_Data_Adani!AB:AP, 8, FALSE) -> #N/A | Q133: =Assumptions!$B$31 -> 45897 | R133: =Q133-A133 -> 19 | S133: =C133*(1+(Assumptions!$B$19*R133/365)) -> #N/A | T133: =P133-S133 -> #N/A | U133: =(C133*Assumptions!$B$16)+(P133*Assumptions!$B$17) -> #N/A | V133: =T133-U133 -> #N/A | W133: =C133+(P133*Assumptions!$B$15) -> #N/A | X133: =V133/W133 -> #N/A | Y133: =X133*(365/R133) -> #N/A | Z133: =IF(AND(R133>0,Y133 > Assumptions!$B$13), "ENTER", "DONT ENTER") -> #N/A | AB133: =VLOOKUP(A133, Raw_Data_Adani!AQ:BE, 8, FALSE) -> #N/A | AC133: =Assumptions!$B$32 -> 45930 | AD133: =AC133-A133 -> 52 | AE133: =C133*(1+(Assumptions!$B$13*AD133/365)) -> #N/A | AF133: =AB133-AE133 -> #N/A | AG133: =(C133*Assumptions!$B$16)+(AB133*Assumptions!$B$17) -> #N/A | AH133: =AF133-AG133 -> #N/A | AI133: =C133+(AB133*Assumptions!$B$15) -> #N/A | AJ133: =AH133/AI133 -> #N/A | AK133: =AJ133*(365/AD133) -> #N/A | AL133: =IF(AND(AD133>0,AK133 > Assumptions!$B$13), "ENTER", "DONT ENTER") -> #N/A
A134: 45879 | B134: ADANI | C134: =VLOOKUP(A134, Raw_Data_Adani!A:N, 8, FALSE) -> #N/A | P134: =VLOOKUP(A134, Raw_Data_Adani!AB:AP, 8, FALSE) -> #N/A | Q134: =Assumptions!$B$31 -> 45897 | R134: =Q134-A134 -> 18 | S134: =C134*(1+(Assumptions!$B$19*R134/365)) -> #N/A | T134: =P134-S134 -> #N/A | U134: =(C134*Assumptions!$B$16)+(P134*Assumptions!$B$17) -> #N/A | V134: =T134-U134 -> #N/A | W134: =C134+(P134*Assumptions!$B$15) -> #N/A | X134: =V134/W134 -> #N/A | Y134: =X134*(365/R134) -> #N/A | Z134: =IF(AND(R134>0,Y134 > Assumptions!$B$13), "ENTER", "DONT ENTER") -> #N/A | AB134: =VLOOKUP(A134, Raw_Data_Adani!AQ:BE, 8, FALSE) -> #N/A | AC134: =Assumptions!$B$32 -> 45930 | AD134: =AC134-A134 -> 51 | AE134: =C134*(1+(Assumptions!$B$13*AD134/365)) -> #N/A | AF134: =AB134-AE134 -> #N/A | AG134: =(C134*Assumptions!$B$16)+(AB134*Assumptions!$B$17) -> #N/A | AH134: =AF134-AG134 -> #N/A | AI134: =C134+(AB134*Assumptions!$B$15) -> #N/A | AJ134: =AH134/AI134 -> #N/A | AK134: =AJ134*(365/AD134) -> #N/A | AL134: =IF(AND(AD134>0,AK134 > Assumptions!$B$13), "ENTER", "DONT ENTER") -> #N/A
A135: 45880 | B135: ADANI | C135: =VLOOKUP(A135, Raw_Data_Adani!A:N, 8, FALSE) -> 2283.4 | P135: =VLOOKUP(A135, Raw_Data_Adani!AB:AP, 8, FALSE) -> 2289.6 | Q135: =Assumptions!$B$31 -> 45897 | R135: =Q135-A135 -> 17 | S135: =C135*(1+(Assumptions!$B$19*R135/365)) -> 2283.9318 | T135: =P135-S135 -> 5.6682493 | U135: =(C135*Assumptions!$B$16)+(P135*Assumptions!$B$17) -> 1.59962 | V135: =T135-U135 -> 4.0686293 | W135: =C135+(P135*Assumptions!$B$15) -> 3038.968 | X135: =V135/W135 -> 0.0013388194 | Y135: =X135*(365/R135) -> 0.02874524 | Z135: =IF(AND(R135>0,Y135 > Assumptions!$B$13), "ENTER", "DONT ENTER") -> DONT ENTER | AB135: =VLOOKUP(A135, Raw_Data_Adani!AQ:BE, 8, FALSE) -> 2309.7 | AC135: =Assumptions!$B$32 -> 45930 | AD135: =AC135-A135 -> 50 | AE135: =C135*(1+(Assumptions!$B$13*AD135/365)) -> 2303.5752 | AF135: =AB135-AE135 -> 6.1247534 | AG135: =(C135*Assumptions!$B$16)+(AB135*Assumptions!$B$17) -> 1.60364 | AH135: =AF135-AG135 -> 4.5211134 | AI135: =C135+(AB135*Assumptions!$B$15) -> 3045.601 | AJ135: =AH135/AI135 -> 0.0014844733 | AK135: =AJ135*(365/AD135) -> 0.010836655 | AL135: =IF(AND(AD135>0,AK135 > Assumptions!$B$13), "ENTER", "DONT ENTER") -> DONT ENTER
A136: 45881 | B136: ADANI | C136: =VLOOKUP(A136, Raw_Data_Adani!A:N, 8, FALSE) -> 2288.2 | P136: =VLOOKUP(A136, Raw_Data_Adani!AB:AP, 8, FALSE) -> 2292.4 | Q136: =Assumptions!$B$31 -> 45897 | R136: =Q136-A136 -> 16 | S136: =C136*(1+(Assumptions!$B$19*R136/365)) -> 2288.7015 | T136: =P136-S136 -> 3.6984767 | U136: =(C136*Assumptions!$B$16)+(P136*Assumptions!$B$17) -> 1.60258 | V136: =T136-U136 -> 2.0958967 | W136: =C136+(P136*Assumptions!$B$15) -> 3044.692 | X136: =V136/W136 -> 0.00068837725 | Y136: =X136*(365/R136) -> 0.015703606 | Z136: =IF(AND(R136>0,Y136 > Assumptions!$B$13), "ENTER", "DONT ENTER") -> DONT ENTER | AB136: =VLOOKUP(A136, Raw_Data_Adani!AQ:BE, 8, FALSE) -> 2307.6 | AC136: =Assumptions!$B$32 -> 45930 | AD136: =AC136-A136 -> 49 | AE136: =C136*(1+(Assumptions!$B$13*AD136/365)) -> 2308.0133 | AF136: =AB136-AE136 -> -0.41330438 | AG136: =(C136*Assumptions!$B$16)+(AB136*Assumptions!$B$17) -> 1.60562 | AH136: =AF136-AG136 -> -2.0189244 | AI136: =C136+(AB136*Assumptions!$B$15) -> 3049.708 | AJ136: =AH136/AI136 -> -0.0006620058 | AK136: =AJ136*(365/AD136) -> -0.0049312677 | AL136: =IF(AND(AD136>0,AK136 > Assumptions!$B$13), "ENTER", "DONT ENTER") -> DONT ENTER
... A152: 45897 | B152: ADANI | C152: =VLOOKUP(A152, Raw_Data_Adani!A:N, 8, FALSE) -> 2275.2 | P152: =VLOOKUP(A152, Raw_Data_Adani!AB:AP, 8, FALSE) -> 2273.4 | Q152: =Assumptions!$B$31 -> 45897 | R152: =Q152-A152 -> 0 | S152: =C152*(1+(Assumptions!$B$19*R152/365)) -> 2275.2 | T152: =P152-S152 -> -1.8 | U152: =(C152*Assumptions!$B$16)+(P152*Assumptions!$B$17) -> 1.59228 | V152: =T152-U152 -> -3.39228 | W152: =C152+(P152*Assumptions!$B$15) -> 3025.422 | X152: =V152/W152 -> -0.0011212585 | Y152: =X152*(365/R152) -> #DIV/0! | Z152: =IF(AND(R152>0,Y152 > Assumptions!$B$13), "ENTER", "DONT ENTER") -> #DIV/0! | AB152: =VLOOKUP(A152, Raw_Data_Adani!AQ:BE, 8, FALSE) -> 2287.1 | AC152: =Assumptions!$B$32 -> 45930 | AD152: =AC152-A152 -> 33 | AE152: =C152*(1+(Assumptions!$B$13*AD152/365)) -> 2288.4678 | AF152: =AB152-AE152 -> -1.3678444 | AG152: =(C152*Assumptions!$B$16)+(AB152*Assumptions!$B$17) -> 1.59502 | AH152: =AF152-AG152 -> -2.9628644 | AI152: =C152+(AB152*Assumptions!$B$15) -> 3029.943 | AJ152: =AH152/AI152 -> -0.00097786143 | AK152: =AJ152*(365/AD152) -> -0.01081574 | AL152: =IF(AND(AD152>0,AK152 > Assumptions!$B$13), "ENTER", "DONT ENTER") -> DONT ENTER
A153: 45898 | B153: ADANI | C153: =VLOOKUP(A153, Raw_Data_Adani!A:N, 8, FALSE) -> 2244.7 | AB153: =VLOOKUP(A153, Raw_Data_Adani!AQ:BE, 8, FALSE) -> 2259.3 | AC153: =Assumptions!$B$32 -> 45930 | AD153: =AC153-A153 -> 32 | AE153: =C153*(1+(Assumptions!$B$13*AD153/365)) -> 2257.3933 | AF153: =AB153-AE153 -> 1.9066827 | AG153: =(C153*Assumptions!$B$16)+(AB153*Assumptions!$B$17) -> 1.57421 | AH153: =AF153-AG153 -> 0.33247274 | AI153: =C153+(AB153*Assumptions!$B$15) -> 2990.269 | AJ153: =AH153/AI153 -> 0.00011118489 | AK153: =AJ153*(365/AD153) -> 0.0012682027 | AL153: =IF(AND(AD153>0,AK153 > Assumptions!$B$13), "ENTER", "DONT ENTER") -> DONT ENTER
A154: 45899 | B154: ADANI | C154: =VLOOKUP(A154, Raw_Data_Adani!A:N, 8, FALSE) -> #N/A | AB154: =VLOOKUP(A154, Raw_Data_Adani!AQ:BE, 8, FALSE) -> #N/A | AC154: =Assumptions!$B$32 -> 45930 | AD154: =AC154-A154 -> 31 | AE154: =C154*(1+(Assumptions!$B$13*AD154/365)) -> #N/A | AF154: =AB154-AE154 -> #N/A | AG154: =(C154*Assumptions!$B$16)+(AB154*Assumptions!$B$17) -> #N/A | AH154: =AF154-AG154 -> #N/A | AI154: =C154+(AB154*Assumptions!$B$15) -> #N/A | AJ154: =AH154/AI154 -> #N/A | AK154: =AJ154*(365/AD154) -> #N/A | AL154: =IF(AND(AD154>0,AK154 > Assumptions!$B$13), "ENTER", "DONT ENTER") -> #N/A
A155: 45900 | B155: ADANI | C155: =VLOOKUP(A155, Raw_Data_Adani!A:N, 8, FALSE) -> #N/A | AB155: =VLOOKUP(A155, Raw_Data_Adani!AQ:BE, 8, FALSE) -> #N/A | AC155: =Assumptions!$B$32 -> 45930 | AD155: =AC155-A155 -> 30 | AE155: =C155*(1+(Assumptions!$B$13*AD155/365)) -> #N/A | AF155: =AB155-AE155 -> #N/A | AG155: =(C155*Assumptions!$B$16)+(AB155*Assumptions!$B$17) -> #N/A | AH155: =AF155-AG155 -> #N/A | AI155: =C155+(AB155*Assumptions!$B$15) -> #N/A | AJ155: =AH155/AI155 -> #N/A | AK155: =AJ155*(365/AD155) -> #N/A | AL155: =IF(AND(AD155>0,AK155 > Assumptions!$B$13), "ENTER", "DONT ENTER") -> #N/A
A156: 45901 | B156: ADANI | C156: =VLOOKUP(A156, Raw_Data_Adani!A:N, 8, FALSE) -> 2284.2 | AB156: =VLOOKUP(A156, Raw_Data_Adani!AQ:BE, 8, FALSE) -> 2295.8 | AC156: =Assumptions!$B$32 -> 45930 | AD156: =AC156-A156 -> 29 | AE156: =C156*(1+(Assumptions!$B$13*AD156/365)) -> 2295.9057 | AF156: =AB156-AE156 -> -0.10574274 | AG156: =(C156*Assumptions!$B$16)+(AB156*Assumptions!$B$17) -> 1.60126 | AH156: =AF156-AG156 -> -1.7070027 | AI156: =C156+(AB156*Assumptions!$B$15) -> 3041.814 | AJ156: =AH156/AI156 -> -0.0005611792 | AK156: =AJ156*(365/AD156) -> -0.0070631175 | AL156: =IF(AND(AD156>0,AK156 > Assumptions!$B$13), "ENTER", "DONT ENTER") -> DONT ENTER
A157: 45902 | B157: ADANI | C157: =VLOOKUP(A157, Raw_Data_Adani!A:N, 8, FALSE) -> 2274.2 | AB157: =VLOOKUP(A157, Raw_Data_Adani!AQ:BE, 8, FALSE) -> 2284.1 | AC157: =Assumptions!$B$32 -> 45930 | AD157: =AC157-A157 -> 28 | AE157: =C157*(1+(Assumptions!$B$13*AD157/365)) -> 2285.4526 | AF157: =AB157-AE157 -> -1.352617 | AG157: =(C157*Assumptions!$B$16)+(AB157*Assumptions!$B$17) -> 1.59392 | AH157: =AF157-AG157 -> -2.946537 | AI157: =C157+(AB157*Assumptions!$B$15) -> 3027.953 | AJ157: =AH157/AI157 -> -0.00097311186 | AK157: =AJ157*(365/AD157) -> -0.012685208 | AL157: =IF(AND(AD157>0,AK157 > Assumptions!$B$13), "ENTER", "DONT ENTER") -> DONT ENTER
A158: 45903 | B158: ADANI | C158: =VLOOKUP(A158, Raw_Data_Adani!A:N, 8, FALSE) -> 2288.7 | AB158: =VLOOKUP(A158, Raw_Data_Adani!AQ:BE, 8, FALSE) -> 2300.5 | AC158: =Assumptions!$B$32 -> 45930 | AD158: =AC158-A158 -> 27 | AE158: =C158*(1+(Assumptions!$B$13*AD158/365)) -> 2299.6199 | AF158: =AB158-AE158 -> 0.88007932 | AG158: =(C158*Assumptions!$B$16)+(AB158*Assumptions!$B$17) -> 1.60445 | AH158: =AF158-AG158 -> -0.72437068 | AI158: =C158+(AB158*Assumptions!$B$15) -> 3047.865 | AJ158: =AH158/AI158 -> -0.00023766495 | AK158: =AJ158*(365/AD158) -> -0.003212878 | AL158: =IF(AND(AD158>0,AK158 > Assumptions!$B$13), "ENTER", "DONT ENTER") -> DONT ENTER
A159: 45904 | B159: ADANI | C159: =VLOOKUP(A159, Raw_Data_Adani!A:N, 8, FALSE) -> 2278.8 | AB159: =VLOOKUP(A159, Raw_Data_Adani!AQ:BE, 8, FALSE) -> 2286.9 | AC159: =Assumptions!$B$32 -> 45930 | AD159: =AC159-A159 -> 26 | AE159: =C159*(1+(Assumptions!$B$13*AD159/365)) -> 2289.27 | AF159: =AB159-AE159 -> -2.3699934 | AG159: =(C159*Assumptions!$B$16)+(AB159*Assumptions!$B$17) -> 1.59678 | AH159: =AF159-AG159 -> -3.9667734 | AI159: =C159+(AB159*Assumptions!$B$15) -> 3033.477 | AJ159: =AH159/AI159 -> -0.0013076656 | AK159: =AJ159*(365/AD159) -> -0.018357613 | AL159: =IF(AND(AD159>0,AK159 > Assumptions!$B$13), "ENTER", "DONT ENTER") -> DONT ENTER
A160: 45905 | B160: ADANI | C160: =VLOOKUP(A160, Raw_Data_Adani!A:N, 8, FALSE) -> 2281.4 | AB160: =VLOOKUP(A160, Raw_Data_Adani!AQ:BE, 8, FALSE) -> 2292.5 | AC160: =Assumptions!$B$32 -> 45930 | AD160: =AC160-A160 -> 25 | AE160: =C160*(1+(Assumptions!$B$13*AD160/365)) -> 2291.4788 | AF160: =AB160-AE160 -> 1.0212123 | AG160: =(C160*Assumptions!$B$16)+(AB160*Assumptions!$B$17) -> 1.5992 | AH160: =AF160-AG160 -> -0.57798767 | AI160: =C160+(AB160*Assumptions!$B$15) -> 3037.925 | AJ160: =AH160/AI160 -> -0.00019025739 | AK160: =AJ160*(365/AD160) -> -0.0027777578 | AL160: =IF(AND(AD160>0,AK160 > Assumptions!$B$13), "ENTER", "DONT ENTER") -> DONT ENTER
A161: 45906 | B161: ADANI | C161: =VLOOKUP(A161, Raw_Data_Adani!A:N, 8, FALSE) -> #N/A | AB161: =VLOOKUP(A161, Raw_Data_Adani!AQ:BE, 8, FALSE) -> #N/A | AC161: =Assumptions!$B$32 -> 45930 | AD161: =AC161-A161 -> 24 | AE161: =C161*(1+(Assumptions!$B$13*AD161/365)) -> #N/A | AF161: =AB161-AE161 -> #N/A | AG161: =(C161*Assumptions!$B$16)+(AB161*Assumptions!$B$17) -> #N/A | AH161: =AF161-AG161 -> #N/A | AI161: =C161+(AB161*Assumptions!$B$15) -> #N/A | AJ161: =AH161/AI161 -> #N/A | AK161: =AJ161*(365/AD161) -> #N/A | AL161: =IF(AND(AD161>0,AK161 > Assumptions!$B$13), "ENTER", "DONT ENTER") -> #N/A
A162: 45907 | B162: ADANI | C162: =VLOOKUP(A162, Raw_Data_Adani!A:N, 8, FALSE) -> #N/A | AB162: =VLOOKUP(A162, Raw_Data_Adani!AQ:BE, 8, FALSE) -> #N/A | AC162: =Assumptions!$B$32 -> 45930 | AD162: =AC162-A162 -> 23 | AE162: =C162*(1+(Assumptions!$B$13*AD162/365)) -> #N/A | AF162: =AB162-AE162 -> #N/A | AG162: =(C162*Assumptions!$B$16)+(AB162*Assumptions!$B$17) -> #N/A | AH162: =AF162-AG162 -> #N/A | AI162: =C162+(AB162*Assumptions!$B$15) -> #N/A | AJ162: =AH162/AI162 -> #N/A | AK162: =AJ162*(365/AD162) -> #N/A | AL162: =IF(AND(AD162>0,AK162 > Assumptions!$B$13), "ENTER", "DONT ENTER") -> #N/A
A163: 45908 | B163: ADANI | C163: =VLOOKUP(A163, Raw_Data_Adani!A:N, 8, FALSE) -> 2310.9 | AB163: =VLOOKUP(A163, Raw_Data_Adani!AQ:BE, 8, FALSE) -> 2323.9 | AC163: =Assumptions!$B$32 -> 45930 | AD163: =AC163-A163 -> 22 | AE163: =C163*(1+(Assumptions!$B$13*AD163/365)) -> 2319.884 | AF163: =AB163-AE163 -> 4.0159805 | AG163: =(C163*Assumptions!$B$16)+(AB163*Assumptions!$B$17) -> 1.62023 | AH163: =AF163-AG163 -> 2.3957505 | AI163: =C163+(AB163*Assumptions!$B$15) -> 3077.787 | AJ163: =AH163/AI163 -> 0.00077840037 | AK163: =AJ163*(365/AD163) -> 0.01291437 | AL163: =IF(AND(AD163>0,AK163 > Assumptions!$B$13), "ENTER", "DONT ENTER") -> DONT ENTER
A164: 45909 | B164: ADANI | C164: =VLOOKUP(A164, Raw_Data_Adani!A:N, 8, FALSE) -> 2311.6 | AB164: =VLOOKUP(A164, Raw_Data_Adani!AQ:BE, 8, FALSE) -> 2317.9 | AC164: =Assumptions!$B$32 -> 45930 | AD164: =AC164-A164 -> 21 | AE164: =C164*(1+(Assumptions!$B$13*AD164/365)) -> 2320.1783 | AF164: =AB164-AE164 -> -2.2782526 | AG164: =(C164*Assumptions!$B$16)+(AB164*Assumptions!$B$17) -> 1.61938 | AH164: =AF164-AG164 -> -3.8976326 | AI164: =C164+(AB164*Assumptions!$B$15) -> 3076.507 | AJ164: =AH164/AI164 -> -0.0012669019 | AK164: =AJ164*(365/AD164) -> -0.022019962 | AL164: =IF(AND(AD164>0,AK164 > Assumptions!$B$13), "ENTER", "DONT ENTER") -> DONT ENTER
... A185: 45930 | B185: ADANI | C185: =VLOOKUP(A185, Raw_Data_Adani!A:N, 8, FALSE) -> 2505.9 | AB185: =VLOOKUP(A185, Raw_Data_Adani!AQ:BE, 8, FALSE) -> 2503.4 | AC185: =Assumptions!$B$32 -> 45930 | AD185: =AC185-A185 -> 0 | AE185: =C185*(1+(Assumptions!$B$13*AD185/365)) -> 2505.9 | AF185: =AB185-AE185 -> -2.5 | AG185: =(C185*Assumptions!$B$16)+(AB185*Assumptions!$B$17) -> 1.75363 | AH185: =AF185-AG185 -> -4.25363 | AI185: =C185+(AB185*Assumptions!$B$15) -> 3332.022 | AJ185: =AH185/AI185 -> -0.0012765912 | AK185: =AJ185*(365/AD185) -> #DIV/0! | AL185: =IF(AND(AD185>0,AK185 > Assumptions!$B$13), "ENTER", "DONT ENTER") -> #DIV/0!

Sheet Trade_Log
A1: Trade ID | B1: Stock | C1: Entry_Date | D1: Exit_Date | E1: Contract | F1: Lots | G1: Entry_Spot_Price | H1: Entry_Futures_Price | I1: Spot_Cost (Total cost of buying spot inventory) | J1: Margin Blocked | K1: Exit_Spot_Price | L1: Settlement_Value
A2: 1 | B2: =Assumptions!$A$24 -> RELIANCE | C2: ='Data Analysis'!A18 -> 45855 | D2: ='Data Analysis'!E18 -> 45869 | E2: =TEXT(D2,"mmm") -> Jul | F2: 37 | G2: =IFERROR(VLOOKUP(C2, 'Data Analysis'!$A:$C, 3, FALSE), 0) -> 1476.4 | H2: =IFERROR( IF(E2="JUL", VLOOKUP(C2, 'Data Analysis'!$A:$E, 4, FALSE), IF(E2="AUG", VLOOKUP(C2, 'Data Analysis'!$A:$Q, 16, FALSE), IF(E2="SEP", VLOOKUP(C2, 'Data Analysis'!$A:$AC, 28, FALSE), 0))), 0) -> 1482.6 | I2: =F2*Assumptions!$B$24*G2*(1+Assumptions!$B$16) -> 27327057 | J2: =F2*Assumptions!$B$24*H2*Assumptions!$B$18 -> 5485620 | K2: =IFERROR(VLOOKUP(D2, 'Data Analysis'!$A:$C, 3, FALSE), 0) -> 1390.2 | L2: =(F2*Assumptions!$B$24*K2*(1-Assumptions!$B$16)) + (F2*Assumptions!$B$24*(H2-K2)*(1-Assumptions!$B$17)) + J2 -> 32900519
A3: =A2+1 -> 2 | B3: =Assumptions!$A$24 -> RELIANCE | C3: ='Data Analysis'!A19 -> 45856 | D3: ='Data Analysis'!E19 -> 45869 | E3: =TEXT(D3,"mmm") -> Jul | F3: 34 | G3: =IFERROR(VLOOKUP(C3, 'Data Analysis'!$A:$C, 3, FALSE), 0) -> 1476 | H3: =IFERROR( IF(E3="JUL", VLOOKUP(C3, 'Data Analysis'!$A:$E, 4, FALSE), IF(E3="AUG", VLOOKUP(C3, 'Data Analysis'!$A:$Q, 16, FALSE), IF(E3="SEP", VLOOKUP(C3, 'Data Analysis'!$A:$AC, 28, FALSE), 0))), 0) -> 1482.6 | I3: =F3*Assumptions!$B$24*G3*(1+Assumptions!$B$16) -> 25104546 | J3: =F3*Assumptions!$B$24*H3*Assumptions!$B$18 -> 5040840 | K3: =IFERROR(VLOOKUP(D3, 'Data Analysis'!$A:$C, 3, FALSE), 0) -> 1390.2 | L3: =(F3*Assumptions!$B$24*K3*(1-Assumptions!$B$16)) + (F3*Assumptions!$B$24*(H3-K3)*(1-Assumptions!$B$17)) + J3 -> 30232909
A4: =A3+1 -> 3 | B4: =Assumptions!$A$24 -> RELIANCE | C4: ='Data Analysis'!A23 -> 45860 | D4: ='Data Analysis'!E23 -> 45869 | E4: =TEXT(D4,"mmm") -> Jul | F4: 19 | G4: =IFERROR(VLOOKUP(C4, 'Data Analysis'!$A:$C, 3, FALSE), 0) -> 1412.8 | H4: =IFERROR( IF(E4="JUL", VLOOKUP(C4, 'Data Analysis'!$A:$E, 4, FALSE), IF(E4="AUG", VLOOKUP(C4, 'Data Analysis'!$A:$Q, 16, FALSE), IF(E4="SEP", VLOOKUP(C4, 'Data Analysis'!$A:$AC, 28, FALSE), 0))), 0) -> 1417.3 | I4: =F4*Assumptions!$B$24*G4*(1+Assumptions!$B$16) -> 13428311 | J4: =F4*Assumptions!$B$24*H4*Assumptions!$B$18 -> 2692870 | K4: =IFERROR(VLOOKUP(D4, 'Data Analysis'!$A:$C, 3, FALSE), 0) -> 1390.2 | L4: =(F4*Assumptions!$B$24*K4*(1-Assumptions!$B$16)) + (F4*Assumptions!$B$24*(H4-K4)*(1-Assumptions!$B$17)) + J4 -> 16150565
A5: =A4+1 -> 4 | B5: =Assumptions!$A$24 -> RELIANCE | C5: ='Data Analysis'!A25 -> 45862 | D5: ='Data Analysis'!E25 -> 45869 | E5: =TEXT(D5,"mmm") -> Jul | F5: 6 | G5: =IFERROR(VLOOKUP(C5, 'Data Analysis'!$A:$C, 3, FALSE), 0) -> 1402.9 | H5: =IFERROR( IF(E5="JUL", VLOOKUP(C5, 'Data Analysis'!$A:$E, 4, FALSE), IF(E5="AUG", VLOOKUP(C5, 'Data Analysis'!$A:$Q, 16, FALSE), IF(E5="SEP", VLOOKUP(C5, 'Data Analysis'!$A:$AC, 28, FALSE), 0))), 0) -> 1406.6 | I5: =F5*Assumptions!$B$24*G5*(1+Assumptions!$B$16) -> 4210804.3 | J5: =F5*Assumptions!$B$24*H5*Assumptions!$B$18 -> 843960 | K5: =IFERROR(VLOOKUP(D5, 'Data Analysis'!$A:$C, 3, FALSE), 0) -> 1390.2 | L5: =(F5*Assumptions!$B$24*K5*(1-Assumptions!$B$16)) + (F5*Assumptions!$B$24*(H5-K5)*(1-Assumptions!$B$17)) + J5 -> 5061664.9
A6: =A5+1 -> 5 | B6: =Assumptions!$A$24 -> RELIANCE | C6: ='Data Analysis'!A50 -> 45887 | D6: ='Data Analysis'!Q51 -> 45897 | E6: =TEXT(D6,"mmm") -> Aug | F6: 39 | G6: =IFERROR(VLOOKUP(C6, 'Data Analysis'!$A:$C, 3, FALSE), 0) -> 1381.7 | H6: =IFERROR( IF(E6="JUL", VLOOKUP(C6, 'Data Analysis'!$A:$E, 4, FALSE), IF(E6="AUG", VLOOKUP(C6, 'Data Analysis'!$A:$Q, 16, FALSE), IF(E6="SEP", VLOOKUP(C6, 'Data Analysis'!$A:$AC, 28, FALSE), 0))), 0) -> 1386.6 | I6: =F6*Assumptions!$B$24*G6*(1+Assumptions!$B$16) -> 26956622 | J6: =F6*Assumptions!$B$24*H6*Assumptions!$B$18 -> 5407740 | K6: =IFERROR(VLOOKUP(D6, 'Data Analysis'!$A:$C, 3, FALSE), 0) -> 1385.9 | L6: =(F6*Assumptions!$B$24*K6*(1-Assumptions!$B$16)) + (F6*Assumptions!$B$24*(H6-K6)*(1-Assumptions!$B$17)) + J6 -> 32432925
A7: =A6+1 -> 6 | B7: =Assumptions!$A$24 -> RELIANCE | C7: ='Data Analysis'!A86 -> 45923 | D7: ='Data Analysis'!AC86 -> 45930 | E7: =TEXT(D7,"mmm") -> Sep | F7: 39 | G7: =IFERROR(VLOOKUP(C7, 'Data Analysis'!$A:$C, 3, FALSE), 0) -> 1389.8 | H7: =IFERROR( IF(E7="JUL", VLOOKUP(C7, 'Data Analysis'!$A:$E, 4, FALSE), IF(E7="AUG", VLOOKUP(C7, 'Data Analysis'!$A:$Q, 16, FALSE), IF(E7="SEP", VLOOKUP(C7, 'Data Analysis'!$A:$AC, 28, FALSE), 0))), 0) -> 1394.9 | I7: =F7*Assumptions!$B$24*G7*(1+Assumptions!$B$16) -> 27114651 | J7: =F7*Assumptions!$B$24*H7*Assumptions!$B$18 -> 5440110 | K7: =IFERROR(VLOOKUP(D7, 'Data Analysis'!$A:$C, 3, FALSE), 0) -> 1364 | L7: =(F7*Assumptions!$B$24*K7*(1-Assumptions!$B$16)) + (F7*Assumptions!$B$24*(H7-K7)*(1-Assumptions!$B$17)) + J7 -> 32627240
A8: =A7+1 -> 7 | B8: =Assumptions!$A$24 -> RELIANCE | C8: ='Data Analysis'!A88 -> 45925 | D8: ='Data Analysis'!AC88 -> 45930 | E8: =TEXT(D8,"mmm") -> Sep | F8: 20 | G8: =IFERROR(VLOOKUP(C8, 'Data Analysis'!$A:$C, 3, FALSE), 0) -> 1372.4 | H8: =IFERROR( IF(E8="JUL", VLOOKUP(C8, 'Data Analysis'!$A:$E, 4, FALSE), IF(E8="AUG", VLOOKUP(C8, 'Data Analysis'!$A:$Q, 16, FALSE), IF(E8="SEP", VLOOKUP(C8, 'Data Analysis'!$A:$AC, 28, FALSE), 0))), 0) -> 1376.6 | I8: =F8*Assumptions!$B$24*G8*(1+Assumptions!$B$16) -> 13730862 | J8: =F8*Assumptions!$B$24*H8*Assumptions!$B$18 -> 2753200 | K8: =IFERROR(VLOOKUP(D8, 'Data Analysis'!$A:$C, 3, FALSE), 0) -> 1364 | L8: =(F8*Assumptions!$B$24*K8*(1-Assumptions!$B$16)) + (F8*Assumptions!$B$24*(H8-K8)*(1-Assumptions!$B$17)) + J8 -> 16512355
A9: =A8+1 -> 8 | B9: =Assumptions!$A$25 -> ADANI | C9: ='Data Analysis'!A116 -> 45861 | D9: ='Data Analysis'!E121 -> 45869 | E9: =TEXT(D9,"mmm") -> Jul | F9: 9 | G9: {=IFERROR( INDEX('Data Analysis'!$C:$C, SMALL( IF('Data Analysis'!$A:$A=C9, ROW('Data Analysis'!$A:$A)), 2) ), 0)} -> 2614.5 | H9: {=IFERROR( IF(E9="JUL", INDEX('Data Analysis'!$D:$D, SMALL(IF('Data Analysis'!$A:$A=C9, ROW('Data Analysis'!$A:$A)), 2)), IF(E9="AUG", INDEX('Data Analysis'!$P:$P, SMALL(IF('Data Analysis'!$A:$A=C9, ROW('Data Analysis'!$A:$A)), 2)), IF(E9="SEP", INDEX('Data Analysis'!$AB:$AB, SMALL(IF('Data Analysis'!$A:$A=C9, ROW('Data Analysis'!$A:$A)), 2)), 0))), 0)} -> 2621.8 | I9: =F9*Assumptions!$B$25*G9*(1+Assumptions!$B$16) -> 7062679.6 | J9: =F9*Assumptions!$B$25*H9*Assumptions!$B$18 -> 1415772 | K9: {=IFERROR( INDEX('Data Analysis'!$C:$C, SMALL( IF('Data Analysis'!$A:$A=D9, ROW('Data Analysis'!$A:$A)), 2) ), 0)} -> 2430.7 | L9: =(F9*Assumptions!$B$25*K9*(1-Assumptions!$B$16)) + (F9*Assumptions!$B$25*(H9-K9)*(1-Assumptions!$B$17)) + J9 -> 8491247.4
A10: =A9+1 -> 9 | B10: =Assumptions!$A$25 -> ADANI | C10: ='Data Analysis'!A122 -> 45867 | D10: ='Data Analysis'!E122 -> 45869 | E10: =TEXT(D10,"mmm") -> Jul | F10: 3 | G10: {=IFERROR( INDEX('Data Analysis'!$C:$C, SMALL( IF('Data Analysis'!$A:$A=C10, ROW('Data Analysis'!$A:$A)), 2) ), 0)} -> 2547.9 | H10: {=IFERROR( IF(E10="JUL", INDEX('Data Analysis'!$D:$D, SMALL(IF('Data Analysis'!$A:$A=C10, ROW('Data Analysis'!$A:$A)), 2)), IF(E10="AUG", INDEX('Data Analysis'!$P:$P, SMALL(IF('Data Analysis'!$A:$A=C10, ROW('Data Analysis'!$A:$A)), 2)), IF(E10="SEP", INDEX('Data Analysis'!$AB:$AB, SMALL(IF('Data Analysis'!$A:$A=C10, ROW('Data Analysis'!$A:$A)), 2)), 0))), 0)} -> 2552.4 | I10: =F10*Assumptions!$B$25*G10*(1+Assumptions!$B$16) -> 2294256.6 | J10: =F10*Assumptions!$B$25*H10*Assumptions!$B$18 -> 459432 | K10: {=IFERROR( INDEX('Data Analysis'!$C:$C, SMALL( IF('Data Analysis'!$A:$A=D10, ROW('Data Analysis'!$A:$A)), 2) ), 0)} -> 2430.7 | L10: =(F10*Assumptions!$B$25*K10*(1-Assumptions!$B$16)) + (F10*Assumptions!$B$25*(H10-K10)*(1-Assumptions!$B$17)) + J10 -> 2755476.3
A11: =A10+1 -> 10 | B11: =Assumptions!$A$25 -> ADANI | C11: ='Data Analysis'!A179 -> 45924 | D11: ='Data Analysis'!AC179 -> 45930 | E11: =TEXT(D11,"mmm") -> Sep | F11: 32 | G11: {=IFERROR( INDEX('Data Analysis'!$C:$C, SMALL( IF('Data Analysis'!$A:$A=C11, ROW('Data Analysis'!$A:$A)), 2) ), 0)} -> 2619.8 | H11: {=IFERROR( IF(E11="JUL", INDEX('Data Analysis'!$D:$D, SMALL(IF('Data Analysis'!$A:$A=C11, ROW('Data Analysis'!$A:$A)), 2)), IF(E11="AUG", INDEX('Data Analysis'!$P:$P, SMALL(IF('Data Analysis'!$A:$A=C11, ROW('Data Analysis'!$A:$A)), 2)), IF(E11="SEP", INDEX('Data Analysis'!$AB:$AB, SMALL(IF('Data Analysis'!$A:$A=C11, ROW('Data Analysis'!$A:$A)), 2)), 0))), 0)} -> 2628.7 | I11: =F11*Assumptions!$B$25*G11*(1+Assumptions!$B$16) -> 25162655 | J11: =F11*Assumptions!$B$25*H11*Assumptions!$B$18 -> 5047104 | K11: {=IFERROR( INDEX('Data Analysis'!$C:$C, SMALL( IF('Data Analysis'!$A:$A=D11, ROW('Data Analysis'!$A:$A)), 2) ), 0)} -> 2505.9 | L11: =(F11*Assumptions!$B$25*K11*(1-Assumptions!$B$16)) + (F11*Assumptions!$B$25*(H11-K11)*(1-Assumptions!$B$17)) + J11 -> 30270360
A12: =A11+1 -> 11 | B12: =Assumptions!$A$25 -> ADANI | C12: ='Data Analysis'!A180 -> 45925 | D12: ='Data Analysis'!AC180 -> 45930 | E12: =TEXT(D12,"mmm") -> Sep | F12: 10 | G12: {=IFERROR( INDEX('Data Analysis'!$C:$C, SMALL( IF('Data Analysis'!$A:$A=C12, ROW('Data Analysis'!$A:$A)), 2) ), 0)} -> 2576.4 | H12: {=IFERROR( IF(E12="JUL", INDEX('Data Analysis'!$D:$D, SMALL(IF('Data Analysis'!$A:$A=C12, ROW('Data Analysis'!$A:$A)), 2)), IF(E12="AUG", INDEX('Data Analysis'!$P:$P, SMALL(IF('Data Analysis'!$A:$A=C12, ROW('Data Analysis'!$A:$A)), 2)), IF(E12="SEP", INDEX('Data Analysis'!$AB:$AB, SMALL(IF('Data Analysis'!$A:$A=C12, ROW('Data Analysis'!$A:$A)), 2)), 0))), 0)} -> 2586 | I12: =F12*Assumptions!$B$25*G12*(1+Assumptions!$B$16) -> 7733064.6 | J12: =F12*Assumptions!$B$25*H12*Assumptions!$B$18 -> 1551600 | K12: {=IFERROR( INDEX('Data Analysis'!$C:$C, SMALL( IF('Data Analysis'!$A:$A=D12, ROW('Data Analysis'!$A:$A)), 2) ), 0)} -> 2505.9 | L12: =(F12*Assumptions!$B$25*K12*(1-Assumptions!$B$16)) + (F12*Assumptions!$B$25*(H12-K12)*(1-Assumptions!$B$17)) + J12 -> 9305793.1
A13: =A12+1 -> 12 | B13: =Assumptions!$A$25 -> ADANI | C13: ='Data Analysis'!A184 -> 45929 | D13: ='Data Analysis'!AC184 -> 45930 | E13: =TEXT(D13,"mmm") -> Sep | F13: 5 | G13: {=IFERROR( INDEX('Data Analysis'!$C:$C, SMALL( IF('Data Analysis'!$A:$A=C13, ROW('Data Analysis'!$A:$A)), 2) ), 0)} -> 2509.5 | H13: {=IFERROR( IF(E13="JUL", INDEX('Data Analysis'!$D:$D, SMALL(IF('Data Analysis'!$A:$A=C13, ROW('Data Analysis'!$A:$A)), 2)), IF(E13="AUG", INDEX('Data Analysis'!$P:$P, SMALL(IF('Data Analysis'!$A:$A=C13, ROW('Data Analysis'!$A:$A)), 2)), IF(E13="SEP", INDEX('Data Analysis'!$AB:$AB, SMALL(IF('Data Analysis'!$A:$A=C13, ROW('Data Analysis'!$A:$A)), 2)), 0))), 0)} -> 2516 | I13: =F13*Assumptions!$B$25*G13*(1+Assumptions!$B$16) -> 3766132.1 | J13: =F13*Assumptions!$B$25*H13*Assumptions!$B$18 -> 754800 | K13: {=IFERROR( INDEX('Data Analysis'!$C:$C, SMALL( IF('Data Analysis'!$A:$A=D13, ROW('Data Analysis'!$A:$A)), 2) ), 0)} -> 2505.9 | L13: =(F13*Assumptions!$B$25*K13*(1-Assumptions!$B$16)) + (F13*Assumptions!$B$25*(H13-K13)*(1-Assumptions!$B$17)) + J13 -> 4526917.5

Sheet Daily_Ledger
A1: Date | B1: Opening_Cash | C1: New Spot Outflow | D1: New Margin Outflow | E1: New Trade Outflow | F1: Closed Trade Inflow | G1: Uninvested_Cash | H1: Interest_Earned | I1: Total_Spot_Inventory_Cost | J1: Total_Margin_Blocked | K1: Closing_Cash | L1: Total_Fund_Value
A2: 45839 | B2: =Assumptions!B4 -> 100000000 | C2: =SUMIF(Trade_Log!$C:$C, A2, Trade_Log!$I:$I) -> 0 | D2: =SUMIF(Trade_Log!$C:$C, A2, Trade_Log!$J:$J) -> 0 | E2: =-(C2+D2) -> 0 | F2: =SUMIF(Trade_Log!$D:$D, A2, Trade_Log!$L:$L) -> 0 | G2: =B2+E2+F2 -> 100000000 | H2: =G2*Assumptions!$B$5/365 -> 16438.356 | I2: =SUMIFS(Trade_Log!$I:$I, Trade_Log!$C:$C, "<="&A2, Trade_Log!$D:$D, ">"&A2) -> 0 | J2: =SUMIFS(Trade_Log!$J:$J, Trade_Log!$C:$C, "<="&A2, Trade_Log!$D:$D, ">"&A2) -> 0 | K2: =G2+H2 -> 1.0001644e+08 | L2: =K2+I2+J2 -> 1.0001644e+08
A3: 45840 | B3: =K2 -> 1.0001644e+08 | C3: =SUMIF(Trade_Log!$C:$C, A3, Trade_Log!$I:$I) -> 0 | D3: =SUMIF(Trade_Log!$C:$C, A3, Trade_Log!$J:$J) -> 0 | E3: =-(C3+D3) -> 0 | F3: =SUMIF(Trade_Log!$D:$D, A3, Trade_Log!$L:$L) -> 0 | G3: =B3+E3+F3 -> 1.0001644e+08 | H3: =G3*Assumptions!$B$5/365 -> 16441.058 | I3: =SUMIFS(Trade_Log!$I:$I, Trade_Log!$C:$C, "<="&A3, Trade_Log!$D:$D, ">"&A3) -> 0 | J3: =SUMIFS(Trade_Log!$J:$J, Trade_Log!$C:$C, "<="&A3, Trade_Log!$D:$D, ">"&A3) -> 0 | K3: =G3+H3 -> 1.0003288e+08 | L3: =K3+I3+J3 -> 1.0003288e+08
A4: 45841 | B4: =K3 -> 1.0003288e+08 | C4: =SUMIF(Trade_Log!$C:$C, A4, Trade_Log!$I:$I) -> 0 | D4: =SUMIF(Trade_Log!$C:$C, A4, Trade_Log!$J:$J) -> 0 | E4: =-(C4+D4) -> 0 | F4: =SUMIF(Trade_Log!$D:$D, A4, Trade_Log!$L:$L) -> 0 | G4: =B4+E4+F4 -> 1.0003288e+08 | H4: =G4*Assumptions!$B$5/365 -> 16443.761 | I4: =SUMIFS(Trade_Log!$I:$I, Trade_Log!$C:$C, "<="&A4, Trade_Log!$D:$D, ">"&A4) -> 0 | J4: =SUMIFS(Trade_Log!$J:$J, Trade_Log!$C:$C, "<="&A4, Trade_Log!$D:$D, ">"&A4) -> 0 | K4: =G4+H4 -> 1.0004932e+08 | L4: =K4+I4+J4 -> 1.0004932e+08
A5: 45842 | B5: =K4 -> 1.0004932e+08 | C5: =SUMIF(Trade_Log!$C:$C, A5, Trade_Log!$I:$I) -> 0 | D5: =SUMIF(Trade_Log!$C:$C, A5, Trade_Log!$J:$J) -> 0 | E5: =-(C5+D5) -> 0 | F5: =SUMIF(Trade_Log!$D:$D, A5, Trade_Log!$L:$L) -> 0 | G5: =B5+E5+F5 -> 1.0004932e+08 | H5: =G5*Assumptions!$B$5/365 -> 16446.464 | I5: =SUMIFS(Trade_Log!$I:$I, Trade_Log!$C:$C, "<="&A5, Trade_Log!$D:$D, ">"&A5) -> 0 | J5: =SUMIFS(Trade_Log!$J:$J, Trade_Log!$C:$C, "<="&A5, Trade_Log!$D:$D, ">"&A5) -> 0 | K5: =G5+H5 -> 1.0006577e+08 | L5: =K5+I5+J5 -> 1.0006577e+08
A6: 45843 | B6: =K5 -> 1.0006577e+08 | C6: =SUMIF(Trade_Log!$C:$C, A6, Trade_Log!$I:$I) -> 0 | D6: =SUMIF(Trade_Log!$C:$C, A6, Trade_Log!$J:$J) -> 0 | E6: =-(C6+D6) -> 0 | F6: =SUMIF(Trade_Log!$D:$D, A6, Trade_Log!$L:$L) -> 0 | G6: =B6+E6+F6 -> 1.0006577e+08 | H6: =G6*Assumptions!$B$5/365 -> 16449.168 | I6: =SUMIFS(Trade_Log!$I:$I, Trade_Log!$C:$C, "<="&A6, Trade_Log!$D:$D, ">"&A6) -> 0 | J6: =SUMIFS(Trade_Log!$J:$J, Trade_Log!$C:$C, "<="&A6, Trade_Log!$D:$D, ">"&A6) -> 0 | K6: =G6+H6 -> 1.0008222e+08 | L6: =K6+I6+J6 -> 1.0008222e+08
A7: 45844 | B7: =K6 -> 1.0008222e+08 | C7: =SUMIF(Trade_Log!$C:$C, A7, Trade_Log!$I:$I) -> 0 | D7: =SUMIF(Trade_Log!$C:$C, A7, Trade_Log!$J:$J) -> 0 | E7: =-(C7+D7) -> 0 | F7: =SUMIF(Trade_Log!$D:$D, A7, Trade_Log!$L:$L) -> 0 | G7: =B7+E7+F7 -> 1.0008222e+08 | H7: =G7*Assumptions!$B$5/365 -> 16451.872 | I7: =SUMIFS(Trade_Log!$I:$I, Trade_Log!$C:$C, "<="&A7, Trade_Log!$D:$D, ">"&A7) -> 0 | J7: =SUMIFS(Trade_Log!$J:$J, Trade_Log!$C:$C, "<="&A7, Trade_Log!$D:$D, ">"&A7) -> 0 | K7: =G7+H7 -> 1.0009867e+08 | L7: =K7+I7+J7 -> 1.0009867e+08
A8: 45845 | B8: =K7 -> 1.0009867e+08 | C8: =SUMIF(Trade_Log!$C:$C, A8, Trade_Log!$I:$I) -> 0 | D8: =SUMIF(Trade_Log!$C:$C, A8, Trade_Log!$J:$J) -> 0 | E8: =-(C8+D8) -> 0 | F8: =SUMIF(Trade_Log!$D:$D, A8, Trade_Log!$L:$L) -> 0 | G8: =B8+E8+F8 -> 1.0009867e+08 | H8: =G8*Assumptions!$B$5/365 -> 16454.576 | I8: =SUMIFS(Trade_Log!$I:$I, Trade_Log!$C:$C, "<="&A8, Trade_Log!$D:$D, ">"&A8) -> 0 | J8: =SUMIFS(Trade_Log!$J:$J, Trade_Log!$C:$C, "<="&A8, Trade_Log!$D:$D, ">"&A8) -> 0 | K8: =G8+H8 -> 1.0011513e+08 | L8: =K8+I8+J8 -> 1.0011513e+08
A9: 45846 | B9: =K8 -> 1.0011513e+08 | C9: =SUMIF(Trade_Log!$C:$C, A9, Trade_Log!$I:$I) -> 0 | D9: =SUMIF(Trade_Log!$C:$C, A9, Trade_Log!$J:$J) -> 0 | E9: =-(C9+D9) -> 0 | F9: =SUMIF(Trade_Log!$D:$D, A9, Trade_Log!$L:$L) -> 0 | G9: =B9+E9+F9 -> 1.0011513e+08 | H9: =G9*Assumptions!$B$5/365 -> 16457.281 | I9: =SUMIFS(Trade_Log!$I:$I, Trade_Log!$C:$C, "<="&A9, Trade_Log!$D:$D, ">"&A9) -> 0 | J9: =SUMIFS(Trade_Log!$J:$J, Trade_Log!$C:$C, "<="&A9, Trade_Log!$D:$D, ">"&A9) -> 0 | K9: =G9+H9 -> 1.0013158e+08 | L9: =K9+I9+J9 -> 1.0013158e+08
A10: 45847 | B10: =K9 -> 1.0013158e+08 | C10: =SUMIF(Trade_Log!$C:$C, A10, Trade_Log!$I:$I) -> 0 | D10: =SUMIF(Trade_Log!$C:$C, A10, Trade_Log!$J:$J) -> 0 | E10: =-(C10+D10) -> 0 | F10: =SUMIF(Trade_Log!$D:$D, A10, Trade_Log!$L:$L) -> 0 | G10: =B10+E10+F10 -> 1.0013158e+08 | H10: =G10*Assumptions!$B$5/365 -> 16459.986 | I10: =SUMIFS(Trade_Log!$I:$I, Trade_Log!$C:$C, "<="&A10, Trade_Log!$D:$D, ">"&A10) -> 0 | J10: =SUMIFS(Trade_Log!$J:$J, Trade_Log!$C:$C, "<="&A10, Trade_Log!$D:$D, ">"&A10) -> 0 | K10: =G10+H10 -> 1.0014804e+08 | L10: =K10+I10+J10 -> 1.0014804e+08
A11: 45848 | B11: =K10 -> 1.0014804e+08 | C11: =SUMIF(Trade_Log!$C:$C, A11, Trade_Log!$I:$I) -> 0 | D11: =SUMIF(Trade_Log!$C:$C, A11, Trade_Log!$J:$J) -> 0 | E11: =-(C11+D11) -> 0 | F11: =SUMIF(Trade_Log!$D:$D, A11, Trade_Log!$L:$L) -> 0 | G11: =B11+E11+F11 -> 1.0014804e+08 | H11: =G11*Assumptions!$B$5/365 -> 16462.692 | I11: =SUMIFS(Trade_Log!$I:$I, Trade_Log!$C:$C, "<="&A11, Trade_Log!$D:$D, ">"&A11) -> 0 | J11: =SUMIFS(Trade_Log!$J:$J, Trade_Log!$C:$C, "<="&A11, Trade_Log!$D:$D, ">"&A11) -> 0 | K11: =G11+H11 -> 1.0016451e+08 | L11: =K11+I11+J11 -> 1.0016451e+08
A12: 45849 | B12: =K11 -> 1.0016451e+08 | C12: =SUMIF(Trade_Log!$C:$C, A12, Trade_Log!$I:$I) -> 0 | D12: =SUMIF(Trade_Log!$C:$C, A12, Trade_Log!$J:$J) -> 0 | E12: =-(C12+D12) -> 0 | F12: =SUMIF(Trade_Log!$D:$D, A12, Trade_Log!$L:$L) -> 0 | G12: =B12+E12+F12 -> 1.0016451e+08 | H12: =G12*Assumptions!$B$5/365 -> 16465.398 | I12: =SUMIFS(Trade_Log!$I:$I, Trade_Log!$C:$C, "<="&A12, Trade_Log!$D:$D, ">"&A12) -> 0 | J12: =SUMIFS(Trade_Log!$J:$J, Trade_Log!$C:$C, "<="&A12, Trade_Log!$D:$D, ">"&A12) -> 0 | K12: =G12+H12 -> 1.0018097e+08 | L12: =K12+I12+J12 -> 1.0018097e+08
A13: 45850 | B13: =K12 -> 1.0018097e+08 | C13: =SUMIF(Trade_Log!$C:$C, A13, Trade_Log!$I:$I) -> 0 | D13: =SUMIF(Trade_Log!$C:$C, A13, Trade_Log!$J:$J) -> 0 | E13: =-(C13+D13) -> 0 | F13: =SUMIF(Trade_Log!$D:$D, A13, Trade_Log!$L:$L) -> 0 | G13: =B13+E13+F13 -> 1.0018097e+08 | H13: =G13*Assumptions!$B$5/365 -> 16468.105 | I13: =SUMIFS(Trade_Log!$I:$I, Trade_Log!$C:$C, "<="&A13, Trade_Log!$D:$D, ">"&A13) -> 0 | J13: =SUMIFS(Trade_Log!$J:$J, Trade_Log!$C:$C, "<="&A13, Trade_Log!$D:$D, ">"&A13) -> 0 | K13: =G13+H13 -> 1.0019744e+08 | L13: =K13+I13+J13 -> 1.0019744e+08
A14: 45851 | B14: =K13 -> 1.0019744e+08 | C14: =SUMIF(Trade_Log!$C:$C, A14, Trade_Log!$I:$I) -> 0 | D14: =SUMIF(Trade_Log!$C:$C, A14, Trade_Log!$J:$J) -> 0 | E14: =-(C14+D14) -> 0 | F14: =SUMIF(Trade_Log!$D:$D, A14, Trade_Log!$L:$L) -> 0 | G14: =B14+E14+F14 -> 1.0019744e+08 | H14: =G14*Assumptions!$B$5/365 -> 16470.812 | I14: =SUMIFS(Trade_Log!$I:$I, Trade_Log!$C:$C, "<="&A14, Trade_Log!$D:$D, ">"&A14) -> 0 | J14: =SUMIFS(Trade_Log!$J:$J, Trade_Log!$C:$C, "<="&A14, Trade_Log!$D:$D, ">"&A14) -> 0 | K14: =G14+H14 -> 1.0021391e+08 | L14: =K14+I14+J14 -> 1.0021391e+08
... A93: 45930 | B93: =K92 -> 8423875.6 | C93: =SUMIF(Trade_Log!$C:$C, A93, Trade_Log!$I:$I) -> 0 | D93: =SUMIF(Trade_Log!$C:$C, A93, Trade_Log!$J:$J) -> 0 | E93: =-(C93+D93) -> 0 | F93: =SUMIF(Trade_Log!$D:$D, A93, Trade_Log!$L:$L) -> 93242666 | G93: =B93+E93+F93 -> 1.0166654e+08 | H93: =G93*Assumptions!$B$5/365 -> 16712.308 | I93: =SUMIFS(Trade_Log!$I:$I, Trade_Log!$C:$C, "<="&A93, Trade_Log!$D:$D, ">"&A93) -> 0 | J93: =SUMIFS(Trade_Log!$J:$J, Trade_Log!$C:$C, "<="&A93, Trade_Log!$D:$D, ">"&A93) -> 0 | K93: =G93+H93 -> 1.0168325e+08 | L93: =K93+I93+J93 -> 1.0168325e+08

Sheet Raw_Data_Reliance
A1: Date | B1: series | C1: OPEN | D1: HIGH | E1: LOW | F1: PREV. CLOSE | G1: ltp | H1: close | I1: vwap | J1: 52W H | K1: 52W L | L1: VOLUME | M1: VALUE | N1: No of trades | O1: DATE | P1: EXPIRY DATE | Q1: OPEN PRICE | R1: HIGH PRICE | S1: LOW PRICE | T1: CLOSE PRICE | U1: LAST PRICE | V1: SETTLE PRICE | W1: Volume | X1: VALUE | Y1: PREMIUM VALUE | Z1: OPEN INTEREST | AA1: CHANGE IN OI | AB1: DATE | AC1: EXPIRY DATE | AD1: OPTION TYPE | AE1: STRIKE PRICE | AF1: OPEN PRICE | AG1: HIGH PRICE | AH1: LOW PRICE | AI1: CLOSE PRICE | AJ1: LAST PRICE | AK1: SETTLE PRICE | AL1: Volume | AM1: VALUE | AN1: PREMIUM VALUE | AO1: OPEN INTEREST | AP1: CHANGE IN OI | AQ1: DATE | AR1: EXPIRY DATE | AS1: OPTION TYPE | AT1: STRIKE PRICE | AU1: OPEN PRICE | AV1: HIGH PRICE | AW1: LOW PRICE | AX1: CLOSE PRICE | AY1: LAST PRICE | AZ1: SETTLE PRICE | BA1: Volume | BB1: VALUE | BC1: PREMIUM VALUE | BD1: OPEN INTEREST | BE1: CHANGE IN OI
A2: 45839 | B2: EQ | C2: 1500.6 | D2: 1531.4 | E2: 1500.1 | F2: 1500.6 | G2: 1526.8 | H2: 1528.4 | I2: 1522.95 | J2: 3217.6 | K2: 1114.85 | L2: 10368523 | M2: 1.5790751e+10 | N2: 232573 | O2: 45869 | P2: 45869 | Q2: 1390 | R2: 1404 | S2: 1385.7 | T2: 1390.6 | U2: 1389 | V2: 1390.2 | W2: 14727500 | X2: 20540308450 | Y2: 20540308450 | Z2: 5830500 | AA2: -8584500 | AB2: 45897 | AC2: 45897 | AD2: XX | AE2: - | AF2: 1386.5 | AG2: 1395 | AH2: 1367.3 | AI2: 1387.6 | AJ2: 1394.2 | AK2: 1385.9 | AL2: 22806000 | AM2: 31469543900 | AN2: 31469543900 | AO2: 4499500 | AP2: -11876500 | AQ2: 45930 | AR2: 45930 | AS2: XX | AT2: - | AU2: 1375.5 | AV2: 1378.6 | AW2: 1361.8 | AX2: 1363.2 | AY2: 1362.3 | AZ2: 1364 | BA2: 21123500 | BB2: 28844600300 | BC2: 28844600300 | BD2: 5832000 | BE2: -13515500
A3: 45840 | B3: EQ | C3: 1528.4 | D3: 1530 | E3: 1508.7 | F3: 1528.4 | G3: 1517.1 | H3: 1518.8 | I3: 1518.29 | J3: 3217.6 | K3: 1114.85 | L3: 6361002 | M3: 9.6578444e+09 | N3: 183873 | O3: 45868 | P3: 45869 | Q3: 1417.3 | R3: 1424.8 | S3: 1403.2 | T3: 1410.1 | U3: 1412 | V3: 1410.1 | W3: 19733500 | X3: 27866248000 | Y3: 27866248000 | Z3: 14415000 | AA3: -15248000 | AB3: 45895 | AC3: 45897 | AD3: XX | AE3: - | AF3: 1409.9 | AG3: 1410.2 | AH3: 1383 | AI3: 1386.5 | AJ3: 1384.3 | AK3: 1386.5 | AL3: 30783500 | AM3: 42991506350 | AN3: 42991506350 | AO3: 16376000 | AP3: -25695000 | AQ3: 45929 | AR3: 45930 | AS3: XX | AT3: - | AU3: 1381 | AV3: 1388 | AW3: 1369.2 | AX3: 1374 | AY3: 1372.6 | AZ3: 1374 | BA3: 25911500 | BB3: 35743026500 | BC3: 35743026500 | BD3: 19347500 | BE3: -21428000
A4: 45841 | B4: EQ | C4: 1520.8 | D4: 1531.9 | E4: 1513 | F4: 1518.8 | G4: 1515 | H4: 1517.8 | I4: 1520.57 | J4: 3217.6 | K4: 1114.85 | L4: 11283291 | M4: 1.715698e+10 | N4: 258008 | O4: 45867 | P4: 45869 | Q4: 1387.2 | R4: 1418.9 | S4: 1386.4 | T4: 1416.4 | U4: 1416 | V4: 1416.4 | W4: 23836000 | X4: 33378962800 | Y4: 33378962800 | Z4: 29663000 | AA4: -16522500 | AB4: 45894 | AC4: 45897 | AD4: XX | AE4: - | AF4: 1414.1 | AG4: 1419 | AH4: 1404.6 | AI4: 1412.2 | AJ4: 1413 | AK4: 1412.2 | AL4: 30618500 | AM4: 43237686600 | AN4: 43237686600 | AO4: 42071000 | AP4: -26337500 | AQ4: 45926 | AR4: 45930 | AS4: XX | AT4: - | AU4: 1375 | AV4: 1383.2 | AW4: 1367.4 | AX4: 1376.5 | AY4: 1377.7 | AZ4: 1376.5 | BA4: 33481500 | BB4: 46085667350 | BC4: 46085667350 | BD4: 40775500 | BE4: -27999000
A5: 45842 | B5: EQ | C5: 1524 | D5: 1530 | E5: 1517.2 | F5: 1517.8 | G5: 1528.1 | H5: 1527.3 | I5: 1523.57 | J5: 3217.6 | K5: 1114.85 | L5: 6603501 | M5: 10060908691 | N5: 167255 | O5: 45866 | P5: 45869 | Q5: 1391.9 | R5: 1409.8 | S5: 1386 | T5: 1389.2 | U5: 1389.2 | V5: 1389.2 | W5: 21711500 | X5: 30361334700 | Y5: 30361334700 | Z5: 46185500 | AA5: -15547000 | AB5: 45891 | AC5: 45897 | AD5: XX | AE5: - | AF5: 1423.4 | AG5: 1423.8 | AH5: 1410.2 | AI5: 1411.5 | AJ5: 1411.8 | AK5: 1411.5 | AL5: 27408000 | AM5: 38799426700 | AN5: 38799426700 | AO5: 68408500 | AP5: -20396500 | AQ5: 45925 | AR5: 45930 | AS5: XX | AT5: - | AU5: 1384.3 | AV5: 1386.2 | AW5: 1373.2 | AX5: 1376.6 | AY5: 1377.1 | AZ5: 1376.6 | BA5: 31780000 | BB5: 43841151300 | BC5: 43841151300 | BD5: 68774500 | BE5: -25111500
A6: 45845 | B6: EQ | C6: 1526.6 | D6: 1544.8 | E6: 1525 | F6: 1527.3 | G6: 1540.5 | H6: 1541.5 | I6: 1539.06 | J6: 3217.6 | K6: 1114.85 | L6: 7251074 | M6: 1.1159859e+10 | N6: 205134 | O6: 45863 | P6: 45869 | Q6: 1403.7 | R6: 1403.7 | S6: 1386 | T6: 1393.7 | U6: 1391.9 | V6: 1393.7 | W6: 9721500 | X6: 13574022650 | Y6: 13574022650 | Z6: 61732500 | AA6: -3441000 | AB6: 45890 | AC6: 45897 | AD6: XX | AE6: - | AF6: 1425 | AG6: 1431.7 | AH6: 1420 | AI6: 1424.8 | AJ6: 1423.5 | AK6: 1424.8 | AL6: 14617000 | AM6: 20866139600 | AN6: 20866139600 | AO6: 88805000 | AP6: -7360500 | AQ6: 45924 | AR6: 45930 | AS6: XX | AT6: - | AU6: 1392.5 | AV6: 1399.8 | AW6: 1383.7 | AX6: 1386.7 | AY6: 1384.3 | AZ6: 1386.7 | BA6: 13749500 | BB6: 19133706900 | BC6: 19133706900 | BD6: 93886000 | BE6: -7716500
A7: 45846 | B7: EQ | C7: 1536 | D7: 1544.9 | E7: 1530.2 | F7: 1541.5 | G7: 1538 | H7: 1537.6 | I7: 1536.23 | J7: 3217.6 | K7: 1114.85 | L7: 7171261 | M7: 1.1016684e+10 | N7: 191265 | O7: 45862 | P7: 45869 | Q7: 1424 | R7: 1426.9 | S7: 1398.1 | T7: 1406.6 | U7: 1406.3 | V7: 1406.6 | W7: 11440000 | X7: 16121394700 | Y7: 16121394700 | Z7: 65173500 | AA7: -2145000 | AB7: 45889 | AC7: 45897 | AD7: XX | AE7: - | AF7: 1416 | AG7: 1425 | AH7: 1412.3 | AI7: 1415.5 | AJ7: 1414.6 | AK7: 1415.5 | AL7: 11678000 | AM7: 16568938550 | AN7: 16568938550 | AO7: 96165500 | AP7: -3422500 | AQ7: 45923 | AR7: 45930 | AS7: XX | AT7: - | AU7: 1397 | AV7: 1399.4 | AW7: 1380.9 | AX7: 1394.9 | AY7: 1395.7 | AZ7: 1394.9 | BA7: 14508000 | BB7: 20172911850 | BC7: 20172911850 | BD7: 101602500 | BE7: -5397500
A8: 45847 | B8: EQ | C8: 1536.7 | D8: 1551 | E8: 1510.1 | F8: 1537.6 | G8: 1520.5 | H8: 1519 | I8: 1532.97 | J8: 3217.6 | K8: 1114.85 | L8: 8870660 | M8: 1.3598441e+10 | N8: 254524 | O8: 45861 | P8: 45869 | Q8: 1430 | R8: 1430 | S8: 1418.3 | T8: 1427.1 | U8: 1428.4 | V8: 1427.1 | W8: 8408500 | X8: 11972690200 | Y8: 11972690200 | Z8: 67318500 | AA8: -1247000 | AB8: 45888 | AC8: 45897 | AD8: XX | AE8: - | AF8: 1395 | AG8: 1422.2 | AH8: 1393 | AI8: 1421.2 | AJ8: 1422 | AK8: 1421.2 | AL8: 21663500 | AM8: 30619996350 | AN8: 30619996350 | AO8: 99588000 | AP8: -5489000 | AQ8: 45922 | AR8: 45930 | AS8: XX | AT8: - | AU8: 1409.3 | AV8: 1414.1 | AW8: 1393.2 | AX8: 1395 | AY8: 1394.8 | AZ8: 1395 | BA8: 13279000 | BB8: 18653831100 | BC8: 18653831100 | BD8: 107000000 | BE8: -6206000
A9: 45848 | B9: EQ | C9: 1519.7 | D9: 1524.7 | E9: 1507.5 | F9: 1519 | G9: 1515.2 | H9: 1517.2 | I9: 1516.2 | J9: 3217.6 | K9: 1114.85 | L9: 10047129 | M9: 1.5233458e+10 | N9: 289035 | O9: 45860 | P9: 45869 | Q9: 1430 | R9: 1435.8 | S9: 1414.6 | T9: 1417.3 | U9: 1417.2 | V9: 1417.3 | W9: 11561000 | X9: 16440116650 | Y9: 16440116650 | Z9: 68565500 | AA9: 184500 | AB9: 45887 | AC9: 45897 | AD9: XX | AE9: - | AF9: 1392.8 | AG9: 1398.1 | AH9: 1380.7 | AI9: 1386.6 | AJ9: 1388 | AK9: 1386.6 | AL9: 10647500 | AM9: 14791645300 | AN9: 14791645300 | AO9: 105077000 | AP9: 396500 | AQ9: 45919 | AR9: 45930 | AS9: XX | AT9: - | AU9: 1417 | AV9: 1419.7 | AW9: 1406.1 | AX9: 1412.1 | AY9: 1412.6 | AZ9: 1412.1 | BA9: 10931000 | BB9: 15432459400 | BC9: 15432459400 | BD9: 113206000 | BE9: -1615000
A10: 45849 | B10: EQ | C10: 1512 | D10: 1515 | E10: 1490.3 | F10: 1517.2 | G10: 1495 | H10: 1495.2 | I10: 1496.06 | J10: 3217.6 | K10: 1114.85 | L10: 7234991 | M10: 1.0823983e+10 | N10: 178490 | O10: 45859 | P10: 45869 | Q10: 1470 | R10: 1477.9 | S10: 1427.2 | T10: 1432.4 | U10: 1433 | V10: 1432.4 | W10: 25319500 | X10: 36505715300 | Y10: 36505715300 | Z10: 68381000 | AA10: -836500 | AB10: 45883 | AC10: 45897 | AD10: XX | AE10: - | AF10: 1382.7 | AG10: 1383.8 | AH10: 1374.2 | AI10: 1376.5 | AJ10: 1376 | AK10: 1376.5 | AL10: 6846500 | AM10: 9438320150 | AN10: 9438320150 | AO10: 104680500 | AP10: -155000 | AQ10: 45918 | AR10: 45930 | AS10: XX | AT10: - | AU10: 1420.2 | AV10: 1424.4 | AW10: 1414.6 | AX10: 1418.5 | AY10: 1418.5 | AZ10: 1418.5 | BA10: 10737500 | BB10: 15234381000 | BC10: 15234381000 | BD10: 114821000 | BE10: 37000
A11: 45852 | B11: EQ | C11: 1492.2 | D11: 1500 | E11: 1479.1 | F11: 1495.2 | G11: 1486.4 | H11: 1483.7 | I11: 1487.76 | J11: 3211.7 | K11: 1114.85 | L11: 10311846 | M11: 1.534153e+10 | N11: 186122 | O11: 45856 | P11: 45869 | Q11: 1485.4 | R11: 1489.5 | S11: 1473.7 | T11: 1482.6 | U11: 1480.5 | V11: 1482.6 | W11: 10341500 | X11: 15310524750 | Y11: 15310524750 | Z11: 69217500 | AA11: 2958500 | AB11: 45882 | AC11: 45897 | AD11: XX | AE11: - | AF11: 1387 | AG11: 1390.8 | AH11: 1378 | AI11: 1383.2 | AJ11: 1384 | AK11: 1383.2 | AL11: 11924000 | AM11: 16497004600 | AN11: 16497004600 | AO11: 104835500 | AP11: -3357000 | AQ11: 45917 | AR11: 45930 | AS11: XX | AT11: - | AU11: 1410.9 | AV11: 1419.1 | AW11: 1410 | AX11: 1416.7 | AY11: 1416.1 | AZ11: 1416.7 | BA11: 9563000 | BB11: 13534511450 | BC11: 13534511450 | BD11: 114784000 | BE11: -2166000
A12: 45853 | B12: EQ | C12: 1486.2 | D12: 1496.5 | E12: 1482.4 | F12: 1483.7 | G12: 1488.5 | H12: 1485.4 | I12: 1487.92 | J12: 3211.7 | K12: 1114.85 | L12: 8132454 | M12: 1.2100448e+10 | N12: 173756 | O12: 45855 | P12: 45869 | Q12: 1492.1 | R12: 1493.5 | S12: 1479.4 | T12: 1482.6 | U12: 1484.5 | V12: 1482.6 | W12: 9720500 | X12: 14441875950 | Y12: 14441875950 | Z12: 66259000 | AA12: 298000 | AB12: 45881 | AC12: 45897 | AD12: XX | AE12: - | AF12: 1380.3 | AG12: 1399.3 | AH12: 1375.3 | AI12: 1380 | AJ12: 1379.6 | AK12: 1380 | AL12: 10492500 | AM12: 14560941650 | AN12: 14560941650 | AO12: 108192500 | AP12: -929000 | AQ12: 45916 | AR12: 45930 | AS12: XX | AT12: - | AU12: 1405 | AV12: 1411.7 | AW12: 1403.5 | AX12: 1409.2 | AY12: 1409.5 | AZ12: 1409.2 | BA12: 10225000 | BB12: 14398361800 | BC12: 14398361800 | BD12: 116950000 | BE12: -562000
A13: 45854 | B13: EQ | C13: 1473 | D13: 1491 | E13: 1471.5 | F13: 1485.4 | G13: 1486.2 | H13: 1485.6 | I13: 1481.43 | J13: 3211.7 | K13: 1114.85 | L13: 10409983 | M13: 1.5421637e+10 | N13: 191598 | O13: 45854 | P13: 45869 | Q13: 1485.7 | R13: 1496.5 | S13: 1477.7 | T13: 1489.4 | U13: 1489 | V13: 1489.4 | W13: 7990000 | X13: 11877002200 | Y13: 11877002200 | Z13: 65961000 | AA13: 1306000 | AB13: 45880 | AC13: 45897 | AD13: XX | AE13: - | AF13: 1367 | AG13: 1385 | AH13: 1360 | AI13: 1383.1 | AJ13: 1381.4 | AK13: 1383.1 | AL13: 9437000 | AM13: 12969914450 | AN13: 12969914450 | AO13: 109121500 | AP13: 428500 | AQ13: 45915 | AR13: 45930 | AS13: XX | AT13: - | AU13: 1395.4 | AV13: 1404.5 | AW13: 1393.8 | AX13: 1402.8 | AY13: 1403.5 | AZ13: 1402.8 | BA13: 8075000 | BB13: 11309130450 | BC13: 11309130450 | BD13: 117512000 | BE13: -2278500
... A24: 45869 | B24: EQ | C24: 1388.1 | D24: 1402.6 | E24: 1382.2 | F24: 1410.1 | G24: 1390 | H24: 1390.2 | I24: 1392.63 | J24: 3079.45 | K24: 1114.85 | L24: 17065827 | M24: 2.3766374e+10 | N24: 373516 | O24: 45839 | P24: 45869 | Q24: 1515 | R24: 1535.5 | S24: 1508.4 | T24: 1532.1 | U24: 1531 | V24: 1532.1 | W24: 11030500 | X24: 16842501800 | Y24: 16842501800 | Z24: 71518500 | AA24: 363500 | AB24: 45863 | AC24: 45897 | AD24: XX | AE24: - | AF24: 1404.5 | AG24: 1405.9 | AH24: 1389 | AI24: 1396.1 | AJ24: 1395.5 | AK24: 1396.1 | AL24: 7780000 | AM24: 10882329000 | AN24: 10882329000 | AO24: 56797000 | AP24: 3983500 | AQ24: 45898 | AR24: 45930 | AS24: XX | AT24: - | AU24: 1400.1 | AV24: 1411.9 | AW24: 1358.1 | AX24: 1364.4 | AY24: 1364 | AZ24: 1364.4 | BA24: 33355000 | BB24: 46139470900 | BC24: 46139470900 | BD24: 119389500 | BE24: 2228000
A25: 45870 | B25: EQ | C25: 1386.9 | D25: 1405.9 | E25: 1384.3 | F25: 1390.2 | G25: 1394.1 | H25: 1393.7 | I25: 1397.47 | J25: 3079.45 | K25: 1114.85 | L25: 10321171 | M25: 1.4423489e+10 | N25: 208431 | AB25: 45862 | AC25: 45897 | AD25: XX | AE25: - | AF25: 1427.6 | AG25: 1427.8 | AH25: 1401 | AI25: 1408.6 | AJ25: 1408 | AK25: 1408.6 | AL25: 7227500 | AM25: 10211359750 | AN25: 10211359750 | AO25: 52813500 | AP25: 4571000 | AQ25: 45897 | AR25: 45930 | AS25: XX | AT25: - | AU25: 1396 | AV25: 1401 | AW25: 1375.2 | AX25: 1395.4 | AY25: 1398.1 | AZ25: 1395.4 | BA25: 29560000 | BB25: 41032146000 | BC25: 41032146000 | BD25: 117161500 | BE25: 16864000
A26: 45873 | B26: EQ | C26: 1395.1 | D26: 1416.1 | E26: 1391.7 | F26: 1393.7 | G26: 1410.2 | H26: 1411.5 | I26: 1410.61 | J26: 3079.45 | K26: 1114.85 | L26: 6312820 | M26: 8.9049079e+09 | N26: 188246 | AB26: 45861 | AC26: 45897 | AD26: XX | AE26: - | AF26: 1426.5 | AG26: 1430.5 | AH26: 1420.6 | AI26: 1429.6 | AJ26: 1430.5 | AK26: 1429.6 | AL26: 3121500 | AM26: 4451629450 | AN26: 4451629450 | AO26: 48242500 | AP26: 1016000 | AQ26: 45895 | AR26: 45930 | AS26: XX | AT26: - | AU26: 1418.1 | AV26: 1419 | AW26: 1391.3 | AX26: 1394.2 | AY26: 1393 | AZ26: 1394.2 | BA26: 35113000 | BB26: 49299709900 | BC26: 49299709900 | BD26: 100297500 | BE26: 28444500
A27: 45874 | B27: EQ | C27: 1411 | D27: 1411 | E27: 1388.1 | F27: 1411.5 | G27: 1390 | H27: 1391.7 | I27: 1394.5 | J27: 3079.45 | K27: 1114.85 | L27: 9315972 | M27: 1.2991163e+10 | N27: 238858 | AB27: 45860 | AC27: 45897 | AD27: XX | AE27: - | AF27: 1431.2 | AG27: 1445 | AH27: 1417 | AI27: 1418.9 | AJ27: 1419.6 | AK27: 1418.9 | AL27: 5914000 | AM27: 8422071350 | AN27: 8422071350 | AO27: 47226500 | AP27: 3861500 | AQ27: 45894 | AR27: 45930 | AS27: XX | AT27: - | AU27: 1420 | AV27: 1427.8 | AW27: 1413 | AX27: 1420.7 | AY27: 1421 | AZ27: 1420.7 | BA27: 28654500 | BB27: 40705415800 | BC27: 40705415800 | BD27: 71853000 | BE27: 24863500
A28: 45875 | B28: EQ | C28: 1391.9 | D28: 1395.9 | E28: 1383.3 | F28: 1391.7 | G28: 1393 | H28: 1392.8 | I28: 1390.57 | J28: 3079.45 | K28: 1114.85 | L28: 5834312 | M28: 8113006686 | N28: 156725 | AB28: 45859 | AC28: 45897 | AD28: XX | AE28: - | AF28: 1499 | AG28: 1499 | AH28: 1430 | AI28: 1434.9 | AJ28: 1435 | AK28: 1434.9 | AL28: 9037000 | AM28: 13046012600 | AN28: 13046012600 | AO28: 43365000 | AP28: 6073000 | AQ28: 45891 | AR28: 45930 | AS28: XX | AT28: - | AU28: 1428.1 | AV28: 1432.3 | AW28: 1418.6 | AX28: 1419.8 | AY28: 1420.1 | AZ28: 1419.8 | BA28: 24172000 | BB28: 34418481700 | BC28: 34418481700 | BD28: 46989500 | BE28: 21081500
A29: 45876 | B29: EQ | C29: 1387.7 | D29: 1393.7 | E29: 1366 | F29: 1392.8 | G29: 1391 | H29: 1389.4 | I29: 1381.52 | J29: 3079.45 | K29: 1114.85 | L29: 9976705 | M29: 1.3783048e+10 | N29: 293767 | AB29: 45856 | AC29: 45897 | AD29: XX | AE29: - | AF29: 1488.7 | AG29: 1489.5 | AH29: 1476.4 | AI29: 1484.4 | AJ29: 1482.5 | AK29: 1484.4 | AL29: 3295000 | AM29: 4882839650 | AN29: 4882839650 | AO29: 37292000 | AP29: 2269000 | AQ29: 45890 | AR29: 45930 | AS29: XX | AT29: - | AU29: 1429 | AV29: 1439.8 | AW29: 1429 | AX29: 1433.6 | AY29: 1432.3 | AZ29: 1433.6 | BA29: 6042000 | BB29: 8675161700 | BC29: 8675161700 | BD29: 25908000 | BE29: 4276500
A30: 45877 | B30: EQ | C30: 1385 | D30: 1397.2 | E30: 1365 | F30: 1389.4 | G30: 1366.2 | H30: 1367.8 | I30: 1374.93 | J30: 3079.45 | K30: 1114.85 | L30: 8793606 | M30: 1.2090592e+10 | N30: 208137 | AB30: 45855 | AC30: 45897 | AD30: XX | AE30: - | AF30: 1494.1 | AG30: 1494.1 | AH30: 1481.9 | AI30: 1484.5 | AJ30: 1486 | AK30: 1484.5 | AL30: 2830500 | AM30: 4209770100 | AN30: 4209770100 | AO30: 35023000 | AP30: 2004500 | AQ30: 45889 | AR30: 45930 | AS30: XX | AT30: - | AU30: 1427.9 | AV30: 1433.4 | AW30: 1420.6 | AX30: 1423.9 | AY30: 1423 | AZ30: 1423.9 | BA30: 3320500 | BB30: 4737794200 | BC30: 4737794200 | BD30: 21631500 | BE30: 2260000
A31: 45880 | B31: EQ | C31: 1370 | D31: 1388 | E31: 1361.2 | F31: 1367.8 | G31: 1384.6 | H31: 1386.2 | I31: 1375.78 | J31: 3079.45 | K31: 1114.85 | L31: 9997486 | M31: 1.3754351e+10 | N31: 226304 | AB31: 45854 | AC31: 45897 | AD31: XX | AE31: - | AF31: 1491 | AG31: 1498 | AH31: 1480.7 | AI31: 1491.8 | AJ31: 1491.5 | AK31: 1491.8 | AL31: 1292500 | AM31: 1924067400 | AN31: 1924067400 | AO31: 33018500 | AP31: 542500 | AQ31: 45888 | AR31: 45930 | AS31: XX | AT31: - | AU31: 1400 | AV31: 1430.5 | AW31: 1400 | AX31: 1429.5 | AY31: 1430.4 | AZ31: 1429.5 | BA31: 3914500 | BB31: 5564990150 | BC31: 5564990150 | BD31: 19371500 | BE31: 1455500
A32: 45881 | B32: EQ | C32: 1381.9 | D32: 1401.9 | E32: 1375.2 | F32: 1386.2 | G32: 1381 | H32: 1380.4 | I32: 1386.76 | J32: 3079.45 | K32: 1114.85 | L32: 12244664 | M32: 1.6980369e+10 | N32: 179433 | AB32: 45853 | AC32: 45897 | AD32: XX | AE32: - | AF32: 1494 | AG32: 1503.8 | AH32: 1490.6 | AI32: 1492.2 | AJ32: 1496.2 | AK32: 1492.2 | AL32: 1192500 | AM32: 1783993750 | AN32: 1783993750 | AO32: 32476000 | AP32: 718500 | AQ32: 45887 | AR32: 45930 | AS32: XX | AT32: - | AU32: 1400 | AV32: 1422.4 | AW32: 1388.9 | AX32: 1393.6 | AY32: 1396 | AZ32: 1393.6 | BA32: 2828000 | BB32: 3947155500 | BC32: 3947155500 | BD32: 17916000 | BE32: 1774000
A33: 45882 | B33: EQ | C33: 1388 | D33: 1391.8 | E33: 1377.5 | F33: 1380.4 | G33: 1384 | H33: 1382.6 | I33: 1384.19 | J33: 3079.45 | K33: 1114.85 | L33: 7457021 | M33: 1.0321969e+10 | N33: 208576 | AB33: 45852 | AC33: 45897 | AD33: XX | AE33: - | AF33: 1499 | AG33: 1507.6 | AH33: 1487 | AI33: 1492.1 | AJ33: 1493.5 | AK33: 1492.1 | AL33: 2275500 | AM33: 3406344700 | AN33: 3406344700 | AO33: 31757500 | AP33: 1436000 | AQ33: 45883 | AR33: 45930 | AS33: XX | AT33: - | AU33: 1390 | AV33: 1391.9 | AW33: 1382.4 | AX33: 1384.2 | AY33: 1384.2 | AZ33: 1384.2 | BA33: 889000 | BB33: 1232960750 | BC33: 1232960750 | BD33: 16142000 | BE33: 508000
A34: 45883 | B34: EQ | C34: 1377.3 | D34: 1380.7 | E34: 1370.1 | F34: 1382.6 | G34: 1372.9 | H34: 1373.8 | I34: 1375.17 | J34: 3079.45 | K34: 1114.85 | L34: 7126128 | M34: 9.7996295e+09 | N34: 175588 | AB34: 45849 | AC34: 45897 | AD34: XX | AE34: - | AF34: 1519.5 | AG34: 1520.3 | AH34: 1499 | AI34: 1503.3 | AJ34: 1503 | AK34: 1503.3 | AL34: 1405000 | AM34: 2114088500 | AN34: 2114088500 | AO34: 30321500 | AP34: 970500 | AQ34: 45882 | AR34: 45930 | AS34: XX | AT34: - | AU34: 1391.3 | AV34: 1398.4 | AW34: 1385.4 | AX34: 1390.7 | AY34: 1392 | AZ34: 1390.7 | BA34: 1907500 | BB34: 2654302350 | BC34: 2654302350 | BD34: 15634000 | BE34: 1337500
A35: 45887 | B35: EQ | C35: 1390 | D35: 1394.9 | E35: 1377 | F35: 1373.8 | G35: 1382.9 | H35: 1381.7 | I35: 1384.21 | J35: 3079.45 | K35: 1114.85 | L35: 11785109 | M35: 1.6313019e+10 | N35: 319844 | AB35: 45848 | AC35: 45897 | AD35: XX | AE35: - | AF35: 1520.1 | AG35: 1530.7 | AH35: 1515.3 | AI35: 1522.5 | AJ35: 1522.3 | AK35: 1522.5 | AL35: 1007500 | AM35: 1533242800 | AN35: 1533242800 | AO35: 29351000 | AP35: 531000 | AQ35: 45881 | AR35: 45930 | AS35: XX | AT35: - | AU35: 1385.5 | AV35: 1406.9 | AW35: 1383 | AX35: 1387.8 | AY35: 1387.5 | AZ35: 1387.8 | BA35: 1646000 | BB35: 2294832800 | BC35: 2294832800 | BD35: 14296500 | BE35: 677000
A36: 45888 | B36: EQ | C36: 1390 | D36: 1421 | E36: 1389.1 | F36: 1381.7 | G36: 1421 | H36: 1420.1 | I36: 1413.6 | J36: 3079.45 | K36: 1114.85 | L36: 14384719 | M36: 2.0334297e+10 | N36: 288664 | AB36: 45847 | AC36: 45897 | AD36: XX | AE36: - | AF36: 1551 | AG36: 1558.5 | AH36: 1517.5 | AI36: 1528.1 | AJ36: 1528.8 | AK36: 1528.1 | AL36: 1589500 | AM36: 2443367000 | AN36: 2443367000 | AO36: 28820000 | AP36: 600500 | AQ36: 45880 | AR36: 45930 | AS36: XX | AT36: - | AU36: 1374 | AV36: 1392.6 | AW36: 1367.5 | AX36: 1390.4 | AY36: 1389.4 | AZ36: 1390.4 | BA36: 1116000 | BB36: 1540576350 | BC36: 1540576350 | BD36: 13619500 | BE36: 242000
... A42: 45897 | B42: EQ | C42: 1389.9 | D42: 1392.2 | E42: 1366.5 | F42: 1384.9 | G42: 1390.9 | H42: 1385.9 | I42: 1380.78 | J42: 3079.45 | K42: 1114.85 | L42: 13161813 | M42: 18173599832 | N42: 252423 | AB42: 45839 | AC42: 45897 | AD42: XX | AE42: - | AF42: 1518.8 | AG42: 1539 | AH42: 1514 | AI42: 1536.2 | AJ42: 1535.5 | AK42: 1536.2 | AL42: 741000 | AM42: 1135305850 | AN42: 1135305850 | AO42: 27254000 | AP42: -199000 | AQ42: 45870 | AR42: 45930 | AS42: XX | AT42: - | AU42: 1399 | AV42: 1413 | AW42: 1392.5 | AX42: 1400.6 | AY42: 1401 | AZ42: 1400.6 | BA42: 557000 | BB42: 783011600 | BC42: 783011600 | BD42: 12629000 | BE42: -12500
A43: 45898 | B43: EQ | C43: 1381.1 | D43: 1403.5 | E43: 1350 | F43: 1385.9 | G43: 1356 | H43: 1357.2 | I43: 1375.14 | J43: 3079.45 | K43: 1114.85 | L43: 18758842 | M43: 2.5796085e+10 | N43: 348532 | AQ43: 45869 | AR43: 45930 | AS43: XX | AT43: - | AU43: 1400 | AV43: 1412.1 | AW43: 1390.1 | AX43: 1400.5 | AY43: 1401.1 | AZ43: 1400.5 | BA43: 1138500 | BB43: 1595849300 | BC43: 1595849300 | BD43: 12641500 | BE43: 577500
A44: 45901 | B44: EQ | C44: 1356 | D44: 1363.2 | E44: 1340.6 | F44: 1357.2 | G44: 1355 | H44: 1353.9 | I44: 1353.99 | J44: 3066.95 | K44: 1114.85 | L44: 11232238 | M44: 1.5208377e+10 | N44: 249574 | AQ44: 45868 | AR44: 45930 | AS44: XX | AT44: - | AU44: 1432 | AV44: 1436 | AW44: 1413.6 | AX44: 1419.9 | AY44: 1422 | AZ44: 1419.9 | BA44: 2873000 | BB44: 4086745700 | BC44: 4086745700 | BD44: 12064000 | BE44: 2527500
A45: 45902 | B45: EQ | C45: 1354.8 | D45: 1384.5 | E45: 1354.5 | F45: 1353.9 | G45: 1367.5 | H45: 1366.5 | I45: 1374.28 | J45: 3066.95 | K45: 1114.85 | L45: 11517006 | M45: 1.582762e+10 | N45: 235433 | AQ45: 45867 | AR45: 45930 | AS45: XX | AT45: - | AU45: 1400.1 | AV45: 1428.8 | AW45: 1398 | AX45: 1427.2 | AY45: 1425.7 | AZ45: 1427.2 | BA45: 4449500 | BB45: 6254946500 | BC45: 6254946500 | BD45: 9536500 | BE45: 3904000
A46: 45903 | B46: EQ | C46: 1369.7 | D46: 1376.5 | E46: 1360.5 | F46: 1366.5 | G46: 1372 | H46: 1372.6 | I46: 1368.85 | J46: 3066.95 | K46: 1114.85 | L46: 7847563 | M46: 1.0742162e+10 | N46: 209277 | AQ46: 45866 | AR46: 45930 | AS46: XX | AT46: - | AU46: 1401 | AV46: 1419 | AW46: 1397.8 | AX46: 1399.7 | AY46: 1399.5 | AZ46: 1399.7 | BA46: 1164000 | BB46: 1644518550 | BC46: 1644518550 | BD46: 5632500 | BE46: 856000
A47: 45904 | B47: EQ | C47: 1371.8 | D47: 1374 | E47: 1357.1 | F47: 1372.6 | G47: 1359.1 | H47: 1359.3 | I47: 1363.97 | J47: 3066.95 | K47: 1114.85 | L47: 13223177 | M47: 1.8035989e+10 | N47: 200473 | AQ47: 45863 | AR47: 45930 | AS47: XX | AT47: - | AU47: 1410 | AV47: 1414 | AW47: 1397.2 | AX47: 1404.4 | AY47: 1404.6 | AZ47: 1404.4 | BA47: 420500 | BB47: 591695800 | BC47: 591695800 | BD47: 4776500 | BE47: 167000
A48: 45905 | B48: EQ | C48: 1363 | D48: 1381 | E48: 1359.3 | F48: 1359.3 | G48: 1375.7 | H48: 1375 | I48: 1370.36 | J48: 3066.95 | K48: 1114.85 | L48: 5777575 | M48: 7.9173738e+09 | N48: 142951 | AQ48: 45862 | AR48: 45930 | AS48: XX | AT48: - | AU48: 1433.3 | AV48: 1434.3 | AW48: 1409.6 | AX48: 1416.6 | AY48: 1416.7 | AZ48: 1416.6 | BA48: 480500 | BB48: 682288400 | BC48: 682288400 | BD48: 4609500 | BE48: 258500
A49: 45908 | B49: EQ | C49: 1380 | D49: 1386 | E49: 1372.4 | F49: 1375 | G49: 1378.9 | H49: 1378.5 | I49: 1379.43 | J49: 3066.95 | K49: 1114.85 | L49: 6986720 | M49: 9.6376805e+09 | N49: 131052 | AQ49: 45861 | AR49: 45930 | AS49: XX | AT49: - | AU49: 1434.6 | AV49: 1438.4 | AW49: 1429.4 | AX49: 1437.4 | AY49: 1438.2 | AZ49: 1437.4 | BA49: 250000 | BB49: 358422800 | BC49: 358422800 | BD49: 4351000 | BE49: 63500
A50: 45909 | B50: EQ | C50: 1376.6 | D50: 1381.2 | E50: 1368.7 | F50: 1378.5 | G50: 1376.1 | H50: 1376.2 | I50: 1375.44 | J50: 3066.95 | K50: 1114.85 | L50: 9754452 | M50: 1.3416676e+10 | N50: 209637 | AQ50: 45860 | AR50: 45930 | AS50: XX | AT50: - | AU50: 1444.2 | AV50: 1446.7 | AW50: 1425.4 | AX50: 1426.7 | AY50: 1427.6 | AZ50: 1426.7 | BA50: 475000 | BB50: 680467100 | BC50: 680467100 | BD50: 4287500 | BE50: 259000
A51: 45910 | B51: EQ | C51: 1383.9 | D51: 1388.5 | E51: 1374.1 | F51: 1376.2 | G51: 1377.5 | H51: 1377 | I51: 1380.12 | J51: 3066.95 | K51: 1114.85 | L51: 7790815 | M51: 1.0752267e+10 | N51: 222655 | AQ51: 45859 | AR51: 45930 | AS51: XX | AT51: - | AU51: 1480 | AV51: 1483.7 | AW51: 1438.8 | AX51: 1443.7 | AY51: 1444.2 | AZ51: 1443.7 | BA51: 912000 | BB51: 1323491400 | BC51: 1323491400 | BD51: 4028500 | BE51: 707500
A52: 45911 | B52: EQ | C52: 1376 | D52: 1385.5 | E52: 1375 | F52: 1377 | G52: 1382.1 | H52: 1383.3 | I52: 1382.49 | J52: 3066.95 | K52: 1114.85 | L52: 9766072 | M52: 1.3501479e+10 | N52: 173431 | AQ52: 45856 | AR52: 45930 | AS52: XX | AT52: - | AU52: 1494.9 | AV52: 1498 | AW52: 1484.7 | AX52: 1493.5 | AY52: 1494 | AZ52: 1493.5 | BA52: 164500 | BB52: 245321000 | BC52: 245321000 | BD52: 3321000 | BE52: 65500
A53: 45912 | B53: EQ | C53: 1383.3 | D53: 1396.3 | E53: 1380.5 | F53: 1383.3 | G53: 1395 | H53: 1395 | I53: 1392.69 | J53: 3066.95 | K53: 1114.85 | L53: 7403368 | M53: 1.0310608e+10 | N53: 156369 | AQ53: 45855 | AR53: 45930 | AS53: XX | AT53: - | AU53: 1504.5 | AV53: 1504.5 | AW53: 1490.8 | AX53: 1493.3 | AY53: 1494.8 | AZ53: 1493.3 | BA53: 2204000 | BB53: 3299112300 | BC53: 3299112300 | BD53: 3255500 | BE53: 2061000
A54: 45915 | B54: EQ | C54: 1393 | D54: 1400.8 | E54: 1388.6 | F54: 1395 | G54: 1399.3 | H54: 1399.3 | I54: 1395.97 | J54: 3066.95 | K54: 1114.85 | L54: 5396697 | M54: 7.5336358e+09 | N54: 130728 | AQ54: 45854 | AR54: 45930 | AS54: XX | AT54: - | AU54: 1490 | AV54: 1507 | AW54: 1490 | AX54: 1501 | AY54: 1500.2 | AZ54: 1501 | BA54: 139000 | BB54: 207973450 | BC54: 207973450 | BD54: 1194500 | BE54: 48500
... A65: 45930 | B65: EQ | C65: 1377.1 | D65: 1377.1 | E65: 1362.8 | F65: 1372.8 | G65: 1364 | H65: 1364 | I65: 1366.52 | J65: 3049.95 | K65: 1114.85 | L65: 14604684 | M65: 1.9957582e+10 | N65: 223375 | AQ65: 45839 | AR65: 45930 | AS65: XX | AT65: - | AU65: 1526.6 | AV65: 1547.6 | AW65: 1523.8 | AX65: 1544.4 | AY65: 1544 | AZ65: 1544.4 | BA65: 130000 | BB65: 200063600 | BC65: 200063600 | BD65: 139500 | BE65: -5500

Sheet Raw_Data_Adani
A1: Date | B1: series | C1: OPEN | D1: HIGH | E1: LOW | F1: PREV. CLOSE | G1: ltp | H1: close | I1: vwap | J1: 52W H | K1: 52W L | L1: VOLUME | M1: VALUE | N1: No of trades | O1: DATE | P1: EXPIRY DATE | Q1: OPEN PRICE | R1: HIGH PRICE | S1: LOW PRICE | T1: CLOSE PRICE | U1: LAST PRICE | V1: SETTLE PRICE | W1: Volume | X1: VALUE | Y1: PREMIUM VALUE | Z1: OPEN INTEREST | AA1: CHANGE IN OI | AB1: DATE | AC1: EXPIRY DATE | AD1: OPTION TYPE | AE1: STRIKE PRICE | AF1: OPEN PRICE | AG1: HIGH PRICE | AH1: LOW PRICE | AI1: CLOSE PRICE | AJ1: LAST PRICE | AK1: SETTLE PRICE | AL1: Volume | AM1: VALUE | AN1: PREMIUM VALUE | AO1: OPEN INTEREST | AP1: CHANGE IN OI | AQ1: DATE | AR1: EXPIRY DATE | AS1: OPTION TYPE | AT1: STRIKE PRICE | AU1: OPEN PRICE | AV1: HIGH PRICE | AW1: LOW PRICE | AX1: CLOSE PRICE | AY1: LAST PRICE | AZ1: SETTLE PRICE | BA1: Volume | BB1: VALUE | BC1: PREMIUM VALUE | BD1: OPEN INTEREST | BE1: CHANGE IN OI
A2: 45930 | B2: EQ | C2: 2522 | D2: 2535 | E2: 2490.6 | F2: 2509.5 | G2: 2509 | H2: 2505.9 | I2: 2512.97 | J2: 3211 | K2: 2025 | L2: 7,12,592 | M2: 1,79,07,19,447.80 | N2: 38461 | O2: 45869 | P2: 45869 | Q2: 2505 | R2: 2519.8 | S2: 2418.7 | T2: 2425.6 | U2: 2424.9 | V2: 2430.7 | W2: 37,73,700 | X2: 9,35,54,00,490.00 | Y2: 9,35,54,00,490.00 | Z2: 11,76,000 | AA2: -21,11,100 | AB2: 45897 | AC2: 45897 | AD2: XX | AE2: - | AF2: 2240 | AG2: 2325 | AH2: 2223.9 | AI2: 2273.4 | AJ2: 2278 | AK2: 2275.1 | AL2: 46,85,700 | AM2: 10,74,47,37,030.00 | AN2: 10,74,47,37,030.00 | AO2: 10,80,000 | AP2: -28,74,300 | AQ2: 45930 | AR2: 45930 | AS2: XX | AT2: - | AU2: 2520.2 | AV2: 2538.8 | AW2: 2490.4 | AX2: 2503.4 | AY2: 2511 | AZ2: 2505.9 | BA2: 33,96,300 | BB2: 8,52,98,84,760.00 | BC2: 8,52,98,84,760.00 | BD2: 11,13,600 | BE2: -17,35,800
A3: 45929 | B3: EQ | C3: 2543.7 | D3: 2555 | E3: 2505 | F3: 2543.7 | G3: 2521 | H3: 2509.5 | I3: 2528.21 | J3: 3211 | K3: 2025 | L3: 10,12,402 | M3: 2,55,95,63,054.80 | N3: 48219 | O3: 45868 | P3: 45869 | Q3: 2548.7 | R3: 2552.5 | S3: 2524.4 | T3: 2531.9 | U3: 2531.7 | V3: 2531.9 | W3: 44,52,000 | X3: 11,31,28,89,270.00 | Y3: 11,31,28,89,270.00 | Z3: 32,87,100 | AA3: -39,48,900 | AB3: 45895 | AC3: 45897 | AD3: XX | AE3: - | AF3: 2281.6 | AG3: 2300.4 | AH3: 2247.1 | AI3: 2270.6 | AJ3: 2298 | AK3: 2270.6 | AL3: 50,49,300 | AM3: 11,46,76,99,440.00 | AN3: 11,46,76,99,440.00 | AO3: 39,54,300 | AP3: -37,42,800 | AQ3: 45929 | AR3: 45930 | AS3: XX | AT3: - | AU3: 2548.6 | AV3: 2558.1 | AW3: 2511.1 | AX3: 2516 | AY3: 2519.6 | AZ3: 2516 | BA3: 30,32,100 | BB3: 7,69,89,22,530.00 | BC3: 7,69,89,22,530.00 | BD3: 28,49,400 | BE3: -17,29,200
A4: 45926 | B4: EQ | C4: 2572.8 | D4: 2605 | E4: 2535 | F4: 2576.4 | G4: 2535.6 | H4: 2543.7 | I4: 2570.86 | J4: 3211 | K4: 2025 | L4: 10,37,808 | M4: 2,66,80,58,103.20 | N4: 46432 | O4: 45867 | P4: 45869 | Q4: 2525.5 | R4: 2561.1 | S4: 2505.7 | T4: 2552.4 | U4: 2551.1 | V4: 2552.4 | W4: 58,39,500 | X4: 14,78,57,36,490.00 | Y4: 14,78,57,36,490.00 | Z4: 72,36,000 | AA4: -46,37,400 | AB4: 45894 | AC4: 45897 | AD4: XX | AE4: - | AF4: 2350 | AG4: 2350 | AH4: 2298.3 | AI4: 2301.7 | AJ4: 2301.6 | AK4: 2301.7 | AL4: 49,32,600 | AM4: 11,44,50,27,330.00 | AN4: 11,44,50,27,330.00 | AO4: 76,97,100 | AP4: -35,37,600 | AQ4: 45926 | AR4: 45930 | AS4: XX | AT4: - | AU4: 2580.1 | AV4: 2612.6 | AW4: 2537.4 | AX4: 2544.4 | AY4: 2540.7 | AZ4: 2544.4 | BA4: 46,14,300 | BB4: 11,86,72,46,040.00 | BC4: 11,86,72,46,040.00 | BD4: 45,78,600 | BE4: -33,21,600
A5: 45925 | B5: EQ | C5: 2625 | D5: 2647.9 | E5: 2567 | F5: 2619.8 | G5: 2573.3 | H5: 2576.4 | I5: 2608.32 | J5: 3211 | K5: 2025 | L5: 14,89,682 | M5: 3,88,55,60,965.20 | N5: 50400 | O5: 45866 | P5: 45869 | Q5: 2554.4 | R5: 2589 | S5: 2513.8 | T5: 2524.7 | U5: 2526 | V5: 2524.7 | W5: 45,32,100 | X5: 11,56,74,66,720.00 | Y5: 11,56,74,66,720.00 | Z5: 1,18,73,400 | AA5: -30,97,200 | AB5: 45891 | AC5: 45897 | AD5: XX | AE5: - | AF5: 2369.4 | AG5: 2377.5 | AH5: 2320.5 | AI5: 2323.6 | AJ5: 2327.4 | AK5: 2323.6 | AL5: 55,00,800 | AM5: 12,85,41,85,890.00 | AN5: 12,85,41,85,890.00 | AO5: 1,12,34,700 | AP5: -37,97,700 | AQ5: 45925 | AR5: 45930 | AS5: XX | AT5: - | AU5: 2621.7 | AV5: 2654 | AW5: 2576.3 | AX5: 2586 | AY5: 2581.9 | AZ5: 2586 | BA5: 49,46,100 | BB5: 12,97,83,63,270.00 | BC5: 12,97,83,63,270.00 | BD5: 79,00,200 | BE5: -33,14,100
A6: 45924 | B6: EQ | C6: 2655 | D6: 2676 | E6: 2614.4 | F6: 2676.4 | G6: 2624 | H6: 2619.8 | I6: 2647.88 | J6: 3211 | K6: 2025 | L6: 17,20,785 | M6: 4,55,64,38,133.60 | N6: 60770 | O6: 45863 | P6: 45869 | Q6: 2606.3 | R6: 2623.9 | S6: 2543.7 | T6: 2550.1 | U6: 2550 | V6: 2550.1 | W6: 30,74,100 | X6: 7,88,12,44,860.00 | Y6: 7,88,12,44,860.00 | Z6: 1,49,70,600 | AA6: -17,88,000 | AB6: 45890 | AC6: 45897 | AD6: XX | AE6: - | AF6: 2384.6 | AG6: 2397 | AH6: 2373.1 | AI6: 2378.2 | AJ6: 2378.4 | AK6: 2378.2 | AL6: 17,97,600 | AM6: 4,28,57,37,240.00 | AN6: 4,28,57,37,240.00 | AO6: 1,50,32,400 | AP6: -7,62,300 | AQ6: 45924 | AR6: 45930 | AS6: XX | AT6: - | AU6: 2661 | AV6: 2684.5 | AW6: 2623.7 | AX6: 2628.7 | AY6: 2630.2 | AZ6: 2628.7 | BA6: 24,45,300 | BB6: 6,49,02,28,680.00 | BC6: 6,49,02,28,680.00 | BD6: 1,12,14,300 | BE6: -4,35,300
A7: 45923 | B7: EQ | C7: 2642.6 | D7: 2695 | E7: 2593 | F7: 2629.5 | G7: 2666 | H7: 2676.4 | I7: 2665.79 | J7: 3211 | K7: 2025 | L7: 56,10,022 | M7: 14,95,51,50,460.50 | N7: 1,67,336 | O7: 45862 | P7: 45869 | Q7: 2615.1 | R7: 2632.6 | S7: 2600 | T7: 2613.1 | U7: 2612.9 | V7: 2613.1 | W7: 12,67,800 | X7: 3,31,31,09,880.00 | Y7: 3,31,31,09,880.00 | Z7: 1,67,58,600 | AA7: -4,23,300 | AB7: 45889 | AC7: 45897 | AD7: XX | AE7: - | AF7: 2381.5 | AG7: 2406.7 | AH7: 2375.6 | AI7: 2386.4 | AJ7: 2382.5 | AK7: 2386.4 | AL7: 20,31,000 | AM7: 4,85,54,27,520.00 | AN7: 4,85,54,27,520.00 | AO7: 1,57,94,700 | AP7: -4,06,800 | AQ7: 45923 | AR7: 45930 | AS7: XX | AT7: - | AU7: 2643.9 | AV7: 2697 | AW7: 2597.6 | AX7: 2677.4 | AY7: 2671 | AZ7: 2677.4 | BA7: 61,33,800 | BB7: 16,33,78,89,840.00 | BC7: 16,33,78,89,840.00 | BD7: 1,16,49,600 | BE7: -13,01,700
A8: 45922 | B8: EQ | C8: 2535 | D8: 2659 | E8: 2522.1 | F8: 2524 | G8: 2624.5 | H8: 2629.5 | I8: 2615.49 | J8: 3211 | K8: 2025 | L8: 70,22,985 | M8: 18,36,85,42,067.50 | N8: 2,00,598 | O8: 45861 | P8: 45869 | Q8: 2603.4 | R8: 2633 | S8: 2599.4 | T8: 2621.8 | U8: 2626.4 | V8: 2621.8 | W8: 10,22,400 | X8: 2,67,89,84,520.00 | Y8: 2,67,89,84,520.00 | Z8: 1,71,81,900 | AA8: -1,68,600 | AB8: 45888 | AC8: 45897 | AD8: XX | AE8: - | AF8: 2333.9 | AG8: 2396.8 | AH8: 2318 | AI8: 2388.9 | AJ8: 2381.5 | AK8: 2388.9 | AL8: 24,45,000 | AM8: 5,79,55,23,450.00 | AN8: 5,79,55,23,450.00 | AO8: 1,62,01,500 | AP8: -5,29,200 | AQ8: 45922 | AR8: 45930 | AS8: XX | AT8: - | AU8: 2538.9 | AV8: 2670 | AW8: 2526.5 | AX8: 2637.8 | AY8: 2632.5 | AZ8: 2637.8 | BA8: 76,47,300 | BB8: 20,02,56,29,760.00 | BC8: 20,02,56,29,760.00 | BD8: 1,29,51,300 | BE8: -15,78,300
A9: 45919 | B9: EQ | C9: 2495 | D9: 2579 | E9: 2466.1 | F9: 2402 | G9: 2528 | H9: 2524 | I9: 2520.01 | J9: 3211 | K9: 2025 | L9: 79,65,135 | M9: 20,07,22,48,387.70 | N9: 2,38,677 | O9: 45860 | P9: 45869 | Q9: 2633.2 | R9: 2636.3 | S9: 2586.9 | T9: 2594.5 | U9: 2599.4 | V9: 2594.5 | W9: 9,60,600 | X9: 2,50,51,97,940.00 | Y9: 2,50,51,97,940.00 | Z9: 1,73,50,500 | AA9: -42600 | AB9: 45887 | AC9: 45897 | AD9: XX | AE9: - | AF9: 2305.9 | AG9: 2363.2 | AH9: 2302 | AI9: 2334.5 | AJ9: 2326.6 | AK9: 2334.5 | AL9: 24,21,600 | AM9: 5,66,57,56,710.00 | AN9: 5,66,57,56,710.00 | AO9: 1,67,30,700 | AP9: -2,76,000 | AQ9: 45919 | AR9: 45930 | AS9: XX | AT9: - | AU9: 2470 | AV9: 2589.4 | AW9: 2470 | AX9: 2533.1 | AY9: 2535 | AZ9: 2533.1 | BA9: 1,24,22,700 | BB9: 31,37,77,09,350.00 | BC9: 31,37,77,09,350.00 | BD9: 1,45,29,600 | BE9: -64500
A10: 45918 | B10: EQ | C10: 2414.5 | D10: 2438 | E10: 2388.4 | F10: 2402 | G10: 2402 | H10: 2402 | I10: 2409.55 | J10: 3211 | K10: 2025 | L10: 7,03,730 | M10: 1,69,56,70,672.20 | N10: 35404 | O10: 45859 | P10: 45869 | Q10: 2604.7 | R10: 2628.9 | S10: 2592 | T10: 2625.8 | U10: 2623.8 | V10: 2625.8 | W10: 11,12,100 | X10: 2,91,45,84,900.00 | Y10: 2,91,45,84,900.00 | Z10: 1,73,93,100 | AA10: -2,54,700 | AB10: 45883 | AC10: 45897 | AD10: XX | AE10: - | AF10: 2290.7 | AG10: 2308 | AH10: 2272.9 | AI10: 2283 | AJ10: 2282.2 | AK10: 2283 | AL10: 15,04,200 | AM10: 3,44,17,50,330.00 | AN10: 3,44,17,50,330.00 | AO10: 1,70,06,700 | AP10: -1,68,000 | AQ10: 45918 | AR10: 45930 | AS10: XX | AT10: - | AU10: 2416.4 | AV10: 2449 | AW10: 2397.4 | AX10: 2412.9 | AY10: 2413 | AZ10: 2412.9 | BA10: 24,23,100 | BB10: 5,87,50,00,710.00 | BC10: 5,87,50,00,710.00 | BD10: 1,45,94,100 | BE10: 1,11,900
A11: 45917 | B11: EQ | C11: 2417 | D11: 2417 | E11: 2391 | F11: 2399.4 | G11: 2408 | H11: 2402 | I11: 2402.5 | J11: 3211 | K11: 2025 | L11: 5,14,354 | M11: 1,23,57,34,218.70 | N11: 30311 | O11: 45856 | P11: 45869 | Q11: 2625.4 | R11: 2636.7 | S11: 2591.7 | T11: 2604.7 | U11: 2605 | V11: 2604.7 | W11: 13,68,900 | X11: 3,56,98,66,440.00 | Y11: 3,56,98,66,440.00 | Z11: 1,76,47,800 | AA11: 26700 | AB11: 45882 | AC11: 45897 | AD11: XX | AE11: - | AF11: 2300.2 | AG11: 2318.4 | AH11: 2248.1 | AI11: 2288 | AJ11: 2294.7 | AK11: 2288 | AL11: 21,34,800 | AM11: 4,87,44,24,390.00 | AN11: 4,87,44,24,390.00 | AO11: 1,71,74,700 | AP11: -75600 | AQ11: 45917 | AR11: 45930 | AS11: XX | AT11: - | AU11: 2414.8 | AV11: 2420.7 | AW11: 2397.7 | AX11: 2409.6 | AY11: 2411 | AZ11: 2409.6 | BA11: 12,73,200 | BB11: 3,06,77,61,510.00 | BC11: 3,06,77,61,510.00 | BD11: 1,44,82,200 | BE11: -1,56,600
A12: 45916 | B12: EQ | C12: 2410 | D12: 2415.8 | E12: 2388 | F12: 2383.4 | G12: 2401 | H12: 2399.4 | I12: 2398.04 | J12: 3211 | K12: 2025 | L12: 7,52,979 | M12: 1,80,56,72,317.40 | N12: 33207 | O12: 45855 | P12: 45869 | Q12: 2620 | R12: 2665.3 | S12: 2610.1 | T12: 2626.4 | U12: 2627.4 | V12: 2626.4 | W12: 26,42,100 | X12: 6,97,94,30,910.00 | Y12: 6,97,94,30,910.00 | Z12: 1,76,21,100 | AA12: -1,71,300 | AB12: 45881 | AC12: 45897 | AD12: XX | AE12: - | AF12: 2277.9 | AG12: 2317.5 | AH12: 2270.2 | AI12: 2292.4 | AJ12: 2295.1 | AK12: 2292.4 | AL12: 16,83,600 | AM12: 3,86,00,50,800.00 | AN12: 3,86,00,50,800.00 | AO12: 1,72,50,300 | AP12: -1,62,600 | AQ12: 45916 | AR12: 45930 | AS12: XX | AT12: - | AU12: 2413.1 | AV12: 2418 | AW12: 2392.6 | AX12: 2408.7 | AY12: 2408.2 | AZ12: 2408.7 | BA12: 12,33,000 | BB12: 2,96,33,09,160.00 | BC12: 2,96,33,09,160.00 | BD12: 1,46,38,800 | BE12: 1,41,900
A13: 45915 | B13: EQ | C13: 2392 | D13: 2402.8 | E13: 2378.1 | F13: 2392 | G13: 2381 | H13: 2383.4 | I13: 2389.59 | J13: 3211 | K13: 2025 | L13: 2,98,129 | M13: 71,24,05,119.00 | N13: 20087 | O13: 45854 | P13: 45869 | Q13: 2619.2 | R13: 2630.6 | S13: 2598.8 | T13: 2617.5 | U13: 2619.8 | V13: 2617.5 | W13: 12,55,200 | X13: 3,28,64,60,820.00 | Y13: 3,28,64,60,820.00 | Z13: 1,77,92,400 | AA13: 23700 | AB13: 45880 | AC13: 45897 | AD13: XX | AE13: - | AF13: 2191.9 | AG13: 2311.9 | AH13: 2187.5 | AI13: 2289.6 | AJ13: 2280 | AK13: 2289.6 | AL13: 38,17,800 | AM13: 8,62,42,30,740.00 | AN13: 8,62,42,30,740.00 | AO13: 1,74,12,900 | AP13: -1,71,600 | AQ13: 45915 | AR13: 45930 | AS13: XX | AT13: - | AU13: 2402.7 | AV13: 2408.9 | AW13: 2385.2 | AX13: 2392.2 | AY13: 2392.7 | AZ13: 2392.2 | BA13: 5,92,200 | BB13: 1,41,87,48,420.00 | BC13: 1,41,87,48,420.00 | BD13: 1,44,96,900 | BE13: -20400
A14: 45912 | B14: EQ | C14: 2416.9 | D14: 2421.6 | E14: 2387.1 | F14: 2398.8 | G14: 2389 | H14: 2392 | I14: 2403.95 | J14: 3211 | K14: 2025 | L14: 5,33,971 | M14: 1,28,36,38,080.00 | N14: 27629 | O14: 45853 | P14: 45869 | Q14: 2593 | R14: 2616.2 | S14: 2582.4 | T14: 2605.5 | U14: 2607 | V14: 2605.5 | W14: 13,80,900 | X14: 3,59,20,55,310.00 | Y14: 3,59,20,55,310.00 | Z14: 1,77,68,700 | AA14: 56700 | AB14: 45877 | AC14: 45897 | AD14: XX | AE14: - | AF14: 2258.7 | AG14: 2266.7 | AH14: 2168 | AI14: 2181.7 | AJ14: 2180.5 | AK14: 2181.7 | AL14: 45,01,200 | AM14: 9,87,66,45,180.00 | AN14: 9,87,66,45,180.00 | AO14: 1,75,84,500 | AP14: -3,34,200 | AQ14: 45912 | AR14: 45930 | AS14: XX | AT14: - | AU14: 2420 | AV14: 2427.4 | AW14: 2394.6 | AX14: 2397.4 | AY14: 2397.6 | AZ14: 2397.4 | BA14: 12,93,600 | BB14: 3,11,72,84,880.00 | BC14: 3,11,72,84,880.00 | BD14: 1,45,17,300 | BE14: -47700
A15: 45911 | B15: EQ | C15: 2348 | D15: 2418.7 | E15: 2340.2 | F15: 2340.2 | G15: 2408 | H15: 2398.8 | I15: 2394.03 | J15: 3211 | K15: 2025 | L15: 21,11,888 | M15: 5,05,59,16,547.10 | N15: 91785 | O15: 45852 | P15: 45869 | Q15: 2566.6 | R15: 2616 | S15: 2553 | T15: 2591.3 | U15: 2587.3 | V15: 2591.3 | W15: 15,26,700 | X15: 3,95,36,26,050.00 | Y15: 3,95,36,26,050.00 | Z15: 1,77,12,000 | AA15: -1,06,200 | AB15: 45876 | AC15: 45897 | AD15: XX | AE15: - | AF15: 2301.7 | AG15: 2303 | AH15: 2206.7 | AI15: 2258.7 | AJ15: 2250.9 | AK15: 2258.7 | AL15: 38,48,400 | AM15: 8,67,72,92,850.00 | AN15: 8,67,72,92,850.00 | AO15: 1,79,18,700 | AP15: -28800 | AQ15: 45911 | AR15: 45930 | AS15: XX | AT15: - | AU15: 2352.9 | AV15: 2427.1 | AW15: 2351.9 | AX15: 2406.4 | AY15: 2413 | AZ15: 2406.4 | BA15: 40,97,100 | BB15: 9,83,19,08,850.00 | BC15: 9,83,19,08,850.00 | BD15: 1,45,65,000 | BE15: -4,21,500
A16: 45910 | B16: EQ | C16: 2330 | D16: 2345.9 | E16: 2325.1 | F16: 2311.6 | G16: 2340.8 | H16: 2340.2 | I16: 2337.73 | J16: 3211 | K16: 2025 | L16: 3,90,490 | M16: 91,28,61,255.60 | N16: 26122 | O16: 45849 | P16: 45869 | Q16: 2587.5 | R16: 2599 | S16: 2563.1 | T16: 2569 | U16: 2573.9 | V16: 2569 | W16: 10,62,900 | X16: 2,74,04,57,820.00 | Y16: 2,74,04,57,820.00 | Z16: 1,78,18,200 | AA16: -38400 | AB16: 45875 | AC16: 45897 | AD16: XX | AE16: - | AF16: 2333 | AG16: 2352.2 | AH16: 2301.1 | AI16: 2304.6 | AJ16: 2303.2 | AK16: 2304.6 | AL16: 18,19,800 | AM16: 4,22,19,70,230.00 | AN16: 4,22,19,70,230.00 | AO16: 1,79,47,500 | AP16: -1,39,800 | AQ16: 45910 | AR16: 45930 | AS16: XX | AT16: - | AU16: 2337.9 | AV16: 2358.1 | AW16: 2335 | AX16: 2351.9 | AY16: 2351.8 | AZ16: 2351.9 | BA16: 11,69,100 | BB16: 2,74,50,02,340.00 | BC16: 2,74,50,02,340.00 | BD16: 1,49,86,500 | BE16: -44100
A17: 45909 | B17: EQ | C17: 2320 | D17: 2325 | E17: 2297 | F17: 2310.9 | G17: 2313.8 | H17: 2311.6 | I17: 2312.02 | J17: 3211 | K17: 2025 | L17: 3,69,431 | M17: 85,41,30,058.50 | N17: 25802 | O17: 45848 | P17: 45869 | Q17: 2594.6 | R17: 2613.6 | S17: 2580.5 | T17: 2587.4 | U17: 2589.8 | V17: 2587.4 | W17: 8,83,200 | X17: 2,29,05,65,220.00 | Y17: 2,29,05,65,220.00 | Z17: 1,78,56,600 | AA17: -37800 | AB17: 45874 | AC17: 45897 | AD17: XX | AE17: - | AF17: 2372.2 | AG17: 2373.5 | AH17: 2321.2 | AI17: 2333 | AJ17: 2335.1 | AK17: 2333 | AL17: 15,18,600 | AM17: 3,55,19,61,930.00 | AN17: 3,55,19,61,930.00 | AO17: 1,80,87,300 | AP17: -5400 | AQ17: 45909 | AR17: 45930 | AS17: XX | AT17: - | AU17: 2335.6 | AV17: 2335.6 | AW17: 2305.2 | AX17: 2317.9 | AY17: 2320.8 | AZ17: 2317.9 | BA17: 7,61,100 | BB17: 1,76,57,75,250.00 | BC17: 1,76,57,75,250.00 | BD17: 1,50,30,600 | BE17: -
A18: 45908 | B18: EQ | C18: 2290 | D18: 2333.9 | E18: 2286 | F18: 2281.4 | G18: 2319 | H18: 2310.9 | I18: 2317.98 | J18: 3211 | K18: 2025 | L18: 5,42,811 | M18: 1,25,82,25,214.30 | N18: 33564 | O18: 45847 | P18: 45869 | Q18: 2601.5 | R18: 2618.6 | S18: 2576.4 | T18: 2591.4 | U18: 2594 | V18: 2591.4 | W18: 13,23,000 | X18: 3,43,37,97,480.00 | Y18: 3,43,37,97,480.00 | Z18: 1,78,94,400 | AA18: 1200 | AB18: 45873 | AC18: 45897 | AD18: XX | AE18: - | AF18: 2364.3 | AG18: 2383.8 | AH18: 2343.8 | AI18: 2372.1 | AJ18: 2373.5 | AK18: 2372.1 | AL18: 13,04,100 | AM18: 3,08,65,93,590.00 | AN18: 3,08,65,93,590.00 | AO18: 1,80,92,700 | AP18: -47400 | AQ18: 45908 | AR18: 45930 | AS18: XX | AT18: - | AU18: 2324 | AV18: 2345 | AW18: 2293.6 | AX18: 2323.9 | AY18: 2328.3 | AZ18: 2323.9 | BA18: 12,05,100 | BB18: 2,80,60,95,720.00 | BC18: 2,80,60,95,720.00 | BD18: 1,50,30,600 | BE18: -1,63,800
A19: 45905 | B19: EQ | C19: 2275 | D19: 2293.5 | E19: 2248 | F19: 2278.8 | G19: 2282.5 | H19: 2281.4 | I19: 2273.81 | J19: 3211 | K19: 2025 | L19: 4,43,010 | M19: 1,00,73,21,887.50 | N19: 28096 | O19: 45846 | P19: 45869 | Q19: 2589 | R19: 2609.8 | S19: 2581.2 | T19: 2605.1 | U19: 2601.5 | V19: 2605.1 | W19: 10,05,900 | X19: 2,61,31,92,930.00 | Y19: 2,61,31,92,930.00 | Z19: 1,78,93,200 | AA19: -20400 | AB19: 45870 | AC19: 45897 | AD19: XX | AE19: - | AF19: 2435.6 | AG19: 2455 | AH19: 2338.2 | AI19: 2356.4 | AJ19: 2339.7 | AK19: 2356.4 | AL19: 31,98,000 | AM19: 7,66,73,04,870.00 | AN19: 7,66,73,04,870.00 | AO19: 1,81,40,100 | AP19: 2,24,100 | AQ19: 45905 | AR19: 45930 | AS19: XX | AT19: - | AU19: 2279.3 | AV19: 2303.6 | AW19: 2254.8 | AX19: 2292.5 | AY19: 2295.1 | AZ19: 2292.5 | BA19: 10,71,600 | BB19: 2,44,64,58,060.00 | BC19: 2,44,64,58,060.00 | BD19: 1,51,94,400 | BE19: -72300
A20: 45904 | B20: EQ | C20: 2309.9 | D20: 2317.3 | E20: 2275 | F20: 2288.7 | G20: 2280 | H20: 2278.8 | I20: 2291.33 | J20: 3211 | K20: 2025 | L20: 3,92,697 | M20: 89,97,99,540.00 | N20: 29912 | O20: 45845 | P20: 45869 | Q20: 2606.2 | R20: 2613.6 | S20: 2583.8 | T20: 2588.9 | U20: 2592.7 | V20: 2588.9 | W20: 11,52,000 | X20: 2,98,86,23,940.00 | Y20: 2,98,86,23,940.00 | Z20: 1,79,13,600 | AA20: -68400 | AB20: 45869 | AC20: 45897 | AD20: XX | AE20: - | AF20: 2525.2 | AG20: 2529.9 | AH20: 2430 | AI20: 2440.1 | AJ20: 2438.6 | AK20: 2440.1 | AL20: 63,80,700 | AM20: 15,85,32,09,480.00 | AN20: 15,85,32,09,480.00 | AO20: 1,79,16,000 | AP20: 30,63,300 | AQ20: 45904 | AR20: 45930 | AS20: XX | AT20: - | AU20: 2310.3 | AV20: 2325.6 | AW20: 2282.3 | AX20: 2286.9 | AY20: 2293.5 | AZ20: 2286.9 | BA20: 9,39,900 | BB20: 2,16,19,38,240.00 | BC20: 2,16,19,38,240.00 | BD20: 1,52,66,700 | BE20: -81300
A21: 45903 | B21: EQ | C21: 2285 | D21: 2293 | E21: 2263.1 | F21: 2274.2 | G21: 2292 | H21: 2288.7 | I21: 2279.5 | J21: 3211 | K21: 2025 | L21: 4,43,629 | M21: 1,01,12,51,185.30 | N21: 28773 | O21: 45842 | P21: 45869 | Q21: 2626.5 | R21: 2627.6 | S21: 2590.3 | T21: 2609.6 | U21: 2608 | V21: 2609.6 | W21: 13,89,900 | X21: 3,62,37,08,880.00 | Y21: 3,62,37,08,880.00 | Z21: 1,79,82,000 | AA21: -1,37,700 | AB21: 45868 | AC21: 45897 | AD21: XX | AE21: - | AF21: 2560.1 | AG21: 2565 | AH21: 2538 | AI21: 2544.7 | AJ21: 2542 | AK21: 2544.7 | AL21: 45,88,200 | AM21: 11,71,90,96,650.00 | AN21: 11,71,90,96,650.00 | AO21: 1,48,52,700 | AP21: 37,28,700 | AQ21: 45903 | AR21: 45930 | AS21: XX | AT21: - | AU21: 2291.2 | AV21: 2305 | AW21: 2274.3 | AX21: 2300.5 | AY21: 2303.9 | AZ21: 2300.5 | BA21: 8,48,400 | BB21: 1,94,45,56,200.00 | BC21: 1,94,45,56,200.00 | BD21: 1,53,48,000 | BE21: -28200
A22: 45902 | B22: EQ | C22: 2291 | D22: 2302 | E22: 2264 | F22: 2284.2 | G22: 2278 | H22: 2274.2 | I22: 2283.41 | J22: 3211 | K22: 2025 | L22: 4,81,894 | M22: 1,10,03,61,913.10 | N22: 37899 | O22: 45841 | P22: 45869 | Q22: 2640.1 | R22: 2658.7 | S22: 2617.3 | T22: 2626.6 | U22: 2624.4 | V22: 2626.6 | W22: 13,79,100 | X22: 3,63,15,19,620.00 | Y22: 3,63,15,19,620.00 | Z22: 1,81,19,700 | AA22: -7200 | AB22: 45867 | AC22: 45897 | AD22: XX | AE22: - | AF22: 2546.8 | AG22: 2574.8 | AH22: 2520.1 | AI22: 2565.8 | AJ22: 2566.5 | AK22: 2565.8 | AL22: 55,68,300 | AM22: 14,17,48,48,140.00 | AN22: 14,17,48,48,140.00 | AO22: 1,11,24,000 | AP22: 46,61,700 | AQ22: 45902 | AR22: 45930 | AS22: XX | AT22: - | AU22: 2299.6 | AV22: 2315 | AW22: 2275.5 | AX22: 2284.1 | AY22: 2286.1 | AZ22: 2284.1 | BA22: 10,90,800 | BB22: 2,50,27,66,980.00 | BC22: 2,50,27,66,980.00 | BD22: 1,53,76,200 | BE22: 11700
A23: 45901 | B23: EQ | C23: 2259 | D23: 2288 | E23: 2252.1 | F23: 2244.7 | G23: 2286.6 | H23: 2284.2 | I23: 2274.83 | J23: 3211 | K23: 2025 | L23: 4,25,639 | M23: 96,82,57,145.60 | N23: 29502 | O23: 45840 | P23: 45869 | Q23: 2641.5 | R23: 2658.1 | S23: 2624 | T23: 2644.4 | U23: 2643.9 | V23: 2644.4 | W23: 17,48,700 | X23: 4,62,09,64,530.00 | Y23: 4,62,09,64,530.00 | Z23: 1,81,26,900 | AA23: -1,94,400 | AB23: 45866 | AC23: 45897 | AD23: XX | AE23: - | AF23: 2564.1 | AG23: 2602.2 | AH23: 2526.8 | AI23: 2538.3 | AJ23: 2538.2 | AK23: 2538.3 | AL23: 40,69,200 | AM23: 10,44,14,65,650.00 | AN23: 10,44,14,65,650.00 | AO23: 64,62,300 | AP23: 33,84,900 | AQ23: 45901 | AR23: 45930 | AS23: XX | AT23: - | AU23: 2274.6 | AV23: 2303.3 | AW23: 2262.6 | AX23: 2295.8 | AY23: 2294.5 | AZ23: 2295.8 | BA23: 8,97,600 | BB23: 2,05,48,66,920.00 | BC23: 2,05,48,66,920.00 | BD23: 1,53,64,500 | BE23: -93900
A24: 45898 | B24: EQ | C24: 2283 | D24: 2289.7 | E24: 2240 | F24: 2275.2 | G24: 2247.9 | H24: 2244.7 | I24: 2257.72 | J24: 3211 | K24: 2025 | L24: 7,95,699 | M24: 1,79,64,67,753.50 | N24: 50217 | O24: 45839 | P24: 45869 | Q24: 2632.9 | R24: 2654.8 | S24: 2615 | T24: 2631.7 | U24: 2633.7 | V24: 2631.7 | W24: 20,31,600 | X24: 5,35,18,31,550.00 | Y24: 5,35,18,31,550.00 | Z24: 1,83,21,300 | AA24: 30900 | AB24: 45863 | AC24: 45897 | AD24: XX | AE24: - | AF24: 2618.6 | AG24: 2636.6 | AH24: 2558.4 | AI24: 2563.8 | AJ24: 2562.1 | AK24: 2563.8 | AL24: 20,06,400 | AM24: 5,16,09,24,660.00 | AN24: 5,16,09,24,660.00 | AO24: 30,77,400 | AP24: 17,89,500 | AQ24: 45898 | AR24: 45930 | AS24: XX | AT24: - | AU24: 2287 | AV24: 2300.4 | AW24: 2254.3 | AX24: 2259.3 | AY24: 2262 | AZ24: 2259.3 | BA24: 12,21,600 | BB24: 2,77,65,57,900.00 | BC24: 2,77,65,57,900.00 | BD24: 1,54,58,400 | BE24: 1,99,800
A25: 45897 | B25: EQ | C25: 2271.9 | D25: 2327.9 | E25: 2255 | F25: 2272 | G25: 2282.1 | H25: 2275.2 | I25: 2295.19 | J25: 3211 | K25: 2025 | L25: 9,07,868 | M25: 2,08,37,29,401.30 | N25: 55327 | AB25: 45862 | AC25: 45897 | AD25: XX | AE25: - | AF25: 2626.6 | AG25: 2645 | AH25: 2613.9 | AI25: 2627.3 | AJ25: 2630.3 | AK25: 2627.3 | AL25: 5,75,100 | AM25: 1,51,02,96,660.00 | AN25: 1,51,02,96,660.00 | AO25: 12,87,900 | AP25: 3,78,000 | AQ25: 45897 | AR25: 45930 | AS25: XX | AT25: - | AU25: 2248.2 | AV25: 2337.8 | AW25: 2248.2 | AX25: 2287.1 | AY25: 2293.8 | AZ25: 2287.1 | BA25: 51,99,000 | BB25: 11,98,09,52,730.00 | BC25: 11,98,09,52,730.00 | BD25: 1,52,58,600 | BE25: 30,48,600
A26: 45895 | B26: EQ | C26: 2304 | D26: 2309.3 | E26: 2249.4 | F26: 2302.9 | G26: 2286 | H26: 2272 | I26: 2271.65 | J26: 3211 | K26: 2025 | L26: 10,71,550 | M26: 2,43,41,85,935.90 | N26: 49449 | AB26: 45861 | AC26: 45897 | AD26: XX | AE26: - | AF26: 2613.8 | AG26: 2645 | AH26: 2611.5 | AI26: 2636.5 | AJ26: 2636.8 | AK26: 2636.5 | AL26: 1,59,000 | AM26: 41,86,03,860.00 | AN26: 41,86,03,860.00 | AO26: 9,09,900 | AP26: 54600 | AQ26: 45895 | AR26: 45930 | AS26: XX | AT26: - | AU26: 2330.2 | AV26: 2330.2 | AW26: 2260 | AX26: 2281.2 | AY26: 2291.1 | AZ26: 2281.2 | BA26: 45,41,400 | BB26: 10,37,12,59,650.00 | BC26: 10,37,12,59,650.00 | BD26: 1,22,10,000 | BE26: 32,71,500
A27: 45894 | B27: EQ | C27: 2335.7 | D27: 2348.4 | E27: 2300 | F27: 2324.9 | G27: 2302.8 | H27: 2302.9 | I27: 2317.89 | J27: 3211 | K27: 2025 | L27: 5,42,455 | M27: 1,25,73,53,106.10 | N27: 28277 | AB27: 45860 | AC27: 45897 | AD27: XX | AE27: - | AF27: 2644.6 | AG27: 2646.8 | AH27: 2601 | AI27: 2608.2 | AJ27: 2611.1 | AK27: 2608.2 | AL27: 1,89,300 | AM27: 49,61,49,780.00 | AN27: 49,61,49,780.00 | AO27: 8,55,300 | AP27: 78900 | AQ27: 45894 | AR27: 45930 | AS27: XX | AT27: - | AU27: 2353 | AV27: 2362.3 | AW27: 2310.9 | AX27: 2314 | AY27: 2315.1 | AZ27: 2314 | BA27: 42,73,200 | BB27: 9,96,98,71,410.00 | BC27: 9,96,98,71,410.00 | BD27: 89,38,500 | BE27: 35,19,900
A28: 45891 | B28: EQ | C28: 2369.9 | D28: 2376.3 | E28: 2321 | F28: 2377.2 | G28: 2323 | H28: 2324.9 | I28: 2338.18 | J28: 3211 | K28: 2025 | L28: 5,84,211 | M28: 1,36,59,92,606.00 | N28: 34341 | AB28: 45859 | AC28: 45897 | AD28: XX | AE28: - | AF28: 2613.7 | AG28: 2643.9 | AH28: 2606 | AI28: 2639.5 | AJ28: 2639 | AK28: 2639.5 | AL28: 1,20,300 | AM28: 31,70,01,030.00 | AN28: 31,70,01,030.00 | AO28: 7,76,400 | AP28: 34500 | AQ28: 45891 | AR28: 45930 | AS28: XX | AT28: - | AU28: 2369.5 | AV28: 2390.1 | AW28: 2334.1 | AX28: 2336.5 | AY28: 2339 | AZ28: 2336.5 | BA28: 47,54,400 | BB28: 11,16,98,45,430.00 | BC28: 11,16,98,45,430.00 | BD28: 54,18,600 | BE28: 36,67,500
A29: 45890 | B29: EQ | C29: 2387.1 | D29: 2397 | E29: 2371.4 | F29: 2387.1 | G29: 2373 | H29: 2377.2 | I29: 2384.83 | J29: 3211 | K29: 2025 | L29: 4,41,867 | M29: 1,05,37,78,241.00 | N29: 24817 | AB29: 45856 | AC29: 45897 | AD29: XX | AE29: - | AF29: 2636.4 | AG29: 2649.5 | AH29: 2606 | AI29: 2618.9 | AJ29: 2619.9 | AK29: 2618.9 | AL29: 1,81,500 | AM29: 47,53,21,980.00 | AN29: 47,53,21,980.00 | AO29: 7,41,900 | AP29: 1,13,400 | AQ29: 45890 | AR29: 45930 | AS29: XX | AT29: - | AU29: 2401.7 | AV29: 2412 | AW29: 2386.4 | AX29: 2393.7 | AY29: 2391.6 | AZ29: 2393.7 | BA29: 9,38,100 | BB29: 2,25,03,91,440.00 | BC29: 2,25,03,91,440.00 | BD29: 17,51,100 | BE29: 7,40,700
A30: 45889 | B30: EQ | C30: 2380 | D30: 2406 | E30: 2372.1 | F30: 2388.4 | G30: 2391 | H30: 2387.1 | I30: 2389.93 | J30: 3211 | K30: 2025 | L30: 7,80,025 | M30: 1,86,42,08,978.30 | N30: 34030 | AB30: 45855 | AC30: 45897 | AD30: XX | AE30: - | AF30: 2628.9 | AG30: 2677 | AH30: 2624.8 | AI30: 2639.9 | AJ30: 2643.7 | AK30: 2639.9 | AL30: 2,88,900 | AM30: 76,72,98,750.00 | AN30: 76,72,98,750.00 | AO30: 6,28,500 | AP30: 1,37,100 | AQ30: 45889 | AR30: 45930 | AS30: XX | AT30: - | AU30: 2400 | AV30: 2420 | AW30: 2390 | AX30: 2400 | AY30: 2397.1 | AZ30: 2400 | BA30: 3,70,800 | BB30: 89,11,15,380.00 | BC30: 89,11,15,380.00 | BD30: 10,10,400 | BE30: 2,07,900
A31: 45888 | B31: EQ | C31: 2339.9 | D31: 2395.6 | E31: 2314.1 | F31: 2333.6 | G31: 2380.7 | H31: 2388.4 | I31: 2368.18 | J31: 3211 | K31: 2025 | L31: 10,69,432 | M31: 2,53,26,11,818.70 | N31: 58469 | AB31: 45854 | AC31: 45897 | AD31: XX | AE31: - | AF31: 2623.6 | AG31: 2644 | AH31: 2620 | AI31: 2630.9 | AJ31: 2633.4 | AK31: 2630.9 | AL31: 1,30,800 | AM31: 34,43,96,190.00 | AN31: 34,43,96,190.00 | AO31: 4,91,400 | AP31: 46800 | AQ31: 45888 | AR31: 45930 | AS31: XX | AT31: - | AU31: 2336.7 | AV31: 2409.8 | AW31: 2333 | AX31: 2402.3 | AY31: 2396.5 | AZ31: 2402.3 | BA31: 5,34,000 | BB31: 1,27,38,90,480.00 | BC31: 1,27,38,90,480.00 | BD31: 8,02,500 | BE31: 3,46,800
A32: 45887 | B32: EQ | C32: 2309.6 | D32: 2360 | E32: 2300 | F32: 2281.6 | G32: 2325.5 | H32: 2333.6 | I32: 2339.34 | J32: 3211 | K32: 2025 | L32: 9,88,629 | M32: 2,31,27,43,728.00 | N32: 45655 | AB32: 45853 | AC32: 45897 | AD32: XX | AE32: - | AF32: 2606.8 | AG32: 2629.7 | AH32: 2597 | AI32: 2618.5 | AJ32: 2620 | AK32: 2618.5 | AL32: 75900 | AM32: 19,85,60,700.00 | AN32: 19,85,60,700.00 | AO32: 4,44,600 | AP32: 33000 | AQ32: 45887 | AR32: 45930 | AS32: XX | AT32: - | AU32: 2319 | AV32: 2375.5 | AW32: 2319 | AX32: 2348.8 | AY32: 2341.2 | AZ32: 2348.8 | BA32: 1,96,500 | BB32: 46,24,67,940.00 | BC32: 46,24,67,940.00 | BD32: 4,55,700 | BE32: 38700
A33: 45883 | B33: EQ | C33: 2288 | D33: 2304 | E33: 2267.7 | F33: 2280.1 | G33: 2280.1 | H33: 2281.6 | I33: 2285.6 | J33: 3211 | K33: 2025 | L33: 9,98,109 | M33: 2,28,12,82,532.50 | N33: 39420 | AB33: 45852 | AC33: 45897 | AD33: XX | AE33: - | AF33: 2577.7 | AG33: 2627.4 | AH33: 2568 | AI33: 2605.3 | AJ33: 2605.3 | AK33: 2605.3 | AL33: 1,16,100 | AM33: 30,18,59,640.00 | AN33: 30,18,59,640.00 | AO33: 4,11,600 | AP33: 54900 | AQ33: 45883 | AR33: 45930 | AS33: XX | AT33: - | AU33: 2310 | AV33: 2320.2 | AW33: 2288 | AX33: 2295.6 | AY33: 2297.1 | AZ33: 2295.6 | BA33: 87000 | BB33: 20,00,98,050.00 | BC33: 20,00,98,050.00 | BD33: 4,17,000 | BE33: 39900
A34: 45882 | B34: EQ | C34: 2299 | D34: 2314.9 | E34: 2245.4 | F34: 2288.2 | G34: 2287 | H34: 2280.1 | I34: 2278.92 | J34: 3211 | K34: 2025 | L34: 8,33,679 | M34: 1,89,98,84,902.70 | N34: 42397 | AB34: 45849 | AC34: 45897 | AD34: XX | AE34: - | AF34: 2592.4 | AG34: 2611.1 | AH34: 2575.7 | AI34: 2580.2 | AJ34: 2581.5 | AK34: 2580.2 | AL34: 63600 | AM34: 16,46,64,990.00 | AN34: 16,46,64,990.00 | AO34: 3,56,700 | AP34: 14700 | AQ34: 45882 | AR34: 45930 | AS34: XX | AT34: - | AU34: 2328.2 | AV34: 2331.9 | AW34: 2262.6 | AX34: 2303.4 | AY34: 2306.6 | AZ34: 2303.4 | BA34: 90900 | BB34: 20,87,96,070.00 | BC34: 20,87,96,070.00 | BD34: 3,77,100 | BE34: 12000
A35: 45881 | B35: EQ | C35: 2280.1 | D35: 2314.7 | E35: 2267 | F35: 2283.4 | G35: 2294.5 | H35: 2288.2 | I35: 2290.14 | J35: 3211 | K35: 2025 | L35: 10,75,526 | M35: 2,46,31,07,533.50 | N35: 61725 | AB35: 45848 | AC35: 45897 | AD35: XX | AE35: - | AF35: 2605.3 | AG35: 2625 | AH35: 2596.5 | AI35: 2601.4 | AJ35: 2603.2 | AK35: 2601.4 | AL35: 43800 | AM35: 11,42,33,190.00 | AN35: 11,42,33,190.00 | AO35: 3,42,000 | AP35: 15300 | AQ35: 45881 | AR35: 45930 | AS35: XX | AT35: - | AU35: 2302.2 | AV35: 2330 | AW35: 2284 | AX35: 2307.6 | AY35: 2309 | AZ35: 2307.6 | BA35: 87600 | BB35: 20,21,01,420.00 | BC35: 20,21,01,420.00 | BD35: 3,65,100 | BE35: 15000
A36: 45880 | B36: EQ | C36: 2196 | D36: 2302 | E36: 2183 | F36: 2178.1 | G36: 2270.2 | H36: 2283.4 | I36: 2257.64 | J36: 3211 | K36: 2025 | L36: 23,76,286 | M36: 5,36,48,00,460.40 | N36: 1,18,272 | AB36: 45847 | AC36: 45897 | AD36: XX | AE36: - | AF36: 2620 | AG36: 2630 | AH36: 2591.6 | AI36: 2604.7 | AJ36: 2606.5 | AK36: 2604.7 | AL36: 60900 | AM36: 15,90,44,100.00 | AN36: 15,90,44,100.00 | AO36: 3,26,700 | AP36: 20100 | AQ36: 45880 | AR36: 45930 | AS36: XX | AT36: - | AU36: 2203.6 | AV36: 2323.5 | AW36: 2203.6 | AX36: 2309.7 | AY36: 2293.2 | AZ36: 2309.7 | BA36: 3,01,500 | BB36: 68,70,19,050.00 | BC36: 68,70,19,050.00 | BD36: 3,50,100 | BE36: 11400
A37: 45877 | B37: EQ | C37: 2247 | D37: 2260.9 | E37: 2164.8 | F37: 2249.8 | G37: 2179 | H37: 2178.1 | I37: 2185.27 | J37: 3242.65 | K37: 2025 | L37: 25,52,736 | M37: 5,57,84,04,691.30 | N37: 1,01,023 | AB37: 45846 | AC37: 45897 | AD37: XX | AE37: - | AF37: 2607.5 | AG37: 2622.3 | AH37: 2596.7 | AI37: 2618.8 | AJ37: 2614.6 | AK37: 2618.8 | AL37: 54300 | AM37: 14,17,56,420.00 | AN37: 14,17,56,420.00 | AO37: 3,06,600 | AP37: 18000 | AQ37: 45877 | AR37: 45930 | AS37: XX | AT37: - | AU37: 2260.6 | AV37: 2277.8 | AW37: 2183 | AX37: 2194.4 | AY37: 2196.7 | AZ37: 2194.4 | BA37: 1,67,700 | BB37: 37,02,66,870.00 | BC37: 37,02,66,870.00 | BD37: 3,38,700 | BE37: 63000
A38: 45876 | B38: EQ | C38: 2290 | D38: 2295 | E38: 2202.8 | F38: 2300.3 | G38: 2245.9 | H38: 2249.8 | I38: 2244.12 | J38: 3242.65 | K38: 2025 | L38: 15,29,410 | M38: 3,43,21,83,084.70 | N38: 72389 | AB38: 45845 | AC38: 45897 | AD38: XX | AE38: - | AF38: 2612.9 | AG38: 2622 | AH38: 2599.3 | AI38: 2601.8 | AJ38: 2603 | AK38: 2601.8 | AL38: 78900 | AM38: 20,54,92,620.00 | AN38: 20,54,92,620.00 | AO38: 2,88,600 | AP38: 39900 | AQ38: 45876 | AR38: 45930 | AS38: XX | AT38: - | AU38: 2307.6 | AV38: 2311 | AW38: 2220 | AX38: 2273.7 | AY38: 2263.4 | AZ38: 2273.7 | BA38: 1,60,500 | BB38: 36,34,29,990.00 | BC38: 36,34,29,990.00 | BD38: 2,75,700 | BE38: 37200
A39: 45875 | B39: EQ | C39: 2333.9 | D39: 2347.9 | E39: 2296 | F39: 2328.2 | G39: 2300 | H39: 2300.3 | I39: 2311.6 | J39: 3242.65 | K39: 2025 | L39: 6,31,582 | M39: 1,45,99,65,783.80 | N39: 35196 | AB39: 45842 | AC39: 45897 | AD39: XX | AE39: - | AF39: 2637.9 | AG39: 2641.3 | AH39: 2605.2 | AI39: 2622.9 | AJ39: 2625.2 | AK39: 2622.9 | AL39: 35400 | AM39: 9,28,84,980.00 | AN39: 9,28,84,980.00 | AO39: 2,48,700 | AP39: 900 | AQ39: 45875 | AR39: 45930 | AS39: XX | AT39: - | AU39: 2344.2 | AV39: 2364.4 | AW39: 2315.5 | AX39: 2318.3 | AY39: 2315.5 | AZ39: 2318.3 | BA39: 74100 | BB39: 17,24,94,240.00 | BC39: 17,24,94,240.00 | BD39: 2,38,500 | BE39: 21600
A40: 45874 | B40: EQ | C40: 2370 | D40: 2370 | E40: 2316 | F40: 2363.6 | G40: 2333 | H40: 2328.2 | I40: 2333.43 | J40: 3242.65 | K40: 2025 | L40: 5,76,742 | M40: 1,34,57,85,609.30 | N40: 36761 | AB40: 45841 | AC40: 45897 | AD40: XX | AE40: - | AF40: 2657.4 | AG40: 2672.7 | AH40: 2632.8 | AI40: 2640.1 | AJ40: 2636 | AK40: 2640.1 | AL40: 45600 | AM40: 12,08,46,900.00 | AN40: 12,08,46,900.00 | AO40: 2,47,800 | AP40: 15900 | AQ40: 45874 | AR40: 45930 | AS40: XX | AT40: - | AU40: 2381.2 | AV40: 2384 | AW40: 2340 | AX40: 2350.2 | AY40: 2349 | AZ40: 2350.2 | BA40: 65400 | BB40: 15,38,18,190.00 | BC40: 15,38,18,190.00 | BD40: 2,16,900 | BE40: 28800
A41: 45873 | B41: EQ | C41: 2360 | D41: 2374.7 | E41: 2338.2 | F41: 2350.9 | G41: 2364.7 | H41: 2363.6 | I41: 2358.52 | J41: 3242.65 | K41: 2025 | L41: 5,76,426 | M41: 1,35,95,14,762.40 | N41: 35680 | AB41: 45840 | AC41: 45897 | AD41: XX | AE41: - | AF41: 2651.6 | AG41: 2671.1 | AH41: 2640 | AI41: 2658.9 | AJ41: 2657.4 | AK41: 2658.9 | AL41: 58800 | AM41: 15,62,17,890.00 | AN41: 15,62,17,890.00 | AO41: 2,31,900 | AP41: 12900 | AQ41: 45873 | AR41: 45930 | AS41: XX | AT41: - | AU41: 2366.9 | AV41: 2397.9 | AW41: 2359 | AX41: 2385.7 | AY41: 2386.1 | AZ41: 2385.7 | BA41: 40500 | BB41: 9,63,57,420.00 | BC41: 9,63,57,420.00 | BD41: 1,88,100 | BE41: 5100
A42: 45870 | B42: EQ | C42: 2425 | D42: 2444.9 | E42: 2333 | F42: 2430.7 | G42: 2341.5 | H42: 2350.9 | I42: 2387.3 | J42: 3258 | K42: 2025 | L42: 9,76,341 | M42: 2,33,08,21,711.40 | N42: 50438 | AB42: 45839 | AC42: 45897 | AD42: XX | AE42: - | AF42: 2651.6 | AG42: 2668.8 | AH42: 2630.1 | AI42: 2647 | AJ42: 2647.4 | AK42: 2647 | AL42: 57300 | AM42: 15,18,27,540.00 | AN42: 15,18,27,540.00 | AO42: 2,19,000 | AP42: 7800 | AQ42: 45870 | AR42: 45930 | AS42: XX | AT42: - | AU42: 2440 | AV42: 2468.9 | AW42: 2355.4 | AX42: 2369.2 | AY42: 2355.4 | AZ42: 2369.2 | BA42: 1,07,100 | BB42: 25,78,30,260.00 | BC42: 25,78,30,260.00 | BD42: 1,83,000 | BE42: 13800
A43: 45869 | B43: EQ | C43: 2509.9 | D43: 2520 | E43: 2422.6 | F43: 2532.9 | G43: 2430 | H43: 2430.7 | I43: 2466.47 | J43: 3258 | K43: 2025 | L43: 14,57,616 | M43: 3,59,51,67,944.00 | N43: 74728 | AQ43: 45869 | AR43: 45930 | AS43: XX | AT43: - | AU43: 2542.8 | AV43: 2542.9 | AW43: 2447.7 | AX43: 2454.7 | AY43: 2459.4 | AZ43: 2454.7 | BA43: 1,38,000 | BB43: 34,39,33,530.00 | BC43: 34,39,33,530.00 | BD43: 1,69,200 | BE43: 37500
A44: 45868 | B44: EQ | C44: 2547.9 | D44: 2552.6 | E44: 2525 | F44: 2547.9 | G44: 2527 | H44: 2532.9 | I44: 2541.06 | J44: 3258 | K44: 2025 | L44: 2,62,063 | M44: 66,59,16,830.10 | N44: 22733 | AQ44: 45868 | AR44: 45930 | AS44: XX | AT44: - | AU44: 2575.2 | AV44: 2580.7 | AW44: 2559 | AX44: 2562.7 | AY44: 2561.7 | AZ44: 2562.7 | BA44: 60900 | BB44: 15,64,39,530.00 | BC44: 15,64,39,530.00 | BD44: 1,31,700 | BE44: 53100
A45: 45867 | B45: EQ | C45: 2529 | D45: 2557.4 | E45: 2507.5 | F45: 2522.3 | G45: 2545.5 | H45: 2547.9 | I45: 2534.72 | J45: 3258 | K45: 2025 | L45: 4,24,781 | M45: 1,07,67,00,049.20 | N45: 32528 | AQ45: 45867 | AR45: 45930 | AS45: XX | AT45: - | AU45: 2566 | AV45: 2589.7 | AW45: 2537.5 | AX45: 2578 | AY45: 2578 | AZ45: 2574.9 | BA45: 14400 | BB45: 3,69,17,490.00 | BC45: 3,69,17,490.00 | BD45: 78600 | BE45: 9600
A46: 45866 | B46: EQ | C46: 2549 | D46: 2585 | E46: 2512.6 | F46: 2550.1 | G46: 2528 | H46: 2522.3 | I46: 2545.55 | J46: 3258 | K46: 2025 | L46: 4,28,409 | M46: 1,09,05,36,114.10 | N46: 33834 | AQ46: 45866 | AR46: 45930 | AS46: XX | AT46: - | AU46: 2578.3 | AV46: 2616.9 | AW46: 2543.4 | AX46: 2555 | AY46: 2555.7 | AZ46: 2555 | BA46: 28800 | BB46: 7,40,71,470.00 | BC46: 7,40,71,470.00 | BD46: 69000 | BE46: 9600
A47: 45863 | B47: EQ | C47: 2605 | D47: 2617 | E47: 2544.1 | F47: 2608.4 | G47: 2549.5 | H47: 2550.1 | I47: 2568.46 | J47: 3258 | K47: 2025 | L47: 4,24,612 | M47: 1,09,05,98,540.70 | N47: 30247 | AQ47: 45863 | AR47: 45930 | AS47: XX | AT47: - | AU47: 2630.9 | AV47: 2650 | AW47: 2575 | AX47: 2577.2 | AY47: 2576 | AZ47: 2577.2 | BA47: 21300 | BB47: 5,54,00,910.00 | BC47: 5,54,00,910.00 | BD47: 59400 | BE47: 10200
A48: 45862 | B48: EQ | C48: 2615.4 | D48: 2624.2 | E48: 2595 | F48: 2614.5 | G48: 2608 | H48: 2608.4 | I48: 2607.65 | J48: 3258 | K48: 2025 | L48: 2,53,782 | M48: 66,17,75,799.00 | N48: 22026 | AQ48: 45862 | AR48: 45930 | AS48: XX | AT48: - | AU48: 2657.7 | AV48: 2658.9 | AW48: 2632 | AX48: 2641.1 | AY48: 2641.1 | AZ48: 2641.1 | BA48: 7500 | BB48: 1,98,35,910.00 | BC48: 1,98,35,910.00 | BD48: 49200 | BE48: 3600
A49: 45861 | B49: EQ | C49: 2600.7 | D49: 2625.9 | E49: 2593.5 | F49: 2587.8 | G49: 2615.5 | H49: 2614.5 | I49: 2612.73 | J49: 3258 | K49: 2025 | L49: 3,16,424 | M49: 82,67,31,600.80 | N49: 24447 | AQ49: 45861 | AR49: 45930 | AS49: XX | AT49: - | AU49: 2641.1 | AV49: 2654.1 | AW49: 2641.1 | AX49: 2651.2 | AY49: 2650 | AZ49: 2651.2 | BA49: 5700 | BB49: 1,50,86,970.00 | BC49: 1,50,86,970.00 | BD49: 45600 | BE49: 2700
A50: 45860 | B50: EQ | C50: 2626 | D50: 2630 | E50: 2581.6 | F50: 2619.5 | G50: 2593.9 | H50: 2587.8 | I50: 2599.99 | J50: 3258 | K50: 2025 | L50: 3,87,055 | M50: 1,00,63,40,863.60 | N50: 25897 | AQ50: 45860 | AR50: 45930 | AS50: XX | AT50: - | AU50: 2645 | AV50: 2652 | AW50: 2618 | AX50: 2621.2 | AY50: 2624.5 | AZ50: 2621.2 | BA50: 6300 | BB50: 1,65,96,000.00 | BC50: 1,65,96,000.00 | BD50: 42900 | BE50: 4200
A51: 45859 | B51: EQ | C51: 2596.3 | D51: 2624.9 | E51: 2585 | F51: 2596.1 | G51: 2615.7 | H51: 2619.5 | I51: 2612.22 | J51: 3258 | K51: 2025 | L51: 3,69,782 | M51: 96,59,53,134.90 | N51: 28077 | AQ51: 45859 | AR51: 45930 | AS51: XX | AT51: - | AU51: 2640 | AV51: 2648 | AW51: 2640 | AX51: 2645 | AY51: 2645 | AZ51: 2650.6 | BA51: 1800 | BB51: 47,60,490.00 | BC51: 47,60,490.00 | BD51: 38700 | BE51: 300
A52: 45856 | B52: EQ | C52: 2612 | D52: 2626.7 | E52: 2584.2 | F52: 2616.6 | G52: 2594.2 | H52: 2596.1 | I52: 2599.8 | J52: 3258 | K52: 2025 | L52: 4,79,942 | M52: 1,24,77,52,864.90 | N52: 32389 | AQ52: 45856 | AR52: 45930 | AS52: XX | AT52: - | AU52: 2656 | AV52: 2656 | AW52: 2620.9 | AX52: 2635 | AY52: 2635 | AZ52: 2635 | BA52: 4200 | BB52: 1,10,77,170.00 | BC52: 1,10,77,170.00 | BD52: 38400 | BE52: 2700
A53: 45855 | B53: EQ | C53: 2612 | D53: 2654.5 | E53: 2605.3 | F53: 2608.5 | G53: 2614.9 | H53: 2616.6 | I53: 2628.55 | J53: 3258 | K53: 2025 | L53: 7,85,771 | M53: 2,06,54,38,554.40 | N53: 43962 | AQ53: 45855 | AR53: 45930 | AS53: XX | AT53: - | AU53: 2655 | AV53: 2690 | AW53: 2653.6 | AX53: 2656.9 | AY53: 2657 | AZ53: 2656.9 | BA53: 10200 | BB53: 2,72,36,340.00 | BC53: 2,72,36,340.00 | BD53: 35700 | BE53: 4500
A54: 45854 | B54: EQ | C54: 2602.5 | D54: 2619.5 | E54: 2595.5 | F54: 2598.2 | G54: 2608.2 | H54: 2608.5 | I54: 2610.55 | J54: 3258 | K54: 2025 | L54: 6,86,644 | M54: 1,79,25,15,079.70 | N54: 37057 | AQ54: 45854 | AR54: 45930 | AS54: XX | AT54: - | AU54: 2645.1 | AV54: 2651.2 | AW54: 2632.6 | AX54: 2646.7 | AY54: 2646.7 | AZ54: 2646.7 | BA54: 4500 | BB54: 1,19,10,570.00 | BC54: 1,19,10,570.00 | BD54: 31200 | BE54: 600
A55: 45853 | B55: EQ | C55: 2588 | D55: 2606.9 | E55: 2576 | F55: 2581.3 | G55: 2603.1 | H55: 2598.2 | I55: 2593.15 | J55: 3258 | K55: 2025 | L55: 3,79,425 | M55: 98,39,07,052.20 | N55: 24377 | AQ55: 45853 | AR55: 45930 | AS55: XX | AT55: - | AU55: 2622.7 | AV55: 2644 | AW55: 2622.7 | AX55: 2630.8 | AY55: 2630.8 | AZ55: 2630.8 | BA55: 5100 | BB55: 1,34,14,740.00 | BC55: 1,34,14,740.00 | BD55: 30600 | BE55: 2400
A56: 45852 | B56: EQ | C56: 2555 | D56: 2604.8 | E56: 2543.5 | F56: 2558.7 | G56: 2578 | H56: 2581.3 | I56: 2576.63 | J56: 3258 | K56: 2025 | L56: 5,36,585 | M56: 1,38,25,79,729.90 | N56: 34764 | AQ56: 45852 | AR56: 45930 | AS56: XX | AT56: - | AU56: 2599 | AV56: 2642 | AW56: 2594.5 | AX56: 2626 | AY56: 2626 | AZ56: 2615.2 | BA56: 4500 | BB56: 1,17,70,380.00 | BC56: 1,17,70,380.00 | BD56: 28200 | BE56: 1800
... A59: 45847 | B59: EQ | C59: 2599 | D59: 2609.9 | E59: 2570 | F59: 2591.3 | G59: 2582.3 | H59: 2583 | I59: 2588.47 | J59: 3258 | K59: 2025 | L59: 3,96,880 | M59: 1,02,73,13,944.80 | N59: 25511 | AQ59: 45847 | AR59: 45930 | AS59: XX | AT59: - | AU59: 2634.4 | AV59: 2645.9 | AW59: 2615 | AX59: 2616.3 | AY59: 2616.3 | AZ59: 2619 | BA59: 7500 | BB59: 1,96,65,570.00 | BC59: 1,96,65,570.00 | BD59: 28500 | BE59: 6600
A60: 45846 | B60: EQ | C60: 2586 | D60: 2600 | E60: 2573 | F60: 2576.1 | G60: 2588 | H60: 2591.3 | I60: 2585.46 | J60: 3258 | K60: 2025 | L60: 3,57,701 | M60: 92,48,20,759.70 | N60: 24369 | AQ60: 45846 | AR60: 45930 | AS60: XX | AT60: - | AU60: 2626.6 | AV60: 2637 | AW60: 2626.6 | AX60: 2635.6 | AY60: 2637 | AZ60: 2635.6 | BA60: 1200 | BB60: 31,59,960.00 | BC60: 31,59,960.00 | BD60: 21900 | BE60: -
A61: 45845 | B61: EQ | C61: 2602 | D61: 2605.4 | E61: 2572 | F61: 2599.1 | G61: 2587.6 | H61: 2576.1 | I61: 2582.98 | J61: 3258 | K61: 2025 | L61: 4,12,159 | M61: 1,06,45,98,371.00 | N61: 30384 | AQ61: 45845 | AR61: 45930 | AS61: XX | AT61: - | AU61: 2638.5 | AV61: 2638.5 | AW61: 2615.5 | AX61: 2617.4 | AY61: 2619.3 | AZ61: 2617.4 | BA61: 5400 | BB61: 1,41,50,490.00 | BC61: 1,41,50,490.00 | BD61: 21900 | BE61: 900
A62: 45842 | B62: EQ | C62: 2617 | D62: 2617 | E62: 2582.2 | F62: 2611.2 | G62: 2599 | H62: 2599.1 | I62: 2599.15 | J62: 3258 | K62: 2025 | L62: 3,70,305 | M62: 96,24,78,336.90 | N62: 25138 | AQ62: 45842 | AR62: 45930 | AS62: XX | AT62: - | AU62: 2647 | AV62: 2647 | AW62: 2626.3 | AX62: 2638.5 | AY62: 2638.5 | AZ62: 2638.5 | BA62: 3000 | BB62: 79,22,010.00 | BC62: 79,22,010.00 | BD62: 21000 | BE62: 300
A63: 45841 | B63: EQ | C63: 2634 | D63: 2644 | E63: 2605.1 | F63: 2630.2 | G63: 2608 | H63: 2611.2 | I63: 2618.1 | J63: 3258 | K63: 2025 | L63: 5,02,724 | M63: 1,31,61,81,025.70 | N63: 29883 | AQ63: 45841 | AR63: 45930 | AS63: XX | AT63: - | AU63: 2653.4 | AV63: 2684.3 | AW63: 2653.4 | AX63: 2668 | AY63: 2668 | AZ63: 2650.5 | BA63: 3600 | BB63: 96,35,640.00 | BC63: 96,35,640.00 | BD63: 20700 | BE63: 2100
A64: 45840 | B64: EQ | C64: 2634 | D64: 2646 | E64: 2613.6 | F64: 2621.8 | G64: 2629 | H64: 2630.2 | I64: 2630.67 | J64: 3258 | K64: 2025 | L64: 6,21,409 | M64: 1,63,47,20,496.70 | N64: 34383 | AQ64: 45840 | AR64: 45930 | AS64: XX | AT64: - | AU64: 2667.6 | AV64: 2689.7 | AW64: 2663.2 | AX64: 2673.4 | AY64: 2673.4 | AZ64: 2673.4 | BA64: 5400 | BB64: 1,44,85,470.00 | BC64: 1,44,85,470.00 | BD64: 18600 | BE64: 3000
A65: 45839 | B65: EQ | C65: 2624.9 | D65: 2645 | E65: 2603 | F65: 2619.4 | G65: 2626 | H65: 2621.8 | I65: 2625.01 | J65: 3258 | K65: 2025 | L65: 7,29,197 | M65: 1,91,41,51,988.60 | N65: 37539 | AQ65: 45839 | AR65: 45930 | AS65: XX | AT65: - | AU65: 2679.7 | AV65: 2681 | AW65: 2646.5 | AX65: 2664.9 | AY65: 2667.6 | AZ65: 2664.9 | BA65: 8100 | BB65: 2,15,96,280.00 | BC65: 2,15,96,280.00 | BD65: 15600 | BE65: 6000
